Workbook
Name JR_PAGE_ANCHOR_0_1: 'Rincian Pesanan Penjualan'!$A$1
Name Slicer_Brand: #N/A
Name Slicer_Divisi: #N/A
Name Slicer_Promo_ID: #N/A
Name Slicer_SALES: #N/A
Name Slicer_Tanggal: #N/A

Sheet DATA MASTER
A1: No. | B1: Brand | C1: Description | D1: Divisi | E1: Kemasan | F1: Gross Weight | G1: Coli Qty. | H1: Base Unit of Measure | I1: Price RTL | J1: sellprice | K1: Price RTL (2025) | L1: sellprice( 2025) | M1: Price RTL ( Agus 2025) | N1: sellprice( Agus 2025) | O1: Price RTL ( April 2026) | P1: sellprice( April 2026) | Q1: Price RTL ( Mei 2026) | R1: sellprice(Mei 2026)
A2: ABEM001K701 | B2: =LEFT(A2,7) -> ABEM001 | C2: ARIES BLING 701 1 KG | D2: DIV 1 | E2: 1 KG | F2: 1.05 | G2: 24 | H2: DS | O2: 28000 | P2: 31900 | Q2: 29400 | R2: 33400
A3: ABEM001K702 | B3: =LEFT(A3,7) -> ABEM001 | C3: ARIES BLING 702 1 KG | D3: DIV 1 | E3: 1 KG | F3: 1.05 | G3: 24 | H3: DS | O3: 28000 | P3: 31900 | Q3: 29400 | R3: 33400
A4: ABEM001K703 | B4: =LEFT(A4,7) -> ABEM001 | C4: ARIES BLING 703 1 KG | D4: DIV 1 | E4: 1 KG | F4: 1.05 | G4: 24 | H4: DS | O4: 28000 | P4: 31900 | Q4: 29400 | R4: 33400
A5: ABEM001K704 | B5: =LEFT(A5,7) -> ABEM001 | C5: ARIES BLING 704 1 KG | D5: DIV 1 | E5: 1 KG | F5: 1.05 | G5: 24 | H5: DS | O5: 28000 | P5: 31900 | Q5: 29400 | R5: 33400
A6: ABEM001K705 | B6: =LEFT(A6,7) -> ABEM001 | C6: ARIES BLING 705 1 KG | D6: DIV 1 | E6: 1 KG | F6: 1.05 | G6: 24 | H6: DS | O6: 28000 | P6: 31900 | Q6: 29400 | R6: 33400
A7: ABEM001K706 | B7: =LEFT(A7,7) -> ABEM001 | C7: ARIES BLING 706 1 KG | D7: DIV 1 | E7: 1 KG | F7: 1.05 | G7: 24 | H7: DS | O7: 28000 | P7: 31900 | Q7: 29400 | R7: 33400
A8: ABEM001K707 | B8: =LEFT(A8,7) -> ABEM001 | C8: ARIES BLING 707 1 KG | D8: DIV 1 | E8: 1 KG | F8: 1.05 | G8: 24 | H8: DS | O8: 28000 | P8: 31900 | Q8: 29400 | R8: 33400
A9: ABEM001K708 | B9: =LEFT(A9,7) -> ABEM001 | C9: ARIES BLING 708 1 KG | D9: DIV 1 | E9: 1 KG | F9: 1.05 | G9: 24 | H9: DS | O9: 28000 | P9: 31900 | Q9: 29400 | R9: 33400
A10: ABEM001K709 | B10: =LEFT(A10,7) -> ABEM001 | C10: ARIES BLING 709 1 KG | D10: DIV 1 | E10: 1 KG | F10: 1.05 | G10: 24 | H10: DS | O10: 28000 | P10: 31900 | Q10: 29400 | R10: 33400
A11: ABEM001K710 | B11: =LEFT(A11,7) -> ABEM001 | C11: ARIES BLING 710 1 KG | D11: DIV 1 | E11: 1 KG | F11: 1.05 | G11: 24 | H11: DS | O11: 28000 | P11: 31900 | Q11: 29400 | R11: 33400
A12: ABEM001K711 | B12: =LEFT(A12,7) -> ABEM001 | C12: ARIES BLING 711 1 KG | D12: DIV 1 | E12: 1 KG | F12: 1.05 | G12: 24 | H12: DS | O12: 28000 | P12: 31900 | Q12: 29400 | R12: 33400
A13: ABEM001K712 | B13: =LEFT(A13,7) -> ABEM001 | C13: ARIES BLING 712 1 KG | D13: DIV 1 | E13: 1 KG | F13: 1.05 | G13: 24 | H13: DS | O13: 28000 | P13: 31900 | Q13: 29400 | R13: 33400
... A25: ABEM001K724 | B25: =LEFT(A25,7) -> ABEM001 | C25: ARIES BLING 724 1 KG | D25: DIV 1 | E25: 1 KG | F25: 1.05 | G25: 24 | H25: DS | O25: 28000 | P25: 31900 | Q25: 29400 | R25: 33400
A26: ABEM001K725 | B26: ABEM001K725 | C26: ARIES BLING 725 1 KG | D26: DIV 1 | E26: 1 KG | F26: 1.05 | G26: 24 | H26: DS | O26: 28000 | P26: 31900 | Q26: 29400 | R26: 33400
A27: ABEM001K726 | B27: =LEFT(A27,7) -> ABEM001 | C27: ARIES BLING 726 1 KG | D27: DIV 1 | E27: 1 KG | F27: 1.05 | G27: 24 | H27: DS | O27: 28000 | P27: 31900 | Q27: 29400 | R27: 33400
A28: ABEM001KBA | B28: ABEM001KBA | C28: Aries Bling Emulsion Base A 1 Kg | D28: MTAB | E28: 1 KG | F28: 1.05 | G28: 24 | H28: DS | O28: 28000 | P28: 30100 | Q28: 29400 | R28: 31500
A29: ABEM001KBC | B29: ABEM001KBC | C29: Aries Bling Emulsion Base C 1 Kg | D29: MTAB | E29: 1 KG | F29: 1.05 | G29: 24 | H29: DS | O29: 25800 | P29: 27900 | Q29: 27000 | R29: 29100
A30: ABEM001KSB | B30: =LEFT(A30,7) -> ABEM001 | C30: ARIES BLING SB 1 KG | D30: DIV 1 | E30: 1 KG | F30: 1.05 | G30: 24 | H30: DS | O30: 28000 | P30: 31900 | Q30: 29400 | R30: 33400
A31: ABEM001KSW | B31: ABEM001KSW | C31: Aries Bling Emulsion SW 1 Kg | D31: DIV 1 | E31: 1 KG | F31: 1.05 | G31: 24 | H31: DS | O31: 28000 | P31: 31900 | Q31: 29400 | R31: 33400
A32: ABEM005K701 | B32: =LEFT(A32,7) -> ABEM005 | C32: Aries Bling Emulsion 701 | D32: DIV 2 | E32: 4.5 KG | F32: 4.74 | G32: 4 | H32: DS | I32: 65300 | J32: 79900 | K32: 67600 | L32: 82400 | M32: 69000 | N32: 82400 | O32: 80000 | P32: 94700 | Q32: 84000 | R32: 99000
A33: ABEM005K702 | B33: =LEFT(A33,7) -> ABEM005 | C33: Aries Bling Emulsion 702 | D33: DIV 2 | E33: 4.5 KG | F33: 4.74 | G33: 4 | H33: DS | I33: 65300 | J33: 79900 | K33: 67600 | L33: 82400 | M33: 69000 | N33: 82400 | O33: 80000 | P33: 94700 | Q33: 84000 | R33: 99000
A34: ABEM005K703 | B34: =LEFT(A34,7) -> ABEM005 | C34: Aries Bling Emulsion 703 | D34: DIV 2 | E34: 4.5 KG | F34: 4.74 | G34: 4 | H34: DS | I34: 65300 | J34: 79900 | K34: 67600 | L34: 82400 | M34: 69000 | N34: 82400 | O34: 80000 | P34: 94700 | Q34: 84000 | R34: 99000
A35: ABEM005K704 | B35: =LEFT(A35,7) -> ABEM005 | C35: Aries Bling Emulsion 704 | D35: DIV 2 | E35: 4.5 KG | F35: 4.74 | G35: 4 | H35: DS | I35: 65300 | J35: 79900 | K35: 67600 | L35: 82400 | M35: 69000 | N35: 82400 | O35: 80000 | P35: 94700 | Q35: 84000 | R35: 99000
A36: ABEM005K705 | B36: =LEFT(A36,7) -> ABEM005 | C36: Aries Bling Emulsion 705 | D36: DIV 2 | E36: 4.5 KG | F36: 4.74 | G36: 4 | H36: DS | I36: 65300 | J36: 79900 | K36: 67600 | L36: 82400 | M36: 69000 | N36: 82400 | O36: 80000 | P36: 94700 | Q36: 84000 | R36: 99000
A37: ABEM005K706 | B37: =LEFT(A37,7) -> ABEM005 | C37: Aries Bling Emulsion 706 | D37: DIV 2 | E37: 4.5 KG | F37: 4.74 | G37: 4 | H37: DS | I37: 65300 | J37: 79900 | K37: 67600 | L37: 82400 | M37: 69000 | N37: 82400 | O37: 80000 | P37: 94700 | Q37: 84000 | R37: 99000
A38: ABEM005K707 | B38: =LEFT(A38,7) -> ABEM005 | C38: Aries Bling Emulsion 707 | D38: DIV 2 | E38: 4.5 KG | F38: 4.74 | G38: 4 | H38: DS | I38: 65300 | J38: 79900 | K38: 67600 | L38: 82400 | M38: 69000 | N38: 82400 | O38: 80000 | P38: 94700 | Q38: 84000 | R38: 99000
A39: ABEM005K708 | B39: =LEFT(A39,7) -> ABEM005 | C39: Aries Bling Emulsion 708 | D39: DIV 2 | E39: 4.5 KG | F39: 4.74 | G39: 4 | H39: DS | I39: 65300 | J39: 79900 | K39: 67600 | L39: 82400 | M39: 69000 | N39: 82400 | O39: 80000 | P39: 94700 | Q39: 84000 | R39: 99000
A40: ABEM005K709 | B40: =LEFT(A40,7) -> ABEM005 | C40: Aries Bling Emulsion 709 | D40: DIV 2 | E40: 4.5 KG | F40: 4.74 | G40: 4 | H40: DS | I40: 65300 | J40: 79900 | K40: 67600 | L40: 82400 | M40: 69000 | N40: 82400 | O40: 80000 | P40: 94700 | Q40: 84000 | R40: 99000
A41: ABEM005K710 | B41: =LEFT(A41,7) -> ABEM005 | C41: Aries Bling Emulsion 710 | D41: DIV 2 | E41: 4.5 KG | F41: 4.74 | G41: 4 | H41: DS | I41: 65300 | J41: 79900 | K41: 67600 | L41: 82400 | M41: 69000 | N41: 82400 | O41: 80000 | P41: 94700 | Q41: 84000 | R41: 99000
A42: ABEM005K711 | B42: =LEFT(A42,7) -> ABEM005 | C42: Aries Bling Emulsion 711 | D42: DIV 2 | E42: 4.5 KG | F42: 4.74 | G42: 4 | H42: DS | I42: 65300 | J42: 79900 | K42: 67600 | L42: 82400 | M42: 69000 | N42: 82400 | O42: 80000 | P42: 94700 | Q42: 84000 | R42: 99000
A43: ABEM005K712 | B43: =LEFT(A43,7) -> ABEM005 | C43: Aries Bling Emulsion 712 | D43: DIV 2 | E43: 4.5 KG | F43: 4.74 | G43: 4 | H43: DS | I43: 65300 | J43: 79900 | K43: 67600 | L43: 82400 | M43: 69000 | N43: 82400 | O43: 80000 | P43: 94700 | Q43: 84000 | R43: 99000
... A55: ABEM005K724 | B55: =LEFT(A55,7) -> ABEM005 | C55: Aries Bling Emulsion 724 | D55: DIV 2 | E55: 4.5 KG | F55: 4.74 | G55: 4 | H55: DS | I55: 65300 | J55: 79900 | K55: 67600 | L55: 82400 | M55: 69000 | N55: 82400 | O55: 80000 | P55: 94700 | Q55: 84000 | R55: 99000
A56: ABEM005K725 | B56: ABEM005K725 | C56: Aries Bling Emulsion 725 | D56: DIV 2 | E56: 4.5 KG | F56: 4.74 | G56: 4 | H56: DS | I56: 65300 | J56: 79900 | K56: 67600 | L56: 82400 | M56: 69000 | N56: 82400 | O56: 80000 | P56: 94700 | Q56: 84000 | R56: 99000
A57: ABEM005K726 | B57: =LEFT(A57,7) -> ABEM005 | C57: Aries Bling Emulsion 726 | D57: DIV 2 | E57: 4.5 KG | F57: 4.74 | G57: 4 | H57: DS | I57: 65300 | J57: 79900 | K57: 67600 | L57: 82400 | M57: 69000 | N57: 82400 | O57: 80000 | P57: 94700 | Q57: 84000 | R57: 99000
A58: ABEM005KSB | B58: =LEFT(A58,7) -> ABEM005 | C58: Aries Bling Emulsion SB | D58: DIV 2 | E58: 4.5 KG | F58: 4.74 | G58: 4 | H58: DS | I58: 65300 | J58: 79900 | K58: 67600 | L58: 82400 | M58: 69000 | N58: 82400 | O58: 80000 | P58: 94700 | Q58: 84000 | R58: 99000
A59: ABEM005KSW | B59: ABEM005KSW | C59: Aries Bling Emulsion SW | D59: DIV 2 | E59: 4.5 KG | F59: 4.74 | G59: 4 | H59: DS | I59: 65300 | J59: 79900 | K59: 67600 | L59: 82400 | M59: 69000 | N59: 82400 | O59: 80000 | P59: 94700 | Q59: 84000 | R59: 99000
A60: ABEM005KBA | B60: ABEM005KBA | C60: Aries Bling Emulsion Base A 5 Kg | D60: MTAB | E60: 4 KG | F60: 4.13 | G60: 4 | H60: DS | O60: 80000 | P60: 89600 | Q60: 84000 | R60: 93600
A61: ABEM005KBC | B61: ABEM005KBC | C61: Aries Bling Emulsion Base C 5 Kg | D61: MTAB | E61: 4 KG | F61: 4.13 | G61: 4 | H61: DS | O61: 73600 | P61: 83200 | Q61: 77300 | R61: 86900
A62: ABEM020KP701 | B62: =LEFT(A62,7) -> ABEM020 | C62: Aries Bling Emulsion 701 | D62: DIV 2 | E62: 20 KG | F62: 19.01 | G62: 1 | H62: PL | I62: 251000 | J62: 308300 | K62: 259800 | L62: 317800 | M62: 265000 | N62: 317800 | O62: 307400 | P62: 365300 | Q62: 322800 | R62: 381600
A63: ABEM020KP702 | B63: =LEFT(A63,7) -> ABEM020 | C63: Aries Bling Emulsion 702 | D63: DIV 2 | E63: 20 KG | F63: 19.01 | G63: 1 | H63: PL | I63: 251000 | J63: 308300 | K63: 259800 | L63: 317800 | M63: 265000 | N63: 317800 | O63: 307400 | P63: 365300 | Q63: 322800 | R63: 381600
A64: ABEM020KP703 | B64: =LEFT(A64,7) -> ABEM020 | C64: Aries Bling Emulsion 703 | D64: DIV 2 | E64: 20 KG | F64: 19.01 | G64: 1 | H64: PL | I64: 251000 | J64: 308300 | K64: 259800 | L64: 317800 | M64: 265000 | N64: 317800 | O64: 307400 | P64: 365300 | Q64: 322800 | R64: 381600
A65: ABEM020KP704 | B65: =LEFT(A65,7) -> ABEM020 | C65: Aries Bling Emulsion 704 | D65: DIV 2 | E65: 20 KG | F65: 19.01 | G65: 1 | H65: PL | I65: 251000 | J65: 308300 | K65: 259800 | L65: 317800 | M65: 265000 | N65: 317800 | O65: 307400 | P65: 365300 | Q65: 322800 | R65: 381600
A66: ABEM020KP705 | B66: =LEFT(A66,7) -> ABEM020 | C66: Aries Bling Emulsion 705 | D66: DIV 2 | E66: 20 KG | F66: 19.01 | G66: 1 | H66: PL | I66: 251000 | J66: 308300 | K66: 259800 | L66: 317800 | M66: 265000 | N66: 317800 | O66: 307400 | P66: 365300 | Q66: 322800 | R66: 381600
A67: ABEM020KP706 | B67: =LEFT(A67,7) -> ABEM020 | C67: Aries Bling Emulsion 706 | D67: DIV 2 | E67: 20 KG | F67: 19.01 | G67: 1 | H67: PL | I67: 251000 | J67: 308300 | K67: 259800 | L67: 317800 | M67: 265000 | N67: 317800 | O67: 307400 | P67: 365300 | Q67: 322800 | R67: 381600
A68: ABEM020KP707 | B68: =LEFT(A68,7) -> ABEM020 | C68: Aries Bling Emulsion 707 | D68: DIV 2 | E68: 20 KG | F68: 19.01 | G68: 1 | H68: PL | I68: 251000 | J68: 308300 | K68: 259800 | L68: 317800 | M68: 265000 | N68: 317800 | O68: 307400 | P68: 365300 | Q68: 322800 | R68: 381600
A69: ABEM020KP708 | B69: =LEFT(A69,7) -> ABEM020 | C69: Aries Bling Emulsion 708 | D69: DIV 2 | E69: 20 KG | F69: 19.01 | G69: 1 | H69: PL | I69: 251000 | J69: 308300 | K69: 259800 | L69: 317800 | M69: 265000 | N69: 317800 | O69: 307400 | P69: 365300 | Q69: 322800 | R69: 381600
A70: ABEM020KP709 | B70: =LEFT(A70,7) -> ABEM020 | C70: Aries Bling Emulsion 709 | D70: DIV 2 | E70: 20 KG | F70: 19.01 | G70: 1 | H70: PL | I70: 251000 | J70: 308300 | K70: 259800 | L70: 317800 | M70: 265000 | N70: 317800 | O70: 307400 | P70: 365300 | Q70: 322800 | R70: 381600
A71: ABEM020KP710 | B71: =LEFT(A71,7) -> ABEM020 | C71: Aries Bling Emulsion 710 | D71: DIV 2 | E71: 20 KG | F71: 19.01 | G71: 1 | H71: PL | I71: 251000 | J71: 308300 | K71: 259800 | L71: 317800 | M71: 265000 | N71: 317800 | O71: 307400 | P71: 365300 | Q71: 322800 | R71: 381600
A72: ABEM020KP711 | B72: =LEFT(A72,7) -> ABEM020 | C72: Aries Bling Emulsion 711 | D72: DIV 2 | E72: 20 KG | F72: 19.01 | G72: 1 | H72: PL | I72: 251000 | J72: 308300 | K72: 259800 | L72: 317800 | M72: 265000 | N72: 317800 | O72: 307400 | P72: 365300 | Q72: 322800 | R72: 381600
A73: ABEM020KP712 | B73: =LEFT(A73,7) -> ABEM020 | C73: Aries Bling Emulsion 712 | D73: DIV 2 | E73: 20 KG | F73: 19.01 | G73: 1 | H73: PL | I73: 251000 | J73: 308300 | K73: 259800 | L73: 317800 | M73: 265000 | N73: 317800 | O73: 307400 | P73: 365300 | Q73: 322800 | R73: 381600
... A85: ABEM020KP724 | B85: =LEFT(A85,7) -> ABEM020 | C85: Aries Bling Emulsion 724 | D85: DIV 2 | E85: 20 KG | F85: 19.01 | G85: 1 | H85: PL | I85: 251000 | J85: 308300 | K85: 259800 | L85: 317800 | M85: 265000 | N85: 317800 | O85: 307400 | P85: 365300 | Q85: 322800 | R85: 381600
A86: ABEM020KP725 | B86: ABEM020KP725 | C86: Aries Bling Emulsion 725 | D86: DIV 2 | E86: 20 KG | F86: 19.01 | G86: 1 | H86: PL | I86: 251000 | J86: 308300 | K86: 259800 | L86: 317800 | M86: 265000 | N86: 317800 | O86: 307400 | P86: 365300 | Q86: 322800 | R86: 381600
A87: ABEM020KP726 | B87: =LEFT(A87,7) -> ABEM020 | C87: Aries Bling Emulsion 726 | D87: DIV 2 | E87: 20 KG | F87: 19.01 | G87: 1 | H87: PL | I87: 251000 | J87: 308300 | K87: 259800 | L87: 317800 | M87: 265000 | N87: 317800 | O87: 307400 | P87: 365300 | Q87: 322800 | R87: 381600
A88: ABEM020KPSB | B88: =LEFT(A88,7) -> ABEM020 | C88: Aries Bling Emulsion SB | D88: DIV 2 | E88: 20 KG | F88: 19.01 | G88: 1 | H88: PL | I88: 251000 | J88: 308300 | K88: 259800 | L88: 317800 | M88: 265000 | N88: 317800 | O88: 307400 | P88: 365300 | Q88: 322800 | R88: 381600
A89: ABEM020KPSW | B89: ABEM020KPSW | C89: Aries Bling Emulsion SW | D89: DIV 2 | E89: 20 KG | F89: 19.01 | G89: 1 | H89: PL | I89: 251000 | J89: 308300 | K89: 259800 | L89: 317800 | M89: 265000 | N89: 317800 | O89: 307400 | P89: 365300 | Q89: 322800 | R89: 381600
A90: ACME001K | B90: ACME001K | C90: Avian Cling Metal Primer 1 kg | D90: DIV 1 | E90: 1 KG | F90: 1.05 | G90: 24 | H90: DS | O90: 48300 | P90: 53300 | Q90: 48300 | R90: 53300
A91: ACME005K | B91: ACME005K | C91: Avian Cling Metal Primer 5 kg | D91: DIV 1 | E91: 4 KG | F91: 4.18 | G91: 4 | H91: DS | O91: 233200 | P91: 257600 | Q91: 233200 | R91: 257600
A92: ACSY001K11 | B92: =LEFT(A92,7) -> ACSY001 | C92: AVIAN Cling Synthetic 11 | D92: DIV 2 | E92: 0.85 LT | F92: 0.902 | G92: 24 | H92: DS | I92: 61600 | J92: 68300 | K92: 62500 | L92: 69300 | M92: 63100 | N92: 69300 | O92: 69400 | P92: 75700 | Q92: 74300 | R92: 81000
A93: ACSY001K12 | B93: =LEFT(A93,7) -> ACSY001 | C93: AVIAN Cling Synthetic 12 | D93: DIV 2 | E93: 0.85 LT | F93: 0.97 | G93: 24 | H93: DS | I93: 61600 | J93: 68300 | K93: 62500 | L93: 69300 | M93: 63100 | N93: 69300 | O93: 69400 | P93: 75700 | Q93: 74300 | R93: 81000
A94: ACSY001K15 | B94: =LEFT(A94,7) -> ACSY001 | C94: AVIAN Cling Synthetic 15 | D94: DIV 2 | E94: 0.85 LT | F94: 0.9615 | G94: 24 | H94: DS | I94: 61600 | J94: 68300 | K94: 62500 | L94: 69300 | M94: 63100 | N94: 69300 | O94: 69400 | P94: 75700 | Q94: 74300 | R94: 81000
A95: ACSY001K16 | B95: =LEFT(A95,7) -> ACSY001 | C95: AVIAN Cling Synthetic 16 | D95: DIV 2 | E95: 0.85 LT | F95: 0.9105 | G95: 24 | H95: DS | I95: 61600 | J95: 68300 | K95: 62500 | L95: 69300 | M95: 63100 | N95: 69300 | O95: 69400 | P95: 75700 | Q95: 74300 | R95: 81000
A96: ACSY001K17 | B96: =LEFT(A96,7) -> ACSY001 | C96: AVIAN Cling Synthetic 17 | D96: DIV 2 | E96: 0.85 LT | F96: 0.953 | G96: 24 | H96: DS | I96: 61600 | J96: 68300 | K96: 62500 | L96: 69300 | M96: 63100 | N96: 69300 | O96: 69400 | P96: 75700 | Q96: 74300 | R96: 81000
A97: ACSY001K33 | B97: =LEFT(A97,7) -> ACSY001 | C97: AVIAN Cling Synthetic 33 | D97: DIV 2 | E97: 0.85 LT | F97: 0.936 | G97: 24 | H97: DS | I97: 61600 | J97: 68300 | K97: 62500 | L97: 69300 | M97: 63100 | N97: 69300 | O97: 69400 | P97: 75700 | Q97: 74300 | R97: 81000
A98: ACSY001K36 | B98: =LEFT(A98,7) -> ACSY001 | C98: AVIAN Cling Synthetic 36 | D98: DIV 2 | E98: 0.85 LT | F98: 0.919 | G98: 24 | H98: DS | I98: 61600 | J98: 68300 | K98: 62500 | L98: 69300 | M98: 63100 | N98: 69300 | O98: 69400 | P98: 75700 | Q98: 74300 | R98: 81000
A99: ACSY001K37 | B99: =LEFT(A99,7) -> ACSY001 | C99: AVIAN Cling Synthetic 37 | D99: DIV 2 | E99: 0.85 LT | F99: 0.9105 | G99: 24 | H99: DS | I99: 61600 | J99: 68300 | K99: 62500 | L99: 69300 | M99: 63100 | N99: 69300 | O99: 69400 | P99: 75700 | Q99: 74300 | R99: 81000
A100: ACSY001K38 | B100: =LEFT(A100,7) -> ACSY001 | C100: AVIAN Cling Synthetic 38 | D100: DIV 2 | E100: 0.85 LT | F100: 0.936 | G100: 24 | H100: DS | I100: 61600 | J100: 68300 | K100: 62500 | L100: 69300 | M100: 63100 | N100: 69300 | O100: 69400 | P100: 75700 | Q100: 74300 | R100: 81000
A101: ACSY001K39 | B101: =LEFT(A101,7) -> ACSY001 | C101: AVIAN Cling Synthetic 39 | D101: DIV 2 | E101: 0.85 LT | F101: 0.936 | G101: 24 | H101: DS | I101: 61600 | J101: 68300 | K101: 62500 | L101: 69300 | M101: 63100 | N101: 69300 | O101: 69400 | P101: 75700 | Q101: 74300 | R101: 81000
A102: ACSY001K41 | B102: =LEFT(A102,7) -> ACSY001 | C102: AVIAN Cling Synthetic 41 | D102: DIV 2 | E102: 0.85 LT | F102: 0.9785 | G102: 24 | H102: DS | I102: 61600 | J102: 68300 | K102: 62500 | L102: 69300 | M102: 63100 | N102: 69300 | O102: 69400 | P102: 75700 | Q102: 74300 | R102: 81000
A103: ACSY001K43 | B103: =LEFT(A103,7) -> ACSY001 | C103: AVIAN Cling Synthetic 43 | D103: DIV 2 | E103: 0.85 LT | F103: 0.9445 | G103: 24 | H103: DS | I103: 61600 | J103: 68300 | K103: 62500 | L103: 69300 | M103: 63100 | N103: 69300 | O103: 69400 | P103: 75700 | Q103: 74300 | R103: 81000
... A126: ACSY001KSWM | B126: =LEFT(A126,7) -> ACSY001 | C126: AVIAN Cling Synthetic SWM | D126: DIV 2 | E126: 0.85 LT | F126: 1.1315 | G126: 24 | H126: DS | I126: 61600 | J126: 68300 | K126: 62500 | L126: 69300 | M126: 63100 | N126: 69300 | O126: 69400 | P126: 75700 | Q126: 74300 | R126: 81000
A127: ACSY001KW11 | B127: =LEFT(A127,9) -> ACSY001KW | C127: AVIAN Cling Synthetic Water 11 | D127: DIV 2 | E127: 0.85 LT | F127: 0.94 | G127: 24 | H127: DS | I127: 72000 | J127: 79500 | K127: 73100 | L127: 80700 | M127: 73800 | N127: 80700 | O127: 81200 | P127: 88100 | Q127: 85300 | R127: 92500
A128: ACSY001KW16 | B128: =LEFT(A128,9) -> ACSY001KW | C128: AVIAN Cling Synthetic Water 16 | D128: DIV 2 | E128: 0.85 LT | F128: 0.94 | G128: 24 | H128: DS | I128: 72000 | J128: 79500 | K128: 73100 | L128: 80700 | M128: 73800 | N128: 80700 | O128: 81200 | P128: 88100 | Q128: 85300 | R128: 92500
A129: ACSY001KW17 | B129: =LEFT(A129,9) -> ACSY001KW | C129: AVIAN Cling Synthetic Water 17 | D129: DIV 2 | E129: 0.85 LT | F129: 0.94 | G129: 24 | H129: DS | I129: 72000 | J129: 79500 | K129: 73100 | L129: 80700 | M129: 73800 | N129: 80700 | O129: 81200 | P129: 88100 | Q129: 85300 | R129: 92500
A130: ACSY001KW33 | B130: =LEFT(A130,9) -> ACSY001KW | C130: AVIAN Cling Synthetic Water 33 | D130: DIV 2 | E130: 0.85 LT | F130: 0.94 | G130: 24 | H130: DS | I130: 72000 | J130: 79500 | K130: 73100 | L130: 80700 | M130: 73800 | N130: 80700 | O130: 81200 | P130: 88100 | Q130: 85300 | R130: 92500
A131: ACSY001KW36 | B131: =LEFT(A131,9) -> ACSY001KW | C131: AVIAN Cling Synthetic Water 36 | D131: DIV 2 | E131: 0.85 LT | F131: 0.94 | G131: 24 | H131: DS | I131: 72000 | J131: 79500 | K131: 73100 | L131: 80700 | M131: 73800 | N131: 80700 | O131: 81200 | P131: 88100 | Q131: 85300 | R131: 92500
A132: ACSY001KW38 | B132: =LEFT(A132,9) -> ACSY001KW | C132: AVIAN Cling Synthetic Water 38 | D132: DIV 2 | E132: 0.85 LT | F132: 0.94 | G132: 24 | H132: DS | I132: 72000 | J132: 79500 | K132: 73100 | L132: 80700 | M132: 73800 | N132: 80700 | O132: 81200 | P132: 88100 | Q132: 85300 | R132: 92500
A133: ACSY001KW41 | B133: =LEFT(A133,9) -> ACSY001KW | C133: AVIAN Cling Synthetic Water 41 | D133: DIV 2 | E133: 0.85 LT | F133: 0.94 | G133: 24 | H133: DS | I133: 72000 | J133: 79500 | K133: 73100 | L133: 80700 | M133: 73800 | N133: 80700 | O133: 81200 | P133: 88100 | Q133: 85300 | R133: 92500
A134: ACSY001KW45 | B134: =LEFT(A134,9) -> ACSY001KW | C134: AVIAN Cling Synthetic Water 45 | D134: DIV 2 | E134: 0.85 LT | F134: 0.94 | G134: 24 | H134: DS | I134: 72000 | J134: 79500 | K134: 73100 | L134: 80700 | M134: 73800 | N134: 80700 | O134: 81200 | P134: 88100 | Q134: 85300 | R134: 92500
A135: ACSY001KW47 | B135: =LEFT(A135,9) -> ACSY001KW | C135: AVIAN Cling Synthetic Water 47 | D135: DIV 2 | E135: 0.85 LT | F135: 0.94 | G135: 24 | H135: DS | I135: 72000 | J135: 79500 | K135: 73100 | L135: 80700 | M135: 73800 | N135: 80700 | O135: 81200 | P135: 88100 | Q135: 85300 | R135: 92500
A136: ACSY001KW61 | B136: =LEFT(A136,9) -> ACSY001KW | C136: AVIAN Cling Synthetic Water 61 | D136: DIV 2 | E136: 0.85 LT | F136: 0.94 | G136: 24 | H136: DS | I136: 72000 | J136: 79500 | K136: 73100 | L136: 80700 | M136: 73800 | N136: 80700 | O136: 81200 | P136: 88100 | Q136: 85300 | R136: 92500
A137: ACSY001KW62 | B137: =LEFT(A137,9) -> ACSY001KW | C137: AVIAN Cling Synthetic Water 62 | D137: DIV 2 | E137: 0.85 LT | F137: 0.94 | G137: 24 | H137: DS | I137: 72000 | J137: 79500 | K137: 73100 | L137: 80700 | M137: 73800 | N137: 80700 | O137: 81200 | P137: 88100 | Q137: 85300 | R137: 92500
A138: ACSY001KW72 | B138: =LEFT(A138,9) -> ACSY001KW | C138: AVIAN Cling Synthetic Water 72 | D138: DIV 2 | E138: 0.85 LT | F138: 0.94 | G138: 24 | H138: DS | I138: 72000 | J138: 79500 | K138: 73100 | L138: 80700 | M138: 73800 | N138: 80700 | O138: 81200 | P138: 88100 | Q138: 85300 | R138: 92500
... A144: ACSY001KWSW | B144: =LEFT(A144,9) -> ACSY001KW | C144: AVIAN Cling Synthetic Water SW | D144: DIV 2 | E144: 0.85 LT | F144: 0.94 | G144: 24 | H144: DS | I144: 72000 | J144: 79500 | K144: 73100 | L144: 80700 | M144: 73800 | N144: 80700 | O144: 81200 | P144: 88100 | Q144: 85300 | R144: 92500
A145: ACSY004K11 | B145: =LEFT(A145,7) -> ACSY004 | C145: AVIAN Cling Synthetic 11 | D145: DIV 2 | E145: 3.4 LT | F145: 3.478 | G145: 4 | H145: DS | I145: 242900 | J145: 269200 | K145: 246600 | L145: 273200 | M145: 249100 | N145: 273200 | O145: 274000 | P145: 298200 | Q145: 293200 | R145: 318600
A146: ACSY004K16 | B146: =LEFT(A146,7) -> ACSY004 | C146: AVIAN Cling Synthetic 16 | D146: DIV 2 | E146: 3.4 LT | F146: 3.512 | G146: 4 | H146: DS | I146: 242900 | J146: 269200 | K146: 246600 | L146: 273200 | M146: 249100 | N146: 273200 | O146: 274000 | P146: 298200 | Q146: 293200 | R146: 318600
A147: ACSY004K17 | B147: =LEFT(A147,7) -> ACSY004 | C147: AVIAN Cling Synthetic 17 | D147: DIV 2 | E147: 3.4 LT | F147: 3.682 | G147: 4 | H147: DS | I147: 242900 | J147: 269200 | K147: 246600 | L147: 273200 | M147: 249100 | N147: 273200 | O147: 274000 | P147: 298200 | Q147: 293200 | R147: 318600
A148: ACSY004K33 | B148: =LEFT(A148,7) -> ACSY004 | C148: AVIAN Cling Synthetic 33 | D148: DIV 2 | E148: 3.4 LT | F148: 3.614 | G148: 4 | H148: DS | I148: 242900 | J148: 269200 | K148: 246600 | L148: 273200 | M148: 249100 | N148: 273200 | O148: 274000 | P148: 298200 | Q148: 293200 | R148: 318600
A149: ACSY004K38 | B149: =LEFT(A149,7) -> ACSY004 | C149: AVIAN Cling Synthetic 38 | D149: DIV 2 | E149: 3.4 LT | F149: 3.614 | G149: 4 | H149: DS | I149: 242900 | J149: 269200 | K149: 246600 | L149: 273200 | M149: 249100 | N149: 273200 | O149: 274000 | P149: 298200 | Q149: 293200 | R149: 318600
A150: ACSY004K41 | B150: =LEFT(A150,7) -> ACSY004 | C150: AVIAN Cling Synthetic 41 | D150: DIV 2 | E150: 3.4 LT | F150: 3.784 | G150: 4 | H150: DS | I150: 242900 | J150: 269200 | K150: 246600 | L150: 273200 | M150: 249100 | N150: 273200 | O150: 274000 | P150: 298200 | Q150: 293200 | R150: 318600
A151: ACSY004K45 | B151: =LEFT(A151,7) -> ACSY004 | C151: AVIAN Cling Synthetic 45 | D151: DIV 2 | E151: 3.4 LT | F151: 3.784 | G151: 4 | H151: DS | I151: 242900 | J151: 269200 | K151: 246600 | L151: 273200 | M151: 249100 | N151: 273200 | O151: 274000 | P151: 298200 | Q151: 293200 | R151: 318600
A152: ACSY004K61 | B152: =LEFT(A152,7) -> ACSY004 | C152: AVIAN Cling Synthetic 61 | D152: DIV 2 | E152: 3.4 LT | F152: 3.716 | G152: 4 | H152: DS | I152: 242900 | J152: 269200 | K152: 246600 | L152: 273200 | M152: 249100 | N152: 273200 | O152: 274000 | P152: 298200 | Q152: 293200 | R152: 318600
A153: ACSY004K62 | B153: =LEFT(A153,7) -> ACSY004 | C153: AVIAN Cling Synthetic 62 | D153: DIV 2 | E153: 3.4 LT | F153: 3.614 | G153: 4 | H153: DS | I153: 242900 | J153: 269200 | K153: 246600 | L153: 273200 | M153: 249100 | N153: 273200 | O153: 274000 | P153: 298200 | Q153: 293200 | R153: 318600
A154: ACSY004K72 | B154: =LEFT(A154,7) -> ACSY004 | C154: AVIAN Cling Synthetic 72 | D154: DIV 2 | E154: 3.4 LT | F154: 3.546 | G154: 4 | H154: DS | I154: 242900 | J154: 269200 | K154: 246600 | L154: 273200 | M154: 249100 | N154: 273200 | O154: 274000 | P154: 298200 | Q154: 293200 | R154: 318600
A155: ACSY004K77 | B155: =LEFT(A155,7) -> ACSY004 | C155: AVIAN Cling Synthetic 77 | D155: DIV 2 | E155: 3.4 LT | F155: 3.614 | G155: 4 | H155: DS | I155: 242900 | J155: 269200 | K155: 246600 | L155: 273200 | M155: 249100 | N155: 273200 | O155: 274000 | P155: 298200 | Q155: 293200 | R155: 318600
A156: ACSY004K79 | B156: =LEFT(A156,7) -> ACSY004 | C156: AVIAN Cling Synthetic 79 | D156: DIV 2 | E156: 3.4 LT | F156: 3.648 | G156: 4 | H156: DS | I156: 242900 | J156: 269200 | K156: 246600 | L156: 273200 | M156: 249100 | N156: 273200 | O156: 274000 | P156: 298200 | Q156: 293200 | R156: 318600
... A182: ACSY020KPSWM | B182: =LEFT(A182,7) -> ACSY020 | C182: AVIAN Cling Synthetic SWM | D182: DIV 2 | E182: 17 LT | F182: 21.74 | G182: 1 | H182: PL | I182: 1202300 | J182: 1332600 | K182: 1220300 | L182: 1352100 | M182: 1232500 | N182: 1352100 | O182: 1355800 | P182: 1475700 | Q182: 1450700 | R182: 1576400
A183: ACSY200C11 | B183: =LEFT(A183,7) -> ACSY200 | C183: AVIAN Cling Synthetic 11 | D183: DIV 2 | E183: 200 CC | F183: 0.222 | G183: 72 | H183: DS | I183: 18600 | J183: 20500 | K183: 19058 | L183: 20992 | M183: =231000/12 -> 19250 | N183: 20992 | O183: 21175 | P183: 22908 | Q183: 22658.333 | R183: 24483.333
A184: ACSY200C16 | B184: =LEFT(A184,7) -> ACSY200 | C184: AVIAN Cling Synthetic 16 | D184: DIV 2 | E184: 200 CC | F184: 0.224 | G184: 72 | H184: DS | I184: 18600 | J184: 20500 | K184: 19058 | L184: 20992 | M184: =231000/12 -> 19250 | N184: 20992 | O184: 21175 | P184: 22908 | Q184: 22658.333 | R184: 24483.333
A185: ACSY200C17 | B185: =LEFT(A185,7) -> ACSY200 | C185: AVIAN Cling Synthetic 17 | D185: DIV 2 | E185: 200 CC | F185: 0.234 | G185: 72 | H185: DS | I185: 18600 | J185: 20500 | K185: 19058 | L185: 20992 | M185: =231000/12 -> 19250 | N185: 20992 | O185: 21175 | P185: 22908 | Q185: 22658.333 | R185: 24483.333
...

Sheet Margin Calculation
AF2: Margin | AG2: =SUM(T:T) -> 3.9276956e+08
AF3: Expdc | AG3: =SUM(U:U) -> 45462434
B4: NAMA TOKO | K4: Margin Promo Juli | AF4: Upah Buruh | AG4: =SUM(V:V) -> 4235630.5
B5: TARGET | K5: =SUM(R:R)*1.11 -> 2.610796e+09 | AF5: Margin Kotor | AG5: =AG2-AG3-AG4 -> 3.4307149e+08
AF6: Reward | AG6: =SUM(AD:AD)+SUM(AC:AC)+SUM(AA:AA) -> #REF!
A7: No | B7: Tanggal | C7: Nomor Faktur | D7: SALES | E7: Brand | F7: Divisi | G7: Kuantitas | H7: Coli Qty. | I7: GrossWeight | J7: Harga Jual April 2026 | K7: Harga Beli April 2026 | L7: SD | M7: BD | N7: Diskon Promo Faktur | O7: Diskon Faktur | P7: Reward hadiah | Q7: Keterangan | R7: HJ Total | S7: HB Total | T7: Margin | U7: EXPDC | V7: Upah Buruh | W7: TW 2% | X7: Margin | Y7: Buffer hadiah | Z7: Cashback kontrak | AA7: Cashback | AB7: Biaya angkut ekspedisi | AC7: CB Kontrak | AD7: Potongan gathering | AF7: TW 2% | AG7: =SUM(W:W) -> 47299145
A8: 1 | B8: 46235 | C8: SO.AV.2026.08.00001 | D8: SALES002 | E8: ABEM005 | F8: =IFERROR(VLOOKUP(E8,'DATA MASTER'!$B$1:$R$3858,3,0),"") -> DIV 2 | G8: 2 | H8: =IFERROR(VLOOKUP(E8,'DATA MASTER'!$B$1:$R$3858,6,0),"") -> 4 | I8: =IFERROR(VLOOKUP(E8,'DATA MASTER'!$B$1:$R$3858,5,0),"") -> 4.74 | J8: =IFERROR(VLOOKUP(E8,'DATA MASTER'!$B$1:$R$3858,17,0),"") -> 99000 | K8: =IFERROR(VLOOKUP(E8,'DATA MASTER'!$B$1:$R$3858,16,0),"") -> 84000 | L8: =IFERROR(IF(F8="MTAB",12.5%*J8,7.5%*J8),"") -> 7425 | M8: =IFERROR(IF(F8="MTAB",19.011%*K8,14.488%*K8),"") -> 12169.92 | N8: 0 | O8: 0 | R8: =IFERROR((((J8-L8)/1.11*(100-O8)%*G8)-(ROUNDDOWN(G8/Y8,0)*N8)),"") -> 165000 | S8: =IFERROR((K8-M8)/1.11*(100-O8)%*G8,"") -> 129423.57 | T8: =IFERROR(R8-S8,"") -> 35576.432 | U8: =IFERROR(I8*G8*700,"") -> 6636 | V8: =IFERROR(G8*I8/23000*1500000,"") -> 618.26087 | W8: =IFERROR(2%*R8*1.11,"") -> 3663 | X8: =IFERROR(T8-U8-V8-W8-Z8-AC8-AB8-AA8-AD8,"") -> 21534.172 | Y8: 1 | Z8: 0 | AA8: =IFERROR(ROUNDDOWN(G8/Y8,0)*P8,"") -> 0 | AB8: =IFERROR(IF(OR(D8="SALES008",D8="SALES010"),IF(MOD(G8,H8)=0,10000*G8/H8,10000*(ROUNDUP(G8/H8,0))),0),"") -> 0 | AC8: 0 | AD8: 3125 | AF8: Laba Bersih | AG8: =AG5-AG6-AG7 -> #REF!
A9: 2 | B9: 46235 | C9: SO.AV.2026.08.00002 | D9: SALES005 | E9: AVSY100 | F9: =IFERROR(VLOOKUP(E9,'DATA MASTER'!$B$1:$R$3858,3,0),"") -> DIV 1 | G9: 24 | H9: =IFERROR(VLOOKUP(E9,'DATA MASTER'!$B$1:$R$3858,6,0),"") -> 120 | I9: =IFERROR(VLOOKUP(E9,'DATA MASTER'!$B$1:$R$3858,5,0),"") -> 0.145 | J9: =IFERROR(VLOOKUP(E9,'DATA MASTER'!$B$1:$R$3858,17,0),"") -> 15108.333 | K9: =IFERROR(VLOOKUP(E9,'DATA MASTER'!$B$1:$R$3858,16,0),"") -> 14025 | L9: =IFERROR(IF(F9="MTAB",12.5%*J9,7.5%*J9),"") -> 1133.125 | M9: =IFERROR(IF(F9="MTAB",19.011%*K9,14.488%*K9),"") -> 2031.942 | N9: 0 | O9: 0 | R9: =IFERROR((((J9-L9)/1.11*(100-O9)%*G9)-(ROUNDDOWN(G9/Y9,0)*N9)),"") -> 302166.67 | S9: =IFERROR((K9-M9)/1.11*(100-O9)%*G9,"") -> 259309.36 | T9: =IFERROR(R9-S9,"") -> 42857.305 | U9: =IFERROR(I9*G9*700,"") -> 2436 | V9: =IFERROR(G9*I9/23000*1500000,"") -> 226.95652 | W9: =IFERROR(2%*R9*1.11,"") -> 6708.1 | X9: =IFERROR(T9-U9-V9-W9-Z9-AC9-AB9-AA9-AD9,"") -> 33486.248 | Y9: 1 | Z9: 0 | AA9: =IFERROR(ROUNDDOWN(G9/Y9,0)*P9,"") -> 0 | AB9: =IFERROR(IF(OR(D9="SALES008",D9="SALES010"),IF(MOD(G9,H9)=0,10000*G9/H9,10000*(ROUNDUP(G9/H9,0))),0),"") -> 0 | AC9: 0 | AD9: 0 | AF9: BIAYA ANGKUT | AG9: =SUM(AB:AB) -> 3730000
A10: 3 | B10: 46235 | C10: SO.AV.2026.08.00002 | D10: SALES005 | E10: AVSY200 | F10: =IFERROR(VLOOKUP(E10,'DATA MASTER'!$B$1:$R$3858,3,0),"") -> DIV 1 | G10: 36 | H10: =IFERROR(VLOOKUP(E10,'DATA MASTER'!$B$1:$R$3858,6,0),"") -> 72 | I10: =IFERROR(VLOOKUP(E10,'DATA MASTER'!$B$1:$R$3858,5,0),"") -> 0.245333 | J10: =IFERROR(VLOOKUP(E10,'DATA MASTER'!$B$1:$R$3858,17,0),"") -> 27908.333 | K10: =IFERROR(VLOOKUP(E10,'DATA MASTER'!$B$1:$R$3858,16,0),"") -> 25850 | L10: =IFERROR(IF(F10="MTAB",12.5%*J10,7.5%*J10),"") -> 2093.125 | M10: =IFERROR(IF(F10="MTAB",19.011%*K10,14.488%*K10),"") -> 3745.148 | N10: 0 | O10: 0 | R10: =IFERROR((((J10-L10)/1.11*(100-O10)%*G10)-(ROUNDDOWN(G10/Y10,0)*N10)),"") -> 837250 | S10: =IFERROR((K10-M10)/1.11*(100-O10)%*G10,"") -> 716914.12 | T10: =IFERROR(R10-S10,"") -> 120335.88 | U10: =IFERROR(I10*G10*700,"") -> 6182.3916 | V10: =IFERROR(G10*I10/23000*1500000,"") -> 575.99922 | W10: =IFERROR(2%*R10*1.11,"") -> 18586.95 | X10: =IFERROR(T10-U10-V10-W10-Z10-AC10-AB10-AA10-AD10,"") -> 94990.54 | Y10: 1 | Z10: 0 | AA10: =IFERROR(ROUNDDOWN(G10/Y10,0)*P10,"") -> 0 | AB10: =IFERROR(IF(OR(D10="SALES008",D10="SALES010"),IF(MOD(G10,H10)=0,10000*G10/H10,10000*(ROUNDUP(G10/H10,0))),0),"") -> 0 | AC10: 0 | AD10: 0 | AF10: Margin total | AG10: =AG8-AG9 -> #REF!
A11: 4 | B11: 46235 | C11: SO.AV.2026.08.00003 | D11: SALES001 | E11: AVSY001 | F11: =IFERROR(VLOOKUP(E11,'DATA MASTER'!$B$1:$R$3858,3,0),"") -> DIV 1 | G11: 6 | H11: =IFERROR(VLOOKUP(E11,'DATA MASTER'!$B$1:$R$3858,6,0),"") -> 24 | I11: =IFERROR(VLOOKUP(E11,'DATA MASTER'!$B$1:$R$3858,5,0),"") -> 1.23 | J11: =IFERROR(VLOOKUP(E11,'DATA MASTER'!$B$1:$R$3858,17,0),"") -> 99800 | K11: =IFERROR(VLOOKUP(E11,'DATA MASTER'!$B$1:$R$3858,16,0),"") -> 92100 | L11: =IFERROR(IF(F11="MTAB",12.5%*J11,7.5%*J11),"") -> 7485 | M11: =IFERROR(IF(F11="MTAB",19.011%*K11,14.488%*K11),"") -> 13343.448 | N11: 0 | O11: 0 | R11: =IFERROR((((J11-L11)/1.11*(100-O11)%*G11)-(ROUNDDOWN(G11/Y11,0)*N11)),"") -> 499000 | S11: =IFERROR((K11-M11)/1.11*(100-O11)%*G11,"") -> 425711.09 | T11: =IFERROR(R11-S11,"") -> 73288.908 | U11: =IFERROR(I11*G11*700,"") -> 5166 | V11: =IFERROR(G11*I11/23000*1500000,"") -> 481.30435 | W11: =IFERROR(2%*R11*1.11,"") -> 11077.8 | X11: =IFERROR(T11-U11-V11-W11-Z11-AC11-AB11-AA11-AD11,"") -> 48230.47 | Y11: 1 | Z11: 0 | AA11: =IFERROR(ROUNDDOWN(G11/Y11,0)*P11,"") -> 0 | AB11: =IFERROR(IF(OR(D11="SALES008",D11="SALES010"),IF(MOD(G11,H11)=0,10000*G11/H11,10000*(ROUNDUP(G11/H11,0))),0),"") -> 0 | AC11: 0 | AD11: 8333.3333 | AF11: Emas
A12: 5 | B12: 46235 | C12: SO.AV.2026.08.00004 | D12: SALES012 | E12: AVSY001 | F12: =IFERROR(VLOOKUP(E12,'DATA MASTER'!$B$1:$R$3858,3,0),"") -> DIV 1 | G12: 5 | H12: =IFERROR(VLOOKUP(E12,'DATA MASTER'!$B$1:$R$3858,6,0),"") -> 24 | I12: =IFERROR(VLOOKUP(E12,'DATA MASTER'!$B$1:$R$3858,5,0),"") -> 1.23 | J12: =IFERROR(VLOOKUP(E12,'DATA MASTER'!$B$1:$R$3858,17,0),"") -> 99800 | K12: =IFERROR(VLOOKUP(E12,'DATA MASTER'!$B$1:$R$3858,16,0),"") -> 92100 | L12: =IFERROR(IF(F12="MTAB",12.5%*J12,7.5%*J12),"") -> 7485 | M12: =IFERROR(IF(F12="MTAB",19.011%*K12,14.488%*K12),"") -> 13343.448 | N12: 0 | O12: 0 | R12: =IFERROR((((J12-L12)/1.11*(100-O12)%*G12)-(ROUNDDOWN(G12/Y12,0)*N12)),"") -> 415833.33 | S12: =IFERROR((K12-M12)/1.11*(100-O12)%*G12,"") -> 354759.24 | T12: =IFERROR(R12-S12,"") -> 61074.09 | U12: =IFERROR(I12*G12*700,"") -> 4305 | V12: =IFERROR(G12*I12/23000*1500000,"") -> 401.08696 | W12: =IFERROR(2%*R12*1.11,"") -> 9231.5 | X12: =IFERROR(T12-U12-V12-W12-Z12-AC12-AB12-AA12-AD12,"") -> 39993.646 | Y12: =IF(E12="avem005",4,1) -> 1 | Z12: 0 | AA12: =IFERROR(ROUNDDOWN(G12/Y12,0)*P12,"") -> 0 | AB12: =IFERROR(IF(OR(D12="SALES008",D12="SALES010"),IF(MOD(G12,H12)=0,10000*G12/H12,10000*(ROUNDUP(G12/H12,0))),0),"") -> 0 | AC12: 0 | AD12: 7142.8571 | AF12: Total margin | AG12: =AG10+AG11 -> #REF!
A13: 6 | B13: 46235 | C13: SO.AV.2026.08.00006 | D13: SALES001 | E13: AVSY100 | F13: =IFERROR(VLOOKUP(E13,'DATA MASTER'!$B$1:$R$3858,3,0),"") -> DIV 1 | G13: 12 | H13: =IFERROR(VLOOKUP(E13,'DATA MASTER'!$B$1:$R$3858,6,0),"") -> 120 | I13: =IFERROR(VLOOKUP(E13,'DATA MASTER'!$B$1:$R$3858,5,0),"") -> 0.145 | J13: =IFERROR(VLOOKUP(E13,'DATA MASTER'!$B$1:$R$3858,17,0),"") -> 15108.333 | K13: =IFERROR(VLOOKUP(E13,'DATA MASTER'!$B$1:$R$3858,16,0),"") -> 14025 | L13: =IFERROR(IF(F13="MTAB",12.5%*J13,7.5%*J13),"") -> 1133.125 | M13: =IFERROR(IF(F13="MTAB",19.011%*K13,14.488%*K13),"") -> 2031.942 | N13: 0 | O13: 0 | R13: =IFERROR((((J13-L13)/1.11*(100-O13)%*G13)-(ROUNDDOWN(G13/Y13,0)*N13)),"") -> 151083.33 | S13: =IFERROR((K13-M13)/1.11*(100-O13)%*G13,"") -> 129654.68 | T13: =IFERROR(R13-S13,"") -> 21428.652 | U13: =IFERROR(I13*G13*700,"") -> 1218 | V13: =IFERROR(G13*I13/23000*1500000,"") -> 113.47826 | W13: =IFERROR(2%*R13*1.11,"") -> 3354.05 | X13: =IFERROR(T13-U13-V13-W13-Z13-AC13-AB13-AA13-AD13,"") -> 13409.791 | Y13: 1 | Z13: 0 | AA13: =IFERROR(ROUNDDOWN(G13/Y13,0)*P13,"") -> 0 | AB13: =IFERROR(IF(OR(D13="SALES008",D13="SALES010"),IF(MOD(G13,H13)=0,10000*G13/H13,10000*(ROUNDUP(G13/H13,0))),0),"") -> 0 | AC13: 0 | AD13: 3333.3333
A14: 7 | B14: 46235 | C14: SO.AV.2026.08.00006 | D14: SALES001 | E14: AVSY500 | F14: =IFERROR(VLOOKUP(E14,'DATA MASTER'!$B$1:$R$3858,3,0),"") -> DIV 1 | G14: 6 | H14: =IFERROR(VLOOKUP(E14,'DATA MASTER'!$B$1:$R$3858,6,0),"") -> 36 | I14: =IFERROR(VLOOKUP(E14,'DATA MASTER'!$B$1:$R$3858,5,0),"") -> 0.621 | J14: =IFERROR(VLOOKUP(E14,'DATA MASTER'!$B$1:$R$3858,17,0),"") -> 56900 | K14: =IFERROR(VLOOKUP(E14,'DATA MASTER'!$B$1:$R$3858,16,0),"") -> 52000 | L14: =IFERROR(IF(F14="MTAB",12.5%*J14,7.5%*J14),"") -> 4267.5 | M14: =IFERROR(IF(F14="MTAB",19.011%*K14,14.488%*K14),"") -> 7533.76 | N14: 0 | O14: 0 | R14: =IFERROR((((J14-L14)/1.11*(100-O14)%*G14)-(ROUNDDOWN(G14/Y14,0)*N14)),"") -> 284500 | S14: =IFERROR((K14-M14)/1.11*(100-O14)%*G14,"") -> 240358.05 | T14: =IFERROR(R14-S14,"") -> 44141.946 | U14: =IFERROR(I14*G14*700,"") -> 2608.2 | V14: =IFERROR(G14*I14/23000*1500000,"") -> 243 | W14: =IFERROR(2%*R14*1.11,"") -> 6315.9 | X14: =IFERROR(T14-U14-V14-W14-Z14-AC14-AB14-AA14-AD14,"") -> 31641.513 | Y14: 1 | Z14: 0 | AA14: =IFERROR(ROUNDDOWN(G14/Y14,0)*P14,"") -> 0 | AB14: =IFERROR(IF(OR(D14="SALES008",D14="SALES010"),IF(MOD(G14,H14)=0,10000*G14/H14,10000*(ROUNDUP(G14/H14,0))),0),"") -> 0 | AC14: 0 | AD14: 3333.3333
A15: 8 | B15: 46235 | C15: SO.AV.2026.08.00007 | D15: SALES004 | E15: AVSY001 | F15: =IFERROR(VLOOKUP(E15,'DATA MASTER'!$B$1:$R$3858,3,0),"") -> DIV 1 | G15: 6 | H15: =IFERROR(VLOOKUP(E15,'DATA MASTER'!$B$1:$R$3858,6,0),"") -> 24 | I15: =IFERROR(VLOOKUP(E15,'DATA MASTER'!$B$1:$R$3858,5,0),"") -> 1.23 | J15: =IFERROR(VLOOKUP(E15,'DATA MASTER'!$B$1:$R$3858,17,0),"") -> 99800 | K15: =IFERROR(VLOOKUP(E15,'DATA MASTER'!$B$1:$R$3858,16,0),"") -> 92100 | L15: =IFERROR(IF(F15="MTAB",12.5%*J15,7.5%*J15),"") -> 7485 | M15: =IFERROR(IF(F15="MTAB",19.011%*K15,14.488%*K15),"") -> 13343.448 | N15: 0 | O15: 0 | R15: =IFERROR((((J15-L15)/1.11*(100-O15)%*G15)-(ROUNDDOWN(G15/Y15,0)*N15)),"") -> 499000 | S15: =IFERROR((K15-M15)/1.11*(100-O15)%*G15,"") -> 425711.09 | T15: =IFERROR(R15-S15,"") -> 73288.908 | U15: =IFERROR(I15*G15*700,"") -> 5166 | V15: =IFERROR(G15*I15/23000*1500000,"") -> 481.30435 | W15: =IFERROR(2%*R15*1.11,"") -> 11077.8 | X15: =IFERROR(T15-U15-V15-W15-Z15-AC15-AB15-AA15-AD15,"") -> 56563.804 | Y15: 1 | Z15: 0 | AA15: =IFERROR(ROUNDDOWN(G15/Y15,0)*P15,"") -> 0 | AB15: =IFERROR(IF(OR(D15="SALES008",D15="SALES010"),IF(MOD(G15,H15)=0,10000*G15/H15,10000*(ROUNDUP(G15/H15,0))),0),"") -> 0 | AC15: 0 | AD15: 0 | AF15: Produk | AG15: Total Penjualan | AH15: Total margin | AI15: Persentase margin
A16: 9 | B16: 46235 | C16: SO.AV.2026.08.00008 | D16: SALES004 | E16: NODR001 | F16: =IFERROR(VLOOKUP(E16,'DATA MASTER'!$B$1:$R$3858,3,0),"") -> DIV 2 | G16: 2 | H16: =IFERROR(VLOOKUP(E16,'DATA MASTER'!$B$1:$R$3858,6,0),"") -> 24 | I16: =IFERROR(VLOOKUP(E16,'DATA MASTER'!$B$1:$R$3858,5,0),"") -> 1.09 | J16: =IFERROR(VLOOKUP(E16,'DATA MASTER'!$B$1:$R$3858,17,0),"") -> 82200 | K16: =IFERROR(VLOOKUP(E16,'DATA MASTER'!$B$1:$R$3858,16,0),"") -> 74900 | L16: =IFERROR(IF(F16="MTAB",12.5%*J16,7.5%*J16),"") -> 6165 | M16: =IFERROR(IF(F16="MTAB",19.011%*K16,14.488%*K16),"") -> 10851.512 | N16: 0 | O16: 0 | Q16: =VLOOKUP(#REF!,#REF!,1,0) -> #REF! | R16: =IFERROR((((J16-L16)/1.11*(100-O16)%*G16)-(ROUNDDOWN(G16/Y16,0)*N16)),"") -> 137000 | S16: =IFERROR((K16-M16)/1.11*(100-O16)%*G16,"") -> 115402.68 | T16: =IFERROR(R16-S16,"") -> 21597.319 | U16: =IFERROR(I16*G16*700,"") -> 1526 | V16: =IFERROR(G16*I16/23000*1500000,"") -> 142.17391 | W16: =IFERROR(2%*R16*1.11,"") -> 3041.4 | X16: =IFERROR(T16-U16-V16-W16-Z16-AC16-AB16-AA16-AD16,"") | Y16: 1 | Z16: =VLOOKUP(Q16,#REF!,4,0) -> #REF! | AA16: =IFERROR(ROUNDDOWN(G16/Y16,0)*P16,"") -> 0 | AB16: =IFERROR(IF(OR(D16="SALES008",D16="SALES010"),IF(MOD(G16,H16)=0,10000*G16/H16,10000*(ROUNDUP(G16/H16,0))),0),"") -> 0 | AC16: =Z16*R16*1.11 -> #REF! | AD16: 0 | AF16: ABEM001 | AG16: =SUMIF($E$8:$X$2162,AF16,$R$8:$R$2162)*1.11 -> 61790 | AH16: =SUMIF($E$8:$X$1048576,AF16,$X$8:$X$1048576) -> 3954.2329 | AI16: =AH16/AG16 -> 0.063994707
A17: 10 | B17: 46235 | C17: SO.AV.2026.08.00009 | D17: SALES005 | E17: YOSY001 | F17: =IFERROR(VLOOKUP(E17,'DATA MASTER'!$B$1:$R$3858,3,0),"") -> DIV 2 | G17: 18 | H17: =IFERROR(VLOOKUP(E17,'DATA MASTER'!$B$1:$R$3858,6,0),"") -> 24 | I17: =IFERROR(VLOOKUP(E17,'DATA MASTER'!$B$1:$R$3858,5,0),"") -> 0.85 | J17: =IFERROR(VLOOKUP(E17,'DATA MASTER'!$B$1:$R$3858,17,0),"") -> 74700 | K17: =IFERROR(VLOOKUP(E17,'DATA MASTER'!$B$1:$R$3858,16,0),"") -> 67900 | L17: =IFERROR(IF(F17="MTAB",12.5%*J17,7.5%*J17),"") -> 5602.5 | M17: =IFERROR(IF(F17="MTAB",19.011%*K17,14.488%*K17),"") -> 9837.352 | N17: 0 | O17: 0 | R17: =IFERROR((((J17-L17)/1.11*(100-O17)%*G17)-(ROUNDDOWN(G17/Y17,0)*N17)),"") -> 1120500 | S17: =IFERROR((K17-M17)/1.11*(100-O17)%*G17,"") -> 941556.45 | T17: =IFERROR(R17-S17,"") -> 178943.55 | U17: =IFERROR(I17*G17*700,"") -> 10710 | V17: =IFERROR(G17*I17/23000*1500000,"") -> 997.82609 | W17: =IFERROR(2%*R17*1.11,"") -> 24875.1 | X17: =IFERROR(T17-U17-V17-W17-Z17-AC17-AB17-AA17-AD17,"") -> 139419.44 | Y17: =IF(E17="avem005",4,1) -> 1 | Z17: 0 | AA17: =IFERROR(ROUNDDOWN(G17/Y17,0)*P17,"") -> 0 | AB17: =IFERROR(IF(OR(D17="SALES008",D17="SALES010"),IF(MOD(G17,H17)=0,10000*G17/H17,10000*(ROUNDUP(G17/H17,0))),0),"") -> 0 | AC17: 0 | AD17: 2941.1765 | AF17: ABEM001K725 | AG17: =SUMIF($E$8:$X$2162,AF17,$R$8:$R$2162)*1.11 -> 55611 | AH17: =SUMIF($E$8:$X$1048576,AF17,$X$8:$X$1048576) -> 3487.3997 | AI17: =AH17/AG17 -> 0.062710609
A18: 11 | B18: 46235 | C18: SO.AV.2026.08.00010 | D18: SALES001 | E18: AVGO005 | F18: =IFERROR(VLOOKUP(E18,'DATA MASTER'!$B$1:$R$3858,3,0),"") -> DIV 1 | G18: 2 | H18: =IFERROR(VLOOKUP(E18,'DATA MASTER'!$B$1:$R$3858,6,0),"") -> 4 | I18: =IFERROR(VLOOKUP(E18,'DATA MASTER'!$B$1:$R$3858,5,0),"") -> 5.23 | J18: =IFERROR(VLOOKUP(E18,'DATA MASTER'!$B$1:$R$3858,17,0),"") -> 231900 | K18: =IFERROR(VLOOKUP(E18,'DATA MASTER'!$B$1:$R$3858,16,0),"") -> 208700 | L18: =IFERROR(IF(F18="MTAB",12.5%*J18,7.5%*J18),"") -> 17392.5 | M18: =IFERROR(IF(F18="MTAB",19.011%*K18,14.488%*K18),"") -> 30236.456 | N18: 0 | O18: 0 | R18: =IFERROR((((J18-L18)/1.11*(100-O18)%*G18)-(ROUNDDOWN(G18/Y18,0)*N18)),"") -> 386500 | S18: =IFERROR((K18-M18)/1.11*(100-O18)%*G18,"") -> 321555.94 | T18: =IFERROR(R18-S18,"") -> 64944.065 | U18: =IFERROR(I18*G18*700,"") -> 7322 | V18: =IFERROR(G18*I18/23000*1500000,"") -> 682.17391 | W18: =IFERROR(2%*R18*1.11,"") -> 8580.3 | X18: =IFERROR(T18-U18-V18-W18-Z18-AC18-AB18-AA18-AD18,"") -> 38359.591 | Y18: =IF(E18="avem005",4,1) -> 1 | Z18: 0 | AA18: =IFERROR(ROUNDDOWN(G18/Y18,0)*P18,"") -> 0 | AB18: =IFERROR(IF(OR(D18="SALES008",D18="SALES010"),IF(MOD(G18,H18)=0,10000*G18/H18,10000*(ROUNDUP(G18/H18,0))),0),"") -> 0 | AC18: 0 | AD18: 10000 | AF18: ABEM001KSW | AG18: =SUMIF($E$8:$X$2162,AF18,$R$8:$R$2162)*1.11 -> 83416.5 | AH18: =SUMIF($E$8:$X$1048576,AF18,$X$8:$X$1048576) -> 6347.171 | AI18: =AH18/AG18 -> 0.076090114
A19: 12 | B19: 46235 | C19: SO.AV.2026.08.00011 | D19: SALES001 | E19: ABEM001 | F19: =IFERROR(VLOOKUP(E19,'DATA MASTER'!$B$1:$R$3858,3,0),"") -> DIV 1 | G19: 2 | H19: =IFERROR(VLOOKUP(E19,'DATA MASTER'!$B$1:$R$3858,6,0),"") -> 24 | I19: =IFERROR(VLOOKUP(E19,'DATA MASTER'!$B$1:$R$3858,5,0),"") -> 1.05 | J19: =IFERROR(VLOOKUP(E19,'DATA MASTER'!$B$1:$R$3858,17,0),"") -> 33400 | K19: =IFERROR(VLOOKUP(E19,'DATA MASTER'!$B$1:$R$3858,16,0),"") -> 29400 | L19: =IFERROR(IF(F19="MTAB",12.5%*J19,7.5%*J19),"") -> 2505 | M19: =IFERROR(IF(F19="MTAB",19.011%*K19,14.488%*K19),"") -> 4259.472 | N19: 0 | O19: 0 | R19: =IFERROR((((J19-L19)/1.11*(100-O19)%*G19)-(ROUNDDOWN(G19/Y19,0)*N19)),"") -> 55666.667 | S19: =IFERROR((K19-M19)/1.11*(100-O19)%*G19,"") -> 45298.249 | T19: =IFERROR(R19-S19,"") -> 10368.418 | U19: =IFERROR(I19*G19*700,"") -> 1470 | V19: =IFERROR(G19*I19/23000*1500000,"") -> 136.95652 | W19: =IFERROR(2%*R19*1.11,"") -> 1235.8 | X19: =IFERROR(T19-U19-V19-W19-Z19-AC19-AB19-AA19-AD19,"") -> 3954.2329 | Y19: 1 | Z19: 0 | AA19: =IFERROR(ROUNDDOWN(G19/Y19,0)*P19,"") -> 0 | AB19: =IFERROR(IF(OR(D19="SALES008",D19="SALES010"),IF(MOD(G19,H19)=0,10000*G19/H19,10000*(ROUNDUP(G19/H19,0))),0),"") -> 0 | AC19: 0 | AD19: 3571.4286 | AF19: ABEM005 | AG19: =SUMIF($E$8:$X$2162,AF19,$R$8:$R$2162)*1.11 -> 5036625 | AH19: =SUMIF($E$8:$X$1048576,AF19,$X$8:$X$1048576) -> 594555.79 | AI19: =AH19/AG19 -> 0.11804647
A20: 13 | B20: 46235 | C20: SO.AV.2026.08.00011 | D20: SALES001 | E20: ABEM005 | F20: =IFERROR(VLOOKUP(E20,'DATA MASTER'!$B$1:$R$3858,3,0),"") -> DIV 2 | G20: 2 | H20: =IFERROR(VLOOKUP(E20,'DATA MASTER'!$B$1:$R$3858,6,0),"") -> 4 | I20: =IFERROR(VLOOKUP(E20,'DATA MASTER'!$B$1:$R$3858,5,0),"") -> 4.74 | J20: =IFERROR(VLOOKUP(E20,'DATA MASTER'!$B$1:$R$3858,17,0),"") -> 99000 | K20: =IFERROR(VLOOKUP(E20,'DATA MASTER'!$B$1:$R$3858,16,0),"") -> 84000 | L20: =IFERROR(IF(F20="MTAB",12.5%*J20,7.5%*J20),"") -> 7425 | M20: =IFERROR(IF(F20="MTAB",19.011%*K20,14.488%*K20),"") -> 12169.92 | N20: 0 | O20: 0 | R20: =IFERROR((((J20-L20)/1.11*(100-O20)%*G20)-(ROUNDDOWN(G20/Y20,0)*N20)),"") -> 165000 | S20: =IFERROR((K20-M20)/1.11*(100-O20)%*G20,"") -> 129423.57 | T20: =IFERROR(R20-S20,"") -> 35576.432 | U20: =IFERROR(I20*G20*700,"") -> 6636 | V20: =IFERROR(G20*I20/23000*1500000,"") -> 618.26087 | W20: =IFERROR(2%*R20*1.11,"") -> 3663 | X20: =IFERROR(T20-U20-V20-W20-Z20-AC20-AB20-AA20-AD20,"") -> 21087.743 | Y20: 1 | Z20: 0 | AA20: =IFERROR(ROUNDDOWN(G20/Y20,0)*P20,"") -> 0 | AB20: =IFERROR(IF(OR(D20="SALES008",D20="SALES010"),IF(MOD(G20,H20)=0,10000*G20/H20,10000*(ROUNDUP(G20/H20,0))),0),"") -> 0 | AC20: 0 | AD20: 3571.4286 | AF20: ABEM005K725 | AG20: =SUMIF($E$8:$X$2162,AF20,$R$8:$R$2162)*1.11 -> 659340 | AH20: =SUMIF($E$8:$X$1048576,AF20,$X$8:$X$1048576) -> 80871.313 | AI20: =AH20/AG20 -> 0.12265495
A21: 14 | B21: 46235 | C21: SO.AV.2026.08.00012 | D21: SALES012 | E21: AVEM005 | F21: =IFERROR(VLOOKUP(E21,'DATA MASTER'!$B$1:$R$3858,3,0),"") -> DIV 1 | G21: 4 | H21: =IFERROR(VLOOKUP(E21,'DATA MASTER'!$B$1:$R$3858,6,0),"") -> 4 | I21: =IFERROR(VLOOKUP(E21,'DATA MASTER'!$B$1:$R$3858,5,0),"") -> 5.388 | J21: =IFERROR(VLOOKUP(E21,'DATA MASTER'!$B$1:$R$3858,17,0),"") -> 185700 | K21: =IFERROR(VLOOKUP(E21,'DATA MASTER'!$B$1:$R$3858,16,0),"") -> 165300 | L21: =IFERROR(IF(F21="MTAB",12.5%*J21,7.5%*J21),"") -> 13927.5 | M21: =IFERROR(IF(F21="MTAB",19.011%*K21,14.488%*K21),"") -> 23948.664 | N21: 0 | O21: 0 | R21: =IFERROR((((J21-L21)/1.11*(100-O21)%*G21)-(ROUNDDOWN(G21/Y21,0)*N21)),"") -> 619000 | S21: =IFERROR((K21-M21)/1.11*(100-O21)%*G21,"") -> 509374.18 | T21: =IFERROR(R21-S21,"") -> 109625.82 | U21: =IFERROR(I21*G21*700,"") -> 15086.4 | V21: =IFERROR(G21*I21/23000*1500000,"") -> 1405.5652 | W21: =IFERROR(2%*R21*1.11,"") -> 13741.8 | X21: =IFERROR(T21-U21-V21-W21-Z21-AC21-AB21-AA21-AD21,"") -> 79392.051 | Y21: 1 | Z21: 0 | AA21: =IFERROR(ROUNDDOWN(G21/Y21,0)*P21,"") -> 0 | AB21: =IFERROR(IF(OR(D21="SALES008",D21="SALES010"),IF(MOD(G21,H21)=0,10000*G21/H21,10000*(ROUNDUP(G21/H21,0))),0),"") -> 0 | AC21: 0 | AD21: 0 | AF21: ABEM005KSW | AG21: =SUMIF($E$8:$X$2162,AF21,$R$8:$R$2162)*1.11 -> 1318680 | AH21: =SUMIF($E$8:$X$1048576,AF21,$X$8:$X$1048576) -> 136742.63 | AI21: =AH21/AG21 -> 0.1036966
A22: 15 | B22: 46235 | C22: SO.AV.2026.08.00013 | D22: SALES006 | E22: AVEM005 | F22: =IFERROR(VLOOKUP(E22,'DATA MASTER'!$B$1:$R$3858,3,0),"") -> DIV 1 | G22: 4 | H22: =IFERROR(VLOOKUP(E22,'DATA MASTER'!$B$1:$R$3858,6,0),"") -> 4 | I22: =IFERROR(VLOOKUP(E22,'DATA MASTER'!$B$1:$R$3858,5,0),"") -> 5.388 | J22: =IFERROR(VLOOKUP(E22,'DATA MASTER'!$B$1:$R$3858,17,0),"") -> 185700 | K22: =IFERROR(VLOOKUP(E22,'DATA MASTER'!$B$1:$R$3858,16,0),"") -> 165300 | L22: =IFERROR(IF(F22="MTAB",12.5%*J22,7.5%*J22),"") -> 13927.5 | M22: =IFERROR(IF(F22="MTAB",19.011%*K22,14.488%*K22),"") -> 23948.664 | N22: 0 | O22: 0 | R22: =IFERROR((((J22-L22)/1.11*(100-O22)%*G22)-(ROUNDDOWN(G22/Y22,0)*N22)),"") -> 619000 | S22: =IFERROR((K22-M22)/1.11*(100-O22)%*G22,"") -> 509374.18 | T22: =IFERROR(R22-S22,"") -> 109625.82 | U22: =IFERROR(I22*G22*700,"") -> 15086.4 | V22: =IFERROR(G22*I22/23000*1500000,"") -> 1405.5652 | W22: =IFERROR(2%*R22*1.11,"") -> 13741.8 | X22: =IFERROR(T22-U22-V22-W22-Z22-AC22-AB22-AA22-AD22,"") -> 79392.051 | Y22: 1 | Z22: 0 | AA22: =IFERROR(ROUNDDOWN(G22/Y22,0)*P22,"") -> 0 | AB22: =IFERROR(IF(OR(D22="SALES008",D22="SALES010"),IF(MOD(G22,H22)=0,10000*G22/H22,10000*(ROUNDUP(G22/H22,0))),0),"") -> 0 | AC22: 0 | AD22: 0 | AF22: ABEM020 | AG22: =SUMIF($E$8:$X$2162,AF22,$R$8:$R$2162)*1.11 -> 2117880 | AH22: =SUMIF($E$8:$X$1048576,AF22,$X$8:$X$1048576) -> 269500.28 | AI22: =AH22/AG22 -> 0.12725002
A23: 16 | B23: 46235 | C23: SO.AV.2026.08.00013 | D23: SALES006 | E23: AVEM025 | F23: =IFERROR(VLOOKUP(E23,'DATA MASTER'!$B$1:$R$3858,3,0),"") -> DIV 1 | G23: 1 | H23: =IFERROR(VLOOKUP(E23,'DATA MASTER'!$B$1:$R$3858,6,0),"") -> 1 | I23: =IFERROR(VLOOKUP(E23,'DATA MASTER'!$B$1:$R$3858,5,0),"") -> 26.02 | J23: =IFERROR(VLOOKUP(E23,'DATA MASTER'!$B$1:$R$3858,17,0),"") -> 876000 | K23: =IFERROR(VLOOKUP(E23,'DATA MASTER'!$B$1:$R$3858,16,0),"") -> 777200 | L23: =IFERROR(IF(F23="MTAB",12.5%*J23,7.5%*J23),"") -> 65700 | M23: =IFERROR(IF(F23="MTAB",19.011%*K23,14.488%*K23),"") -> 112600.74 | N23: 0 | O23: 0 | R23: =IFERROR((((J23-L23)/1.11*(100-O23)%*G23)-(ROUNDDOWN(G23/Y23,0)*N23)),"") -> 730000 | S23: =IFERROR((K23-M23)/1.11*(100-O23)%*G23,"") -> 598738.08 | T23: =IFERROR(R23-S23,"") -> 131261.92 | U23: =IFERROR(I23*G23*700,"") -> 18214 | V23: =IFERROR(G23*I23/23000*1500000,"") -> 1696.9565 | W23: =IFERROR(2%*R23*1.11,"") -> 16206 | X23: =IFERROR(T23-U23-V23-W23-Z23-AC23-AB23-AA23-AD23,"") -> 95144.968 | Y23: 1 | Z23: 0 | AA23: =IFERROR(ROUNDDOWN(G23/Y23,0)*P23,"") -> 0 | AB23: =IFERROR(IF(OR(D23="SALES008",D23="SALES010"),IF(MOD(G23,H23)=0,10000*G23/H23,10000*(ROUNDUP(G23/H23,0))),0),"") -> 0 | AC23: 0 | AD23: 0 | AF23: ABEM020KP725 | AG23: =SUMIF($E$8:$X$2162,AF23,$R$8:$R$2162)*1.11 -> 635364 | AH23: =SUMIF($E$8:$X$1048576,AF23,$X$8:$X$1048576) -> 82978.502 | AI23: =AH23/AG23 -> 0.13059994
A24: 17 | B24: 46235 | C24: SO.AV.2026.08.00014 | D24: SALES001 | E24: AVGO025 | F24: =IFERROR(VLOOKUP(E24,'DATA MASTER'!$B$1:$R$3858,3,0),"") -> DIV 1 | G24: 2 | H24: =IFERROR(VLOOKUP(E24,'DATA MASTER'!$B$1:$R$3858,6,0),"") -> 1 | I24: =IFERROR(VLOOKUP(E24,'DATA MASTER'!$B$1:$R$3858,5,0),"") -> 26.01 | J24: =IFERROR(VLOOKUP(E24,'DATA MASTER'!$B$1:$R$3858,17,0),"") -> 1103500 | K24: =IFERROR(VLOOKUP(E24,'DATA MASTER'!$B$1:$R$3858,16,0),"") -> 991800 | L24: =IFERROR(IF(F24="MTAB",12.5%*J24,7.5%*J24),"") -> 82762.5 | M24: =IFERROR(IF(F24="MTAB",19.011%*K24,14.488%*K24),"") -> 143691.98 | N24: 0 | O24: 0 | Q24: =VLOOKUP(#REF!,#REF!,1,0) -> #REF! | R24: =IFERROR((((J24-L24)/1.11*(100-O24)%*G24)-(ROUNDDOWN(G24/Y24,0)*N24)),"") -> 1839166.7 | S24: =IFERROR((K24-M24)/1.11*(100-O24)%*G24,"") -> 1528122.6 | T24: =IFERROR(R24-S24,"") -> 311044.12 | U24: =IFERROR(I24*G24*700,"") -> 36414 | V24: =IFERROR(G24*I24/23000*1500000,"") -> 3392.6087 | W24: 0 | X24: =IFERROR(T24-U24-V24-W24-Z24-AC24-AB24-AA24-AD24,"") | Y24: 1 | Z24: =VLOOKUP(Q24,#REF!,4,0) -> #REF! | AA24: =IFERROR(ROUNDDOWN(G24/Y24,0)*P24,"") -> 0 | AB24: =IFERROR(IF(OR(D24="SALES008",D24="SALES010"),IF(MOD(G24,H24)=0,10000*G24/H24,10000*(ROUNDUP(G24/H24,0))),0),"") -> 0 | AC24: =Z24*R24*1.11 -> #REF! | AD24: 0 | AF24: ABEM020KPBA | AG24: =SUMIF($E$8:$X$2162,AF24,$R$8:$R$2162)*1.11 -> 631925 | AH24: =SUMIF($E$8:$X$1048576,AF24,$X$8:$X$1048576) -> 53395.201 | AI24: =AH24/AG24 -> 0.084496105
A25: 18 | B25: 46235 | C25: SO.AV.2026.08.00015 | D25: SALES002 | E25: NODR001 | F25: =IFERROR(VLOOKUP(E25,'DATA MASTER'!$B$1:$R$3858,3,0),"") -> DIV 2 | G25: 2 | H25: =IFERROR(VLOOKUP(E25,'DATA MASTER'!$B$1:$R$3858,6,0),"") -> 24 | I25: =IFERROR(VLOOKUP(E25,'DATA MASTER'!$B$1:$R$3858,5,0),"") -> 1.09 | J25: =IFERROR(VLOOKUP(E25,'DATA MASTER'!$B$1:$R$3858,17,0),"") -> 82200 | K25: =IFERROR(VLOOKUP(E25,'DATA MASTER'!$B$1:$R$3858,16,0),"") -> 74900 | L25: =IFERROR(IF(F25="MTAB",12.5%*J25,7.5%*J25),"") -> 6165 | M25: =IFERROR(IF(F25="MTAB",19.011%*K25,14.488%*K25),"") -> 10851.512 | N25: 0 | O25: 0 | R25: =IFERROR((((J25-L25)/1.11*(100-O25)%*G25)-(ROUNDDOWN(G25/Y25,0)*N25)),"") -> 137000 | S25: =IFERROR((K25-M25)/1.11*(100-O25)%*G25,"") -> 115402.68 | T25: =IFERROR(R25-S25,"") -> 21597.319 | U25: =IFERROR(I25*G25*700,"") -> 1526 | V25: =IFERROR(G25*I25/23000*1500000,"") -> 142.17391 | W25: =IFERROR(2%*R25*1.11,"") -> 3041.4 | X25: =IFERROR(T25-U25-V25-W25-Z25-AC25-AB25-AA25-AD25,"") -> 8554.4117 | Y25: 1 | Z25: 0 | AA25: =IFERROR(ROUNDDOWN(G25/Y25,0)*P25,"") -> 0 | AB25: =IFERROR(IF(OR(D25="SALES008",D25="SALES010"),IF(MOD(G25,H25)=0,10000*G25/H25,10000*(ROUNDUP(G25/H25,0))),0),"") -> 0 | AC25: 0 | AD25: 8333.3333 | AF25: ABEM020KPBC | AG25: =SUMIF($E$8:$X$2162,AF25,$R$8:$R$2162)*1.11 -> 587300 | AH25: =SUMIF($E$8:$X$1048576,AF25,$X$8:$X$1048576) -> 54858.939 | AI25: =AH25/AG25 -> 0.093408717
A26: 19 | B26: 46235 | C26: SO.AV.2026.08.00016 | D26: SALES002 | E26: ABEM020 | F26: =IFERROR(VLOOKUP(E26,'DATA MASTER'!$B$1:$R$3858,3,0),"") -> DIV 2 | G26: 1 | H26: =IFERROR(VLOOKUP(E26,'DATA MASTER'!$B$1:$R$3858,6,0),"") -> 1 | I26: =IFERROR(VLOOKUP(E26,'DATA MASTER'!$B$1:$R$3858,5,0),"") -> 19.01 | J26: =IFERROR(VLOOKUP(E26,'DATA MASTER'!$B$1:$R$3858,17,0),"") -> 381600 | K26: =IFERROR(VLOOKUP(E26,'DATA MASTER'!$B$1:$R$3858,16,0),"") -> 322800 | L26: =IFERROR(IF(F26="MTAB",12.5%*J26,7.5%*J26),"") -> 28620 | M26: =IFERROR(IF(F26="MTAB",19.011%*K26,14.488%*K26),"") -> 46767.264 | N26: 0 | O26: 0 | R26: =IFERROR((((J26-L26)/1.11*(100-O26)%*G26)-(ROUNDDOWN(G26/Y26,0)*N26)),"") -> 318000 | S26: =IFERROR((K26-M26)/1.11*(100-O26)%*G26,"") -> 248678.14 | T26: =IFERROR(R26-S26,"") -> 69321.859 | U26: =IFERROR(I26*G26*700,"") -> 13307 | V26: =IFERROR(G26*I26/23000*1500000,"") -> 1239.7826 | W26: =IFERROR(2%*R26*1.11,"") -> 7059.6 | X26: =IFERROR(T26-U26-V26-W26-Z26-AC26-AB26-AA26-AD26,"") -> 44590.477 | Y26: 1 | Z26: 0 | AA26: =IFERROR(ROUNDDOWN(G26/Y26,0)*P26,"") -> 0 | AB26: =IFERROR(IF(OR(D26="SALES008",D26="SALES010"),IF(MOD(G26,H26)=0,10000*G26/H26,10000*(ROUNDUP(G26/H26,0))),0),"") -> 0 | AC26: 0 | AD26: 3125 | AF26: ABEM020KPSW | AG26: =SUMIF($E$8:$X$2162,AF26,$R$8:$R$2162)*1.11 -> 2223774 | AH26: =SUMIF($E$8:$X$1048576,AF26,$X$8:$X$1048576) -> 283637.43 | AI26: =AH26/AG26 -> 0.12754778
A27: 20 | B27: 46235 | C27: SO.AV.2026.08.00017 | D27: SALES001 | E27: AGEM005 | F27: =IFERROR(VLOOKUP(E27,'DATA MASTER'!$B$1:$R$3858,3,0),"") -> DIV 2 | G27: 3 | H27: =IFERROR(VLOOKUP(E27,'DATA MASTER'!$B$1:$R$3858,6,0),"") -> 4 | I27: =IFERROR(VLOOKUP(E27,'DATA MASTER'!$B$1:$R$3858,5,0),"") -> 4.68 | J27: =IFERROR(VLOOKUP(E27,'DATA MASTER'!$B$1:$R$3858,17,0),"") -> 112100 | K27: =IFERROR(VLOOKUP(E27,'DATA MASTER'!$B$1:$R$3858,16,0),"") -> 96500 | L27: =IFERROR(IF(F27="MTAB",12.5%*J27,7.5%*J27),"") -> 8407.5 | M27: =IFERROR(IF(F27="MTAB",19.011%*K27,14.488%*K27),"") -> 13980.92 | N27: 0 | O27: 0 | R27: =IFERROR((((J27-L27)/1.11*(100-O27)%*G27)-(ROUNDDOWN(G27/Y27,0)*N27)),"") -> 280250 | S27: =IFERROR((K27-M27)/1.11*(100-O27)%*G27,"") -> 223024.54 | T27: =IFERROR(R27-S27,"") -> 57225.459 | U27: =IFERROR(I27*G27*700,"") -> 9828 | V27: =IFERROR(G27*I27/23000*1500000,"") -> 915.65217 | W27: =IFERROR(2%*R27*1.11,"") -> 6221.55 | X27: =IFERROR(T27-U27-V27-W27-Z27-AC27-AB27-AA27-AD27,"") -> 34377.904 | Y27: 1 | Z27: 0 | AA27: =IFERROR(ROUNDDOWN(G27/Y27,0)*P27,"") -> 0 | AB27: =IFERROR(IF(OR(D27="SALES008",D27="SALES010"),IF(MOD(G27,H27)=0,10000*G27/H27,10000*(ROUNDUP(G27/H27,0))),0),"") -> 0 | AC27: 0 | AD27: 5882.3529 | AF27: ACSY001 | AG27: =SUMIF($E$8:$X$2162,AF27,$R$8:$R$2162)*1.11 -> 1.2340148e+08 | AH27: =SUMIF($E$8:$X$1048576,AF27,$X$8:$X$1048576) -> 9929827.9 | AI27: =AH27/AG27 -> 0.08046766
A28: 21 | B28: 46235 | C28: SO.AV.2026.08.00017 | D28: SALES001 | E28: YOSY001 | F28: =IFERROR(VLOOKUP(E28,'DATA MASTER'!$B$1:$R$3858,3,0),"") -> DIV 2 | G28: 12 | H28: =IFERROR(VLOOKUP(E28,'DATA MASTER'!$B$1:$R$3858,6,0),"") -> 24 | I28: =IFERROR(VLOOKUP(E28,'DATA MASTER'!$B$1:$R$3858,5,0),"") -> 0.85 | J28: =IFERROR(VLOOKUP(E28,'DATA MASTER'!$B$1:$R$3858,17,0),"") -> 74700 | K28: =IFERROR(VLOOKUP(E28,'DATA MASTER'!$B$1:$R$3858,16,0),"") -> 67900 | L28: =IFERROR(IF(F28="MTAB",12.5%*J28,7.5%*J28),"") -> 5602.5 | M28: =IFERROR(IF(F28="MTAB",19.011%*K28,14.488%*K28),"") -> 9837.352 | N28: 0 | O28: 0 | R28: =IFERROR((((J28-L28)/1.11*(100-O28)%*G28)-(ROUNDDOWN(G28/Y28,0)*N28)),"") -> 747000 | S28: =IFERROR((K28-M28)/1.11*(100-O28)%*G28,"") -> 627704.3 | T28: =IFERROR(R28-S28,"") -> 119295.7 | U28: =IFERROR(I28*G28*700,"") -> 7140 | V28: =IFERROR(G28*I28/23000*1500000,"") -> 665.21739 | W28: =IFERROR(2%*R28*1.11,"") -> 16583.4 | X28: =IFERROR(T28-U28-V28-W28-Z28-AC28-AB28-AA28-AD28,"") -> 89024.727 | Y28: 1 | Z28: 0 | AA28: =IFERROR(ROUNDDOWN(G28/Y28,0)*P28,"") -> 0 | AB28: =IFERROR(IF(OR(D28="SALES008",D28="SALES010"),IF(MOD(G28,H28)=0,10000*G28/H28,10000*(ROUNDUP(G28/H28,0))),0),"") -> 0 | AC28: 0 | AD28: 5882.3529 | AF28: ACSY002 | AG28: =SUMIF($E$8:$X$2162,AF28,$R$8:$R$2162)*1.11 -> 587661.75 | AH28: =SUMIF($E$8:$X$1048576,AF28,$X$8:$X$1048576) -> 62140.134 | AI28: =AH28/AG28 -> 0.10574133
A29: 22 | B29: 46235 | C29: SO.AV.2026.08.00018 | D29: SALES006 | E29: NODR020 | F29: =IFERROR(VLOOKUP(E29,'DATA MASTER'!$B$1:$R$3858,3,0),"") -> DIV 2 | G29: 2 | H29: =IFERROR(VLOOKUP(E29,'DATA MASTER'!$B$1:$R$3858,6,0),"") -> 1 | I29: =IFERROR(VLOOKUP(E29,'DATA MASTER'!$B$1:$R$3858,5,0),"") -> 21.11 | J29: =IFERROR(VLOOKUP(E29,'DATA MASTER'!$B$1:$R$3858,17,0),"") -> 1428200 | K29: =IFERROR(VLOOKUP(E29,'DATA MASTER'!$B$1:$R$3858,16,0),"") -> 1291700 | L29: =IFERROR(IF(F29="MTAB",12.5%*J29,7.5%*J29),"") -> 107115 | M29: =IFERROR(IF(F29="MTAB",19.011%*K29,14.488%*K29),"") -> 187141.5 | N29: 0 | O29: 0 | R29: =IFERROR((((J29-L29)/1.11*(100-O29)%*G29)-(ROUNDDOWN(G29/Y29,0)*N29)),"") -> 2380333.3 | S29: =IFERROR((K29-M29)/1.11*(100-O29)%*G29,"") -> 1990195.5 | T29: =IFERROR(R29-S29,"") -> 390137.83 | U29: =IFERROR(I29*G29*700,"") -> 29554 | V29: =IFERROR(G29*I29/23000*1500000,"") -> 2753.4783 | W29: =IFERROR(2%*R29*1.11,"") -> 52843.4 | X29: =IFERROR(T29-U29-V29-W29-Z29-AC29-AB29-AA29-AD29,"") -> 294986.95 | Y29: 1 | Z29: 0 | AA29: =IFERROR(ROUNDDOWN(G29/Y29,0)*P29,"") -> 0 | AB29: =IFERROR(IF(OR(D29="SALES008",D29="SALES010"),IF(MOD(G29,H29)=0,10000*G29/H29,10000*(ROUNDUP(G29/H29,0))),0),"") -> 0 | AC29: 0 | AD29: 10000 | AF29: ACSY004 | AG29: =SUMIF($E$8:$X$2162,AF29,$R$8:$R$2162)*1.11 -> 2917579.5 | AH29: =SUMIF($E$8:$X$1048576,AF29,$X$8:$X$1048576) -> 184904.83 | AI29: =AH29/AG29 -> 0.063376108
A30: 23 | B30: 46235 | C30: SO.AV.2026.08.00019 | D30: SALES002 | E30: AVSY001 | F30: =IFERROR(VLOOKUP(E30,'DATA MASTER'!$B$1:$R$3858,3,0),"") -> DIV 1 | G30: 2 | H30: =IFERROR(VLOOKUP(E30,'DATA MASTER'!$B$1:$R$3858,6,0),"") -> 24 | I30: =IFERROR(VLOOKUP(E30,'DATA MASTER'!$B$1:$R$3858,5,0),"") -> 1.23 | J30: =IFERROR(VLOOKUP(E30,'DATA MASTER'!$B$1:$R$3858,17,0),"") -> 99800 | K30: =IFERROR(VLOOKUP(E30,'DATA MASTER'!$B$1:$R$3858,16,0),"") -> 92100 | L30: =IFERROR(IF(F30="MTAB",12.5%*J30,7.5%*J30),"") -> 7485 | M30: =IFERROR(IF(F30="MTAB",19.011%*K30,14.488%*K30),"") -> 13343.448 | N30: 0 | O30: 0 | R30: =IFERROR((((J30-L30)/1.11*(100-O30)%*G30)-(ROUNDDOWN(G30/Y30,0)*N30)),"") -> 166333.33 | S30: =IFERROR((K30-M30)/1.11*(100-O30)%*G30,"") -> 141903.7 | T30: =IFERROR(R30-S30,"") -> 24429.636 | U30: =IFERROR(I30*G30*700,"") -> 1722 | V30: =IFERROR(G30*I30/23000*1500000,"") -> 160.43478 | W30: =IFERROR(2%*R30*1.11,"") -> 3692.6 | X30: =IFERROR(T30-U30-V30-W30-Z30-AC30-AB30-AA30-AD30,"") -> 13085.37 | Y30: 1 | Z30: 0 | AA30: =IFERROR(ROUNDDOWN(G30/Y30,0)*P30,"") -> 0 | AB30: =IFERROR(IF(OR(D30="SALES008",D30="SALES010"),IF(MOD(G30,H30)=0,10000*G30/H30,10000*(ROUNDUP(G30/H30,0))),0),"") -> 0 | AC30: 0 | AD30: 5769.2308 | AF30: ACSY200 | AG30: =SUMIF($E$8:$X$2162,AF30,$R$8:$R$2162)*1.11 -> 4647181.5 | AH30: =SUMIF($E$8:$X$1048576,AF30,$X$8:$X$1048576) -> 364106.16 | AI30: =AH30/AG30 -> 0.07834989
A31: 24 | B31: 46235 | C31: SO.AV.2026.08.00020 | D31: SALES003 | E31: AVEM025 | F31: =IFERROR(VLOOKUP(E31,'DATA MASTER'!$B$1:$R$3858,3,0),"") -> DIV 1 | G31: 1 | H31: =IFERROR(VLOOKUP(E31,'DATA MASTER'!$B$1:$R$3858,6,0),"") -> 1 | I31: =IFERROR(VLOOKUP(E31,'DATA MASTER'!$B$1:$R$3858,5,0),"") -> 26.02 | J31: =IFERROR(VLOOKUP(E31,'DATA MASTER'!$B$1:$R$3858,17,0),"") -> 876000 | K31: =IFERROR(VLOOKUP(E31,'DATA MASTER'!$B$1:$R$3858,16,0),"") -> 777200 | L31: =IFERROR(IF(F31="MTAB",12.5%*J31,7.5%*J31),"") -> 65700 | M31: =IFERROR(IF(F31="MTAB",19.011%*K31,14.488%*K31),"") -> 112600.74 | N31: 0 | O31: 0 | R31: =IFERROR((((J31-L31)/1.11*(100-O31)%*G31)-(ROUNDDOWN(G31/Y31,0)*N31)),"") -> 730000 | S31: =IFERROR((K31-M31)/1.11*(100-O31)%*G31,"") -> 598738.08 | T31: =IFERROR(R31-S31,"") -> 131261.92 | U31: =IFERROR(I31*G31*700,"") -> 18214 | V31: =IFERROR(G31*I31/23000*1500000,"") -> 1696.9565 | W31: =IFERROR(2%*R31*1.11,"") -> 16206 | X31: =IFERROR(T31-U31-V31-W31-Z31-AC31-AB31-AA31-AD31,"") -> 87452.66 | Y31: =IF(E31="avem005",4,IF(E31="avem025",1,1)) -> 1 | Z31: 0 | AA31: =IFERROR(ROUNDDOWN(G31/Y31,0)*P31,"") -> 0 | AB31: =IFERROR(IF(OR(D31="SALES008",D31="SALES010"),IF(MOD(G31,H31)=0,10000*G31/H31,10000*(ROUNDUP(G31/H31,0))),0),"") -> 0 | AC31: 0 | AD31: 7692.3077 | AF31: ACZI001 | AG31: =SUMIF($E$8:$X$2162,AF31,$R$8:$R$2162)*1.11 -> 1367520 | AH31: =SUMIF($E$8:$X$1048576,AF31,$X$8:$X$1048576) -> 126393.82 | AI31: =AH31/AG31 -> 0.092425574
A32: 25 | B32: 46235 | C32: SO.AV.2026.08.00021 | D32: SALES001 | E32: NOBI001 | F32: =IFERROR(VLOOKUP(E32,'DATA MASTER'!$B$1:$R$3858,3,0),"") -> DIV 2 | G32: 6 | H32: =IFERROR(VLOOKUP(E32,'DATA MASTER'!$B$1:$R$3858,6,0),"") -> 24 | I32: =IFERROR(VLOOKUP(E32,'DATA MASTER'!$B$1:$R$3858,5,0),"") -> 1.084 | J32: =IFERROR(VLOOKUP(E32,'DATA MASTER'!$B$1:$R$3858,17,0),"") -> 54000 | K32: =IFERROR(VLOOKUP(E32,'DATA MASTER'!$B$1:$R$3858,16,0),"") -> 48900 | L32: =IFERROR(IF(F32="MTAB",12.5%*J32,7.5%*J32),"") -> 4050 | M32: =IFERROR(IF(F32="MTAB",19.011%*K32,14.488%*K32),"") -> 7084.632 | N32: 0 | O32: 0 | Q32: =VLOOKUP(#REF!,#REF!,1,0) -> #REF! | R32: =IFERROR((((J32-L32)/1.11*(100-O32)%*G32)-(ROUNDDOWN(G32/Y32,0)*N32)),"") -> 270000 | S32: =IFERROR((K32-M32)/1.11*(100-O32)%*G32,"") -> 226029.02 | T32: =IFERROR(R32-S32,"") -> 43970.984 | U32: =IFERROR(I32*G32*700,"") -> 4552.8 | V32: =IFERROR(G32*I32/23000*1500000,"") -> 424.17391 | W32: =IFERROR(2%*R32*1.11,"") -> 5994 | X32: =IFERROR(T32-U32-V32-W32-Z32-AC32-AB32-AA32-AD32,"") | Y32: 1 | Z32: =VLOOKUP(Q32,#REF!,4,0) -> #REF! | AA32: =IFERROR(ROUNDDOWN(G32/Y32,0)*P32,"") -> 0 | AB32: =IFERROR(IF(OR(D32="SALES008",D32="SALES010"),IF(MOD(G32,H32)=0,10000*G32/H32,10000*(ROUNDUP(G32/H32,0))),0),"") -> 0 | AC32: =Z32*R32*1.11 -> #REF! | AD32: 0 | AF32: ADFO005 | AG32: =SUMIF($E$8:$X$2162,AF32,$R$8:$R$2162)*1.11 -> 1666850 | AH32: =SUMIF($E$8:$X$1048576,AF32,$X$8:$X$1048576) -> 199043.65 | AI32: =AH32/AG32 -> 0.11941305
A33: 26 | B33: 46235 | C33: SO.AV.2026.08.00022 | D33: SALES012 | E33: AVSY001 | F33: =IFERROR(VLOOKUP(E33,'DATA MASTER'!$B$1:$R$3858,3,0),"") -> DIV 1 | G33: 6 | H33: =IFERROR(VLOOKUP(E33,'DATA MASTER'!$B$1:$R$3858,6,0),"") -> 24 | I33: =IFERROR(VLOOKUP(E33,'DATA MASTER'!$B$1:$R$3858,5,0),"") -> 1.23 | J33: =IFERROR(VLOOKUP(E33,'DATA MASTER'!$B$1:$R$3858,17,0),"") -> 99800 | K33: =IFERROR(VLOOKUP(E33,'DATA MASTER'!$B$1:$R$3858,16,0),"") -> 92100 | L33: =IFERROR(IF(F33="MTAB",12.5%*J33,7.5%*J33),"") -> 7485 | M33: =IFERROR(IF(F33="MTAB",19.011%*K33,14.488%*K33),"") -> 13343.448 | N33: 0 | O33: 0 | R33: =IFERROR((((J33-L33)/1.11*(100-O33)%*G33)-(ROUNDDOWN(G33/Y33,0)*N33)),"") -> 499000 | S33: =IFERROR((K33-M33)/1.11*(100-O33)%*G33,"") -> 425711.09 | T33: =IFERROR(R33-S33,"") -> 73288.908 | U33: =IFERROR(I33*G33*700,"") -> 5166 | V33: =IFERROR(G33*I33/23000*1500000,"") -> 481.30435 | W33: =IFERROR(2%*R33*1.11,"") -> 11077.8 | X33: =IFERROR(T33-U33-V33-W33-Z33-AC33-AB33-AA33-AD33,"") -> 49420.947 | Y33: 1 | Z33: 0 | AA33: =IFERROR(ROUNDDOWN(G33/Y33,0)*P33,"") -> 0 | AB33: =IFERROR(IF(OR(D33="SALES008",D33="SALES010"),IF(MOD(G33,H33)=0,10000*G33/H33,10000*(ROUNDUP(G33/H33,0))),0),"") -> 0 | AC33: 0 | AD33: 7142.8571 | AF33: AGEM001 | AG33: =SUMIF($E$8:$X$2162,AF33,$R$8:$R$2162)*1.11 -> 2109555 | AH33: =SUMIF($E$8:$X$1048576,AF33,$X$8:$X$1048576) -> 130097.7 | AI33: =AH33/AG33 -> 0.061670685
A34: 27 | B34: 46235 | C34: SO.AV.2026.08.00023 | D34: SALES010 | E34: AGEM005 | F34: =IFERROR(VLOOKUP(E34,'DATA MASTER'!$B$1:$R$3858,3,0),"") -> DIV 2 | G34: 8 | H34: =IFERROR(VLOOKUP(E34,'DATA MASTER'!$B$1:$R$3858,6,0),"") -> 4 | I34: =IFERROR(VLOOKUP(E34,'DATA MASTER'!$B$1:$R$3858,5,0),"") -> 4.68 | J34: =IFERROR(VLOOKUP(E34,'DATA MASTER'!$B$1:$R$3858,17,0),"") -> 112100 | K34: =IFERROR(VLOOKUP(E34,'DATA MASTER'!$B$1:$R$3858,16,0),"") -> 96500 | L34: =IFERROR(IF(F34="MTAB",12.5%*J34,7.5%*J34),"") -> 8407.5 | M34: =IFERROR(IF(F34="MTAB",19.011%*K34,14.488%*K34),"") -> 13980.92 | N34: 0 | O34: 0 | R34: =IFERROR((((J34-L34)/1.11*(100-O34)%*G34)-(ROUNDDOWN(G34/Y34,0)*N34)),"") -> 747333.33 | S34: =IFERROR((K34-M34)/1.11*(100-O34)%*G34,"") -> 594732.11 | T34: =IFERROR(R34-S34,"") -> 152601.23 | U34: =IFERROR(I34*G34*700,"") -> 26208 | V34: =IFERROR(G34*I34/23000*1500000,"") -> 2441.7391 | W34: =IFERROR(2%*R34*1.11,"") -> 16590.8 | X34: =IFERROR(T34-U34-V34-W34-Z34-AC34-AB34-AA34-AD34,"") -> 87360.686 | Y34: 1 | Z34: 0 | AA34: =IFERROR(ROUNDDOWN(G34/Y34,0)*P34,"") -> 0 | AB34: =IFERROR(IF(OR(D34="SALES008",D34="SALES010"),IF(MOD(G34,H34)=0,10000*G34/H34,10000*(ROUNDUP(G34/H34,0))),0),"") -> 20000 | AC34: 0 | AD34: 0 | AF34: AGEM001KBA | AG34: =SUMIF($E$8:$X$2162,AF34,$R$8:$R$2162)*1.11 -> 126700 | AH34: =SUMIF($E$8:$X$1048576,AF34,$X$8:$X$1048576) -> 8400.4407 | AI34: =AH34/AG34 -> 0.066301821
A35: 28 | B35: 46235 | C35: SO.AV.2026.08.00024 | D35: SALES010 | E35: BOVE001KSW | F35: =IFERROR(VLOOKUP(E35,'DATA MASTER'!$B$1:$R$3858,3,0),"") -> DIV 1 | G35: 24 | H35: =IFERROR(VLOOKUP(E35,'DATA MASTER'!$B$1:$R$3858,6,0),"") -> 24 | I35: =IFERROR(VLOOKUP(E35,'DATA MASTER'!$B$1:$R$3858,5,0),"") -> 1.126 | J35: =IFERROR(VLOOKUP(E35,'DATA MASTER'!$B$1:$R$3858,17,0),"") -> 105400 | K35: =IFERROR(VLOOKUP(E35,'DATA MASTER'!$B$1:$R$3858,16,0),"") -> 96600 | L35: =IFERROR(IF(F35="MTAB",12.5%*J35,7.5%*J35),"") -> 7905 | M35: =IFERROR(IF(F35="MTAB",19.011%*K35,14.488%*K35),"") -> 13995.408 | N35: 0 | O35: 0 | R35: =IFERROR((((J35-L35)/1.11*(100-O35)%*G35)-(ROUNDDOWN(G35/Y35,0)*N35)),"") -> 2108000 | S35: =IFERROR((K35-M35)/1.11*(100-O35)%*G35,"") -> 1786045.2 | T35: =IFERROR(R35-S35,"") -> 321954.77 | U35: =IFERROR(I35*G35*700,"") -> 18916.8 | V35: =IFERROR(G35*I35/23000*1500000,"") -> 1762.4348 | W35: =IFERROR(2%*R35*1.11,"") -> 46797.6 | X35: =IFERROR(T35-U35-V35-W35-Z35-AC35-AB35-AA35-AD35,"") -> 230192.22 | Y35: 1 | Z35: 0 | AA35: =IFERROR(ROUNDDOWN(G35/Y35,0)*P35,"") -> 0 | AB35: =IFERROR(IF(OR(D35="SALES008",D35="SALES010"),IF(MOD(G35,H35)=0,10000*G35/H35,10000*(ROUNDUP(G35/H35,0))),0),"") -> 10000 | AC35: 0 | AD35: 14285.714 | AF35: AGEM001KBB | AG35: =SUMIF($E$8:$X$2162,AF35,$R$8:$R$2162)*1.11 -> 63350 | AH35: =SUMIF($E$8:$X$1048576,AF35,$X$8:$X$1048576) -> 4261.4378 | AI35: =AH35/AG35 -> 0.067268157
A36: 29 | B36: 46235 | C36: SO.AV.2026.08.00025 | D36: SALES003 | E36: ACSY001 | F36: =IFERROR(VLOOKUP(E36,'DATA MASTER'!$B$1:$R$3858,3,0),"") -> DIV 2 | G36: 4 | H36: =IFERROR(VLOOKUP(E36,'DATA MASTER'!$B$1:$R$3858,6,0),"") -> 24 | I36: =IFERROR(VLOOKUP(E36,'DATA MASTER'!$B$1:$R$3858,5,0),"") -> 0.902 | J36: =IFERROR(VLOOKUP(E36,'DATA MASTER'!$B$1:$R$3858,17,0),"") -> 81000 | K36: =IFERROR(VLOOKUP(E36,'DATA MASTER'!$B$1:$R$3858,16,0),"") -> 74300 | L36: =IFERROR(IF(F36="MTAB",12.5%*J36,7.5%*J36),"") -> 6075 | M36: =IFERROR(IF(F36="MTAB",19.011%*K36,14.488%*K36),"") -> 10764.584 | N36: 0 | O36: 10 | R36: =IFERROR((((J36-L36)/1.11*(100-O36)%*G36)-(ROUNDDOWN(G36/Y36,0)*N36)),"") -> 243000 | S36: =IFERROR((K36-M36)/1.11*(100-O36)%*G36,"") -> 206060.81 | T36: =IFERROR(R36-S36,"") -> 36939.191 | U36: =IFERROR(I36*G36*700,"") -> 2525.6 | V36: =IFERROR(G36*I36/23000*1500000,"") -> 235.30435 | W36: =IFERROR(2%*R36*1.11,"") -> 5394.6 | X36: =IFERROR(T36-U36-V36-W36-Z36-AC36-AB36-AA36-AD36,"") -> 28783.687 | Y36: 1 | Z36: 0 | AA36: =IFERROR(ROUNDDOWN(G36/Y36,0)*P36,"") -> 0 | AB36: =IFERROR(IF(OR(D36="SALES008",D36="SALES010"),IF(MOD(G36,H36)=0,10000*G36/H36,10000*(ROUNDUP(G36/H36,0))),0),"") -> 0 | AC36: 0 | AD36: 0 | AF36: AGEM001KBC | AG36: =SUMIF($E$8:$X$2162,AF36,$R$8:$R$2162)*1.11 -> 126700 | AH36: =SUMIF($E$8:$X$1048576,AF36,$X$8:$X$1048576) -> 8645.3103 | AI36: =AH36/AG36 -> 0.068234493
A37: 30 | B37: 46235 | C37: SO.AV.2026.08.00026 | D37: SALES019 | E37: AGEM020 | F37: =IFERROR(VLOOKUP(E37,'DATA MASTER'!$B$1:$R$3858,3,0),"") -> DIV 2 | G37: 7 | H37: =IFERROR(VLOOKUP(E37,'DATA MASTER'!$B$1:$R$3858,6,0),"") -> 1 | I37: =IFERROR(VLOOKUP(E37,'DATA MASTER'!$B$1:$R$3858,5,0),"") -> 18.84 | J37: =IFERROR(VLOOKUP(E37,'DATA MASTER'!$B$1:$R$3858,17,0),"") -> 432400 | K37: =IFERROR(VLOOKUP(E37,'DATA MASTER'!$B$1:$R$3858,16,0),"") -> 376500 | L37: =IFERROR(IF(F37="MTAB",12.5%*J37,7.5%*J37),"") -> 32430 | M37: =IFERROR(IF(F37="MTAB",19.011%*K37,14.488%*K37),"") -> 54547.32 | N37: 0 | O37: 0 | R37: =IFERROR((((J37-L37)/1.11*(100-O37)%*G37)-(ROUNDDOWN(G37/Y37,0)*N37)),"") -> 2522333.3 | S37: =IFERROR((K37-M37)/1.11*(100-O37)%*G37,"") -> 2030332.2 | T37: =IFERROR(R37-S37,"") -> 492001.12 | U37: =IFERROR(I37*G37*700,"") -> 92316 | V37: =IFERROR(G37*I37/23000*1500000,"") -> 8600.8696 | W37: =IFERROR(2%*R37*1.11,"") -> 55995.8 | X37: =IFERROR(T37-U37-V37-W37-Z37-AC37-AB37-AA37-AD37,"") -> 315088.45 | Y37: =IF(E37="arem005",20,IF(E37="arem020",5,1)) -> 1 | Z37: 0 | AA37: =IFERROR(ROUNDDOWN(G37/Y37,0)*P37,"") -> 0 | AB37: =IFERROR(IF(OR(D37="SALES008",D37="SALES010"),IF(MOD(G37,H37)=0,10000*G37/H37,10000*(ROUNDUP(G37/H37,0))),0),"") -> 0 | AC37: 0 | AD37: 20000 | AF37: AGEM005 | AG37: =SUMIF($E$8:$X$2162,AF37,$R$8:$R$2162)*1.11 -> 42306540 | AH37: =SUMIF($E$8:$X$1048576,AF37,$X$8:$X$1048576) -> 4393903.1 | AI37: =AH37/AG37 -> 0.10385872
A38: 31 | B38: 46235 | C38: SO.AV.2026.08.00027 | D38: SALES004 | E38: AVSY001 | F38: =IFERROR(VLOOKUP(E38,'DATA MASTER'!$B$1:$R$3858,3,0),"") -> DIV 1 | G38: 6 | H38: =IFERROR(VLOOKUP(E38,'DATA MASTER'!$B$1:$R$3858,6,0),"") -> 24 | I38: =IFERROR(VLOOKUP(E38,'DATA MASTER'!$B$1:$R$3858,5,0),"") -> 1.23 | J38: =IFERROR(VLOOKUP(E38,'DATA MASTER'!$B$1:$R$3858,17,0),"") -> 99800 | K38: =IFERROR(VLOOKUP(E38,'DATA MASTER'!$B$1:$R$3858,16,0),"") -> 92100 | L38: =IFERROR(IF(F38="MTAB",12.5%*J38,7.5%*J38),"") -> 7485 | M38: =IFERROR(IF(F38="MTAB",19.011%*K38,14.488%*K38),"") -> 13343.448 | N38: 0 | O38: 0 | R38: =IFERROR((((J38-L38)/1.11*(100-O38)%*G38)-(ROUNDDOWN(G38/Y38,0)*N38)),"") -> 499000 | S38: =IFERROR((K38-M38)/1.11*(100-O38)%*G38,"") -> 425711.09 | T38: =IFERROR(R38-S38,"") -> 73288.908 | U38: =IFERROR(I38*G38*700,"") -> 5166 | V38: =IFERROR(G38*I38/23000*1500000,"") -> 481.30435 | W38: =IFERROR(2%*R38*1.11,"") -> 11077.8 | X38: =IFERROR(T38-U38-V38-W38-Z38-AC38-AB38-AA38-AD38,"") -> 56563.804 | Y38: 1 | Z38: 0 | AA38: =IFERROR(ROUNDDOWN(G38/Y38,0)*P38,"") -> 0 | AB38: =IFERROR(IF(OR(D38="SALES008",D38="SALES010"),IF(MOD(G38,H38)=0,10000*G38/H38,10000*(ROUNDUP(G38/H38,0))),0),"") -> 0 | AC38: 0 | AD38: 0 | AF38: AGEM005KBA | AG38: =SUMIF($E$8:$X$2162,AF38,$R$8:$R$2162)*1.11 -> 934500 | AH38: =SUMIF($E$8:$X$1048576,AF38,$X$8:$X$1048576) -> 60171.159 | AI38: =AH38/AG38 -> 0.064388614
A39: 32 | B39: 46235 | C39: SO.AV.2026.08.00028 | D39: SALES012 | E39: AVSY001 | F39: =IFERROR(VLOOKUP(E39,'DATA MASTER'!$B$1:$R$3858,3,0),"") -> DIV 1 | G39: 8 | H39: =IFERROR(VLOOKUP(E39,'DATA MASTER'!$B$1:$R$3858,6,0),"") -> 24 | I39: =IFERROR(VLOOKUP(E39,'DATA MASTER'!$B$1:$R$3858,5,0),"") -> 1.23 | J39: =IFERROR(VLOOKUP(E39,'DATA MASTER'!$B$1:$R$3858,17,0),"") -> 99800 | K39: =IFERROR(VLOOKUP(E39,'DATA MASTER'!$B$1:$R$3858,16,0),"") -> 92100 | L39: =IFERROR(IF(F39="MTAB",12.5%*J39,7.5%*J39),"") -> 7485 | M39: =IFERROR(IF(F39="MTAB",19.011%*K39,14.488%*K39),"") -> 13343.448 | N39: 0 | O39: 0 | R39: =IFERROR((((J39-L39)/1.11*(100-O39)%*G39)-(ROUNDDOWN(G39/Y39,0)*N39)),"") -> 665333.33 | S39: =IFERROR((K39-M39)/1.11*(100-O39)%*G39,"") -> 567614.79 | T39: =IFERROR(R39-S39,"") -> 97718.544 | U39: =IFERROR(I39*G39*700,"") -> 6888 | V39: =IFERROR(G39*I39/23000*1500000,"") -> 641.73913 | W39: =IFERROR(2%*R39*1.11,"") -> 14770.4 | X39: =IFERROR(T39-U39-V39-W39-Z39-AC39-AB39-AA39-AD39,"") -> 67085.072 | Y39: 1 | Z39: 0 | AA39: =IFERROR(ROUNDDOWN(G39/Y39,0)*P39,"") -> 0 | AB39: =IFERROR(IF(OR(D39="SALES008",D39="SALES010"),IF(MOD(G39,H39)=0,10000*G39/H39,10000*(ROUNDUP(G39/H39,0))),0),"") -> 0 | AC39: 0 | AD39: 8333.3333 | AF39: AGEM005KBB | AG39: =SUMIF($E$8:$X$2162,AF39,$R$8:$R$2162)*1.11 -> 1080450 | AH39: =SUMIF($E$8:$X$1048576,AF39,$X$8:$X$1048576) -> 69695.88 | AI39: =AH39/AG39 -> 0.064506344
A40: 33 | B40: 46235 | C40: SO.AV.2026.08.00029 | D40: SALES002 | E40: AVSY001 | F40: =IFERROR(VLOOKUP(E40,'DATA MASTER'!$B$1:$R$3858,3,0),"") -> DIV 1 | G40: 24 | H40: =IFERROR(VLOOKUP(E40,'DATA MASTER'!$B$1:$R$3858,6,0),"") -> 24 | I40: =IFERROR(VLOOKUP(E40,'DATA MASTER'!$B$1:$R$3858,5,0),"") -> 1.23 | J40: =IFERROR(VLOOKUP(E40,'DATA MASTER'!$B$1:$R$3858,17,0),"") -> 99800 | K40: =IFERROR(VLOOKUP(E40,'DATA MASTER'!$B$1:$R$3858,16,0),"") -> 92100 | L40: =IFERROR(IF(F40="MTAB",12.5%*J40,7.5%*J40),"") -> 7485 | M40: =IFERROR(IF(F40="MTAB",19.011%*K40,14.488%*K40),"") -> 13343.448 | N40: 0 | O40: 0 | P40: 60000 | Q40: 148 | R40: =IFERROR((((J40-L40)/1.11*(100-O40)%*G40)-(ROUNDDOWN(G40/Y40,0)*N40)),"") -> 1996000 | S40: =IFERROR((K40-M40)/1.11*(100-O40)%*G40,"") -> 1702844.4 | T40: =IFERROR(R40-S40,"") -> 293155.63 | U40: =IFERROR(I40*G40*700,"") -> 20664 | V40: =IFERROR(G40*I40/23000*1500000,"") -> 1925.2174 | W40: =IFERROR(2%*R40*1.11,"") -> 44311.2 | X40: =IFERROR(T40-U40-V40-W40-Z40-AC40-AB40-AA40-AD40,"") -> 152618.85 | Y40: 24 | Z40: 0 | AA40: =IFERROR(ROUNDDOWN(G40/Y40,0)*P40,"") -> 60000 | AB40: =IFERROR(IF(OR(D40="SALES008",D40="SALES010"),IF(MOD(G40,H40)=0,10000*G40/H40,10000*(ROUNDUP(G40/H40,0))),0),"") -> 0 | AC40: 0 | AD40: 13636.364 | AF40: AGEM005KBC | AG40: =SUMIF($E$8:$X$2162,AF40,$R$8:$R$2162)*1.11 -> 606987.5 | AH40: =SUMIF($E$8:$X$1048576,AF40,$X$8:$X$1048576) -> 49838.914 | AI40: =AH40/AG40 -> 0.082108633
A41: 34 | B41: 46235 | C41: SO.AV.2026.08.00030 | D41: SALES002 | E41: AVEM025 | F41: =IFERROR(VLOOKUP(E41,'DATA MASTER'!$B$1:$R$3858,3,0),"") -> DIV 1 | G41: 1 | H41: =IFERROR(VLOOKUP(E41,'DATA MASTER'!$B$1:$R$3858,6,0),"") -> 1 | I41: =IFERROR(VLOOKUP(E41,'DATA MASTER'!$B$1:$R$3858,5,0),"") -> 26.02 | J41: =IFERROR(VLOOKUP(E41,'DATA MASTER'!$B$1:$R$3858,17,0),"") -> 876000 | K41: =IFERROR(VLOOKUP(E41,'DATA MASTER'!$B$1:$R$3858,16,0),"") -> 777200 | L41: =IFERROR(IF(F41="MTAB",12.5%*J41,7.5%*J41),"") -> 65700 | M41: =IFERROR(IF(F41="MTAB",19.011%*K41,14.488%*K41),"") -> 112600.74 | N41: 0 | O41: 0 | R41: =IFERROR((((J41-L41)/1.11*(100-O41)%*G41)-(ROUNDDOWN(G41/Y41,0)*N41)),"") -> 730000 | S41: =IFERROR((K41-M41)/1.11*(100-O41)%*G41,"") -> 598738.08 | T41: =IFERROR(R41-S41,"") -> 131261.92 | U41: =IFERROR(I41*G41*700,"") -> 18214 | V41: =IFERROR(G41*I41/23000*1500000,"") -> 1696.9565 | W41: =IFERROR(2%*R41*1.11,"") -> 16206 | X41: =IFERROR(T41-U41-V41-W41-Z41-AC41-AB41-AA41-AD41,"") -> 95144.968 | Y41: 1 | Z41: 0 | AA41: =IFERROR(ROUNDDOWN(G41/Y41,0)*P41,"") -> 0 | AB41: =IFERROR(IF(OR(D41="SALES008",D41="SALES010"),IF(MOD(G41,H41)=0,10000*G41/H41,10000*(ROUNDUP(G41/H41,0))),0),"") -> 0 | AC41: 0 | AD41: 0 | AF41: AGEM020 | AG41: =SUMIF($E$8:$X$2162,AF41,$R$8:$R$2162)*1.11 -> 37197210 | AH41: =SUMIF($E$8:$X$1048576,AF41,$X$8:$X$1048576) -> 3388880.3 | AI41: =AH41/AG41 -> 0.091105766
A42: 35 | B42: 46235 | C42: SO.AV.2026.08.00031 | D42: SALES014 | E42: AVEM005 | F42: =IFERROR(VLOOKUP(E42,'DATA MASTER'!$B$1:$R$3858,3,0),"") -> DIV 1 | G42: 2 | H42: =IFERROR(VLOOKUP(E42,'DATA MASTER'!$B$1:$R$3858,6,0),"") -> 4 | I42: =IFERROR(VLOOKUP(E42,'DATA MASTER'!$B$1:$R$3858,5,0),"") -> 5.388 | J42: =IFERROR(VLOOKUP(E42,'DATA MASTER'!$B$1:$R$3858,17,0),"") -> 185700 | K42: =IFERROR(VLOOKUP(E42,'DATA MASTER'!$B$1:$R$3858,16,0),"") -> 165300 | L42: =IFERROR(IF(F42="MTAB",12.5%*J42,7.5%*J42),"") -> 13927.5 | M42: =IFERROR(IF(F42="MTAB",19.011%*K42,14.488%*K42),"") -> 23948.664 | N42: 0 | O42: 0 | R42: =IFERROR((((J42-L42)/1.11*(100-O42)%*G42)-(ROUNDDOWN(G42/Y42,0)*N42)),"") -> 309500 | S42: =IFERROR((K42-M42)/1.11*(100-O42)%*G42,"") -> 254687.09 | T42: =IFERROR(R42-S42,"") -> 54812.908 | U42: =IFERROR(I42*G42*700,"") -> 7543.2 | V42: =IFERROR(G42*I42/23000*1500000,"") -> 702.78261 | W42: =IFERROR(2%*R42*1.11,"") -> 6870.9 | X42: =IFERROR(T42-U42-V42-W42-Z42-AC42-AB42-AA42-AD42,"") -> 39696.025 | Y42: 1 | Z42: 0 | AA42: =IFERROR(ROUNDDOWN(G42/Y42,0)*P42,"") -> 0 | AB42: =IFERROR(IF(OR(D42="SALES008",D42="SALES010"),IF(MOD(G42,H42)=0,10000*G42/H42,10000*(ROUNDUP(G42/H42,0))),0),"") -> 0 | AC42: 0 | AD42: 0 | AF42: AGEM020KPBC | AG42: =SUMIF($E$8:$X$2162,AF42,$R$8:$R$2162)*1.11 -> 1014825 | AH42: =SUMIF($E$8:$X$1048576,AF42,$X$8:$X$1048576) -> 56139.584 | AI42: =AH42/AG42 -> 0.055319472
A43: 36 | B43: 46235 | C43: SO.AV.2026.08.00032 | D43: SALES005 | E43: AVSY004 | F43: =IFERROR(VLOOKUP(E43,'DATA MASTER'!$B$1:$R$3858,3,0),"") -> DIV 1 | G43: 4 | H43: =IFERROR(VLOOKUP(E43,'DATA MASTER'!$B$1:$R$3858,6,0),"") -> 4 | I43: =IFERROR(VLOOKUP(E43,'DATA MASTER'!$B$1:$R$3858,5,0),"") -> 4.238 | J43: =IFERROR(VLOOKUP(E43,'DATA MASTER'!$B$1:$R$3858,17,0),"") -> 392400 | K43: =IFERROR(VLOOKUP(E43,'DATA MASTER'!$B$1:$R$3858,16,0),"") -> 362700 | L43: =IFERROR(IF(F43="MTAB",12.5%*J43,7.5%*J43),"") -> 29430 | M43: =IFERROR(IF(F43="MTAB",19.011%*K43,14.488%*K43),"") -> 52547.976 | N43: 0 | O43: 0 | R43: =IFERROR((((J43-L43)/1.11*(100-O43)%*G43)-(ROUNDDOWN(G43/Y43,0)*N43)),"") -> 1308000 | S43: =IFERROR((K43-M43)/1.11*(100-O43)%*G43,"") -> 1117665 | T43: =IFERROR(R43-S43,"") -> 190335.05 | U43: =IFERROR(I43*G43*700,"") -> 11866.4 | V43: =IFERROR(G43*I43/23000*1500000,"") -> 1105.5652 | W43: =IFERROR(2%*R43*1.11,"") -> 29037.6 | X43: =IFERROR(T43-U43-V43-W43-Z43-AC43-AB43-AA43-AD43,"") -> 141182.63 | Y43: 1 | Z43: 0 | AA43: =IFERROR(ROUNDDOWN(G43/Y43,0)*P43,"") -> 0 | AB43: =IFERROR(IF(OR(D43="SALES008",D43="SALES010"),IF(MOD(G43,H43)=0,10000*G43/H43,10000*(ROUNDUP(G43/H43,0))),0),"") -> 0 | AC43: 0 | AD43: 7142.8571 | AF43: AGWA025 | AG43: =SUMIF($E$8:$X$2162,AF43,$R$8:$R$2162)*1.11 -> 345580 | AH43: =SUMIF($E$8:$X$1048576,AF43,$X$8:$X$1048576) -> 49652.239 | AI43: =AH43/AG43 -> 0.14367799
A44: 37 | B44: 46235 | C44: SO.AV.2026.08.00033 | D44: SALES008 | E44: AVSY001 | F44: =IFERROR(VLOOKUP(E44,'DATA MASTER'!$B$1:$R$3858,3,0),"") -> DIV 1 | G44: 72 | H44: =IFERROR(VLOOKUP(E44,'DATA MASTER'!$B$1:$R$3858,6,0),"") -> 24 | I44: =IFERROR(VLOOKUP(E44,'DATA MASTER'!$B$1:$R$3858,5,0),"") -> 1.23 | J44: =IFERROR(VLOOKUP(E44,'DATA MASTER'!$B$1:$R$3858,17,0),"") -> 99800 | K44: =IFERROR(VLOOKUP(E44,'DATA MASTER'!$B$1:$R$3858,16,0),"") -> 92100 | L44: =IFERROR(IF(F44="MTAB",12.5%*J44,7.5%*J44),"") -> 7485 | M44: =IFERROR(IF(F44="MTAB",19.011%*K44,14.488%*K44),"") -> 13343.448 | N44: 0 | O44: 0 | P44: 60000 | Q44: 148 | R44: =IFERROR((((J44-L44)/1.11*(100-O44)%*G44)-(ROUNDDOWN(G44/Y44,0)*N44)),"") -> 5988000 | S44: =IFERROR((K44-M44)/1.11*(100-O44)%*G44,"") -> 5108533.1 | T44: =IFERROR(R44-S44,"") -> 879466.9 | U44: =IFERROR(I44*G44*700,"") -> 61992 | V44: =IFERROR(G44*I44/23000*1500000,"") -> 5775.6522 | W44: =IFERROR(2%*R44*1.11,"") -> 132933.6 | X44: =IFERROR(T44-U44-V44-W44-Z44-AC44-AB44-AA44-AD44,"") -> 418765.65 | Y44: 24 | Z44: 0 | AA44: =IFERROR(ROUNDDOWN(G44/Y44,0)*P44,"") -> 180000 | AB44: =IFERROR(IF(OR(D44="SALES008",D44="SALES010"),IF(MOD(G44,H44)=0,10000*G44/H44,10000*(ROUNDUP(G44/H44,0))),0),"") -> 30000 | AC44: 0 | AD44: 50000 | AF44: AREM005 | AG44: =SUMIF($E$8:$X$2162,AF44,$R$8:$R$2162)*1.11 -> 21284250 | AH44: =SUMIF($E$8:$X$1048576,AF44,$X$8:$X$1048576) -> 2976863.3 | AI44: =AH44/AG44 -> 0.13986226
A45: 38 | B45: 46235 | C45: SO.AV.2026.08.00035 | D45: SALES008 | E45: AVSY001 | F45: =IFERROR(VLOOKUP(E45,'DATA MASTER'!$B$1:$R$3858,3,0),"") -> DIV 1 | G45: 24 | H45: =IFERROR(VLOOKUP(E45,'DATA MASTER'!$B$1:$R$3858,6,0),"") -> 24 | I45: =IFERROR(VLOOKUP(E45,'DATA MASTER'!$B$1:$R$3858,5,0),"") -> 1.23 | J45: =IFERROR(VLOOKUP(E45,'DATA MASTER'!$B$1:$R$3858,17,0),"") -> 99800 | K45: =IFERROR(VLOOKUP(E45,'DATA MASTER'!$B$1:$R$3858,16,0),"") -> 92100 | L45: =IFERROR(IF(F45="MTAB",12.5%*J45,7.5%*J45),"") -> 7485 | M45: =IFERROR(IF(F45="MTAB",19.011%*K45,14.488%*K45),"") -> 13343.448 | N45: 0 | O45: 0 | P45: 60000 | Q45: 148 | R45: =IFERROR((((J45-L45)/1.11*(100-O45)%*G45)-(ROUNDDOWN(G45/Y45,0)*N45)),"") -> 1996000 | S45: =IFERROR((K45-M45)/1.11*(100-O45)%*G45,"") -> 1702844.4 | T45: =IFERROR(R45-S45,"") -> 293155.63 | U45: =IFERROR(I45*G45*700,"") -> 20664 | V45: =IFERROR(G45*I45/23000*1500000,"") -> 1925.2174 | W45: =IFERROR(2%*R45*1.11,"") -> 44311.2 | X45: =IFERROR(T45-U45-V45-W45-Z45-AC45-AB45-AA45-AD45,"") -> 156255.22 | Y45: 24 | Z45: 0 | AA45: =IFERROR(ROUNDDOWN(G45/Y45,0)*P45,"") -> 60000 | AB45: =IFERROR(IF(OR(D45="SALES008",D45="SALES010"),IF(MOD(G45,H45)=0,10000*G45/H45,10000*(ROUNDUP(G45/H45,0))),0),"") -> 10000 | AC45: 0 | AD45: 0 | AF45: AREM005KSW | AG45: =SUMIF($E$8:$X$2162,AF45,$R$8:$R$2162)*1.11 -> 28606032 | AH45: =SUMIF($E$8:$X$1048576,AF45,$X$8:$X$1048576) -> 3380474.1 | AI45: =AH45/AG45 -> 0.11817347
A46: 39 | B46: 46235 | C46: SO.AV.2026.08.00036 | D46: SALES001 | E46: AVEM025 | F46: =IFERROR(VLOOKUP(E46,'DATA MASTER'!$B$1:$R$3858,3,0),"") -> DIV 1 | G46: 1 | H46: =IFERROR(VLOOKUP(E46,'DATA MASTER'!$B$1:$R$3858,6,0),"") -> 1 | I46: =IFERROR(VLOOKUP(E46,'DATA MASTER'!$B$1:$R$3858,5,0),"") -> 26.02 | J46: =IFERROR(VLOOKUP(E46,'DATA MASTER'!$B$1:$R$3858,17,0),"") -> 876000 | K46: =IFERROR(VLOOKUP(E46,'DATA MASTER'!$B$1:$R$3858,16,0),"") -> 777200 | L46: =IFERROR(IF(F46="MTAB",12.5%*J46,7.5%*J46),"") -> 65700 | M46: =IFERROR(IF(F46="MTAB",19.011%*K46,14.488%*K46),"") -> 112600.74 | N46: 0 | O46: 0 | R46: =IFERROR((((J46-L46)/1.11*(100-O46)%*G46)-(ROUNDDOWN(G46/Y46,0)*N46)),"") -> 730000 | S46: =IFERROR((K46-M46)/1.11*(100-O46)%*G46,"") -> 598738.08 | T46: =IFERROR(R46-S46,"") -> 131261.92 | U46: =IFERROR(I46*G46*700,"") -> 18214 | V46: =IFERROR(G46*I46/23000*1500000,"") -> 1696.9565 | W46: =IFERROR(2%*R46*1.11,"") -> 16206 | X46: =IFERROR(T46-U46-V46-W46-Z46-AC46-AB46-AA46-AD46,"") -> 78478.301 | Y46: 1 | Z46: 0 | AA46: =IFERROR(ROUNDDOWN(G46/Y46,0)*P46,"") -> 0 | AB46: =IFERROR(IF(OR(D46="SALES008",D46="SALES010"),IF(MOD(G46,H46)=0,10000*G46/H46,10000*(ROUNDUP(G46/H46,0))),0),"") -> 0 | AC46: 0 | AD46: 16666.667 | AF46: AREM020 | AG46: =SUMIF($E$8:$X$2162,AF46,$R$8:$R$2162)*1.11 -> 24824225 | AH46: =SUMIF($E$8:$X$1048576,AF46,$X$8:$X$1048576) -> 2068233.2 | AI46: =AH46/AG46 -> 0.083315119
A47: 40 | B47: 46235 | C47: SO.AV.2026.08.00037 | D47: SALES008 | E47: NODR001 | F47: =IFERROR(VLOOKUP(E47,'DATA MASTER'!$B$1:$R$3858,3,0),"") -> DIV 2 | G47: 20 | H47: =IFERROR(VLOOKUP(E47,'DATA MASTER'!$B$1:$R$3858,6,0),"") -> 24 | I47: =IFERROR(VLOOKUP(E47,'DATA MASTER'!$B$1:$R$3858,5,0),"") -> 1.09 | J47: =IFERROR(VLOOKUP(E47,'DATA MASTER'!$B$1:$R$3858,17,0),"") -> 82200 | K47: =IFERROR(VLOOKUP(E47,'DATA MASTER'!$B$1:$R$3858,16,0),"") -> 74900 | L47: =IFERROR(IF(F47="MTAB",12.5%*J47,7.5%*J47),"") -> 6165 | M47: =IFERROR(IF(F47="MTAB",19.011%*K47,14.488%*K47),"") -> 10851.512 | N47: 0 | O47: 0 | R47: =IFERROR((((J47-L47)/1.11*(100-O47)%*G47)-(ROUNDDOWN(G47/Y47,0)*N47)),"") -> 1370000 | S47: =IFERROR((K47-M47)/1.11*(100-O47)%*G47,"") -> 1154026.8 | T47: =IFERROR(R47-S47,"") -> 215973.19 | U47: =IFERROR(I47*G47*700,"") -> 15260 | V47: =IFERROR(G47*I47/23000*1500000,"") -> 1421.7391 | W47: =IFERROR(2%*R47*1.11,"") -> 30414 | X47: =IFERROR(T47-U47-V47-W47-Z47-AC47-AB47-AA47-AD47,"") -> 133877.45 | Y47: =IF(E47="avem005",4,1) -> 1 | Z47: 0 | AA47: =IFERROR(ROUNDDOWN(G47/Y47,0)*P47,"") -> 0 | AB47: =IFERROR(IF(OR(D47="SALES008",D47="SALES010"),IF(MOD(G47,H47)=0,10000*G47/H47,10000*(ROUNDUP(G47/H47,0))),0),"") -> 10000 | AC47: 0 | AD47: 25000 | AF47: AREM020KPSW | AG47: =SUMIF($E$8:$X$2162,AF47,$R$8:$R$2162)*1.11 -> 75106485 | AH47: =SUMIF($E$8:$X$1048576,AF47,$X$8:$X$1048576) -> 7972519.1 | AI47: =AH47/AG47 -> 0.10614954
A48: 41 | B48: 46235 | C48: SO.AV.2026.08.00037 | D48: SALES008 | E48: NODR004 | F48: =IFERROR(VLOOKUP(E48,'DATA MASTER'!$B$1:$R$3858,3,0),"") -> DIV 2 | G48: 4 | H48: =IFERROR(VLOOKUP(E48,'DATA MASTER'!$B$1:$R$3858,6,0),"") -> 4 | I48: =IFERROR(VLOOKUP(E48,'DATA MASTER'!$B$1:$R$3858,5,0),"") -> 4.24 | J48: =IFERROR(VLOOKUP(E48,'DATA MASTER'!$B$1:$R$3858,17,0),"") -> 310600 | K48: =IFERROR(VLOOKUP(E48,'DATA MASTER'!$B$1:$R$3858,16,0),"") -> 283000 | L48: =IFERROR(IF(F48="MTAB",12.5%*J48,7.5%*J48),"") -> 23295 | M48: =IFERROR(IF(F48="MTAB",19.011%*K48,14.488%*K48),"") -> 41001.04 | N48: 0 | O48: 0 | R48: =IFERROR((((J48-L48)/1.11*(100-O48)%*G48)-(ROUNDDOWN(G48/Y48,0)*N48)),"") -> 1035333.3 | S48: =IFERROR((K48-M48)/1.11*(100-O48)%*G48,"") -> 872068.32 | T48: =IFERROR(R48-S48,"") -> 163265.01 | U48: =IFERROR(I48*G48*700,"") -> 11872 | V48: =IFERROR(G48*I48/23000*1500000,"") -> 1106.087 | W48: =IFERROR(2%*R48*1.11,"") -> 22984.4 | X48: =IFERROR(T48-U48-V48-W48-Z48-AC48-AB48-AA48-AD48,"") -> 92302.522 | Y48: 1 | Z48: 0 | AA48: =IFERROR(ROUNDDOWN(G48/Y48,0)*P48,"") -> 0 | AB48: =IFERROR(IF(OR(D48="SALES008",D48="SALES010"),IF(MOD(G48,H48)=0,10000*G48/H48,10000*(ROUNDUP(G48/H48,0))),0),"") -> 10000 | AC48: 0 | AD48: 25000 | AF48: AVAL001 | AG48: =SUMIF($E$8:$X$2162,AF48,$R$8:$R$2162)*1.11 -> 95090 | AH48: =SUMIF($E$8:$X$1048576,AF48,$X$8:$X$1048576) -> 0 | AI48: =AH48/AG48 -> 0
A49: 42 | B49: 46235 | C49: SO.AV.2026.08.00038 | D49: SALES008 | E49: AVSY001 | F49: =IFERROR(VLOOKUP(E49,'DATA MASTER'!$B$1:$R$3858,3,0),"") -> DIV 1 | G49: 48 | H49: =IFERROR(VLOOKUP(E49,'DATA MASTER'!$B$1:$R$3858,6,0),"") -> 24 | I49: =IFERROR(VLOOKUP(E49,'DATA MASTER'!$B$1:$R$3858,5,0),"") -> 1.23 | J49: =IFERROR(VLOOKUP(E49,'DATA MASTER'!$B$1:$R$3858,17,0),"") -> 99800 | K49: =IFERROR(VLOOKUP(E49,'DATA MASTER'!$B$1:$R$3858,16,0),"") -> 92100 | L49: =IFERROR(IF(F49="MTAB",12.5%*J49,7.5%*J49),"") -> 7485 | M49: =IFERROR(IF(F49="MTAB",19.011%*K49,14.488%*K49),"") -> 13343.448 | N49: 0 | O49: 0 | R49: =IFERROR((((J49-L49)/1.11*(100-O49)%*G49)-(ROUNDDOWN(G49/Y49,0)*N49)),"") -> 3992000 | S49: =IFERROR((K49-M49)/1.11*(100-O49)%*G49,"") -> 3405688.7 | T49: =IFERROR(R49-S49,"") -> 586311.26 | U49: =IFERROR(I49*G49*700,"") -> 41328 | V49: =IFERROR(G49*I49/23000*1500000,"") -> 3850.4348 | W49: =IFERROR(2%*R49*1.11,"") -> 88622.4 | X49: =IFERROR(T49-U49-V49-W49-Z49-AC49-AB49-AA49-AD49,"") -> 403939 | Y49: 1 | Z49: 0 | AA49: =IFERROR(ROUNDDOWN(G49/Y49,0)*P49,"") -> 0 | AB49: =IFERROR(IF(OR(D49="SALES008",D49="SALES010"),IF(MOD(G49,H49)=0,10000*G49/H49,10000*(ROUNDUP(G49/H49,0))),0),"") -> 20000 | AC49: 0 | AD49: 28571.429 | AF49: AVAL004 | AG49: =SUMIF($E$8:$X$2162,AF49,$R$8:$R$2162)*1.11 -> 7698960 | AH49: =SUMIF($E$8:$X$1048576,AF49,$X$8:$X$1048576) -> 697458.22 | AI49: =AH49/AG49 -> 0.090591225
A50: 43 | B50: 46235 | C50: SO.AV.2026.08.00039 | D50: SALES001 | E50: AVGO025 | F50: =IFERROR(VLOOKUP(E50,'DATA MASTER'!$B$1:$R$3858,3,0),"") -> DIV 1 | G50: 2 | H50: =IFERROR(VLOOKUP(E50,'DATA MASTER'!$B$1:$R$3858,6,0),"") -> 1 | I50: =IFERROR(VLOOKUP(E50,'DATA MASTER'!$B$1:$R$3858,5,0),"") -> 26.01 | J50: =IFERROR(VLOOKUP(E50,'DATA MASTER'!$B$1:$R$3858,17,0),"") -> 1103500 | K50: =IFERROR(VLOOKUP(E50,'DATA MASTER'!$B$1:$R$3858,16,0),"") -> 991800 | L50: =IFERROR(IF(F50="MTAB",12.5%*J50,7.5%*J50),"") -> 82762.5 | M50: =IFERROR(IF(F50="MTAB",19.011%*K50,14.488%*K50),"") -> 143691.98 | O50: 0 | Q50: =VLOOKUP(#REF!,#REF!,1,0) -> #REF! | R50: =IFERROR((((J50-L50)/1.11*(100-O50)%*G50)-(ROUNDDOWN(G50/Y50,0)*N50)),"") -> 1839166.7 | S50: =IFERROR((K50-M50)/1.11*(100-O50)%*G50,"") -> 1528122.6 | T50: =IFERROR(R50-S50,"") -> 311044.12 | U50: =IFERROR(I50*G50*700,"") -> 36414 | V50: =IFERROR(G50*I50/23000*1500000,"") -> 3392.6087 | W50: 0 | X50: =IFERROR(T50-U50-V50-W50-Z50-AC50-AB50-AA50-AD50,"") | Y50: 1 | Z50: =VLOOKUP(Q50,#REF!,4,0) -> #REF! | AA50: =IFERROR(ROUNDDOWN(G50/Y50,0)*P50,"") -> 0 | AB50: =IFERROR(IF(OR(D50="SALES008",D50="SALES010"),IF(MOD(G50,H50)=0,10000*G50/H50,10000*(ROUNDUP(G50/H50,0))),0),"") -> 0 | AC50: =Z50*R50*1.11 -> #REF! | AD50: 0 | AF50: AVAL021 | AG50: =SUMIF($E$8:$X$2162,AF50,$R$8:$R$2162)*1.11 -> 8127050 | AH50: =SUMIF($E$8:$X$1048576,AF50,$X$8:$X$1048576) -> 908659.6 | AI50: =AH50/AG50 -> 0.11180682
A51: 44 | B51: 46235 | C51: SO.AV.2026.08.00040 | D51: SALES003 | E51: AVEM005 | F51: =IFERROR(VLOOKUP(E51,'DATA MASTER'!$B$1:$R$3858,3,0),"") -> DIV 1 | G51: 2 | H51: =IFERROR(VLOOKUP(E51,'DATA MASTER'!$B$1:$R$3858,6,0),"") -> 4 | I51: =IFERROR(VLOOKUP(E51,'DATA MASTER'!$B$1:$R$3858,5,0),"") -> 5.388 | J51: =IFERROR(VLOOKUP(E51,'DATA MASTER'!$B$1:$R$3858,17,0),"") -> 185700 | K51: =IFERROR(VLOOKUP(E51,'DATA MASTER'!$B$1:$R$3858,16,0),"") -> 165300 | L51: =IFERROR(IF(F51="MTAB",12.5%*J51,7.5%*J51),"") -> 13927.5 | M51: =IFERROR(IF(F51="MTAB",19.011%*K51,14.488%*K51),"") -> 23948.664 | O51: 0 | R51: =IFERROR((((J51-L51)/1.11*(100-O51)%*G51)-(ROUNDDOWN(G51/Y51,0)*N51)),"") -> 309500 | S51: =IFERROR((K51-M51)/1.11*(100-O51)%*G51,"") -> 254687.09 | T51: =IFERROR(R51-S51,"") -> 54812.908 | U51: =IFERROR(I51*G51*700,"") -> 7543.2 | V51: =IFERROR(G51*I51/23000*1500000,"") -> 702.78261 | W51: =IFERROR(2%*R51*1.11,"") -> 6870.9 | X51: =IFERROR(T51-U51-V51-W51-Z51-AC51-AB51-AA51-AD51,"") -> 33813.673 | Y51: 1 | Z51: 0 | AA51: =IFERROR(ROUNDDOWN(G51/Y51,0)*P51,"") -> 0 | AB51: =IFERROR(IF(OR(D51="SALES008",D51="SALES010"),IF(MOD(G51,H51)=0,10000*G51/H51,10000*(ROUNDUP(G51/H51,0))),0),"") -> 0 | AC51: 0 | AD51: 5882.3529 | AF51: AVBR100 | AG51: =SUMIF($E$8:$X$2162,AF51,$R$8:$R$2162)*1.11 -> 669130.2 | AH51: =SUMIF($E$8:$X$1048576,AF51,$X$8:$X$1048576) -> 22444.581 | AI51: =AH51/AG51 -> 0.033542921
A52: 45 | B52: 46235 | C52: SO.AV.2026.08.00041 | D52: SALES001 | E52: AVSY001 | F52: =IFERROR(VLOOKUP(E52,'DATA MASTER'!$B$1:$R$3858,3,0),"") -> DIV 1 | G52: 8 | H52: =IFERROR(VLOOKUP(E52,'DATA MASTER'!$B$1:$R$3858,6,0),"") -> 24 | I52: =IFERROR(VLOOKUP(E52,'DATA MASTER'!$B$1:$R$3858,5,0),"") -> 1.23 | J52: =IFERROR(VLOOKUP(E52,'DATA MASTER'!$B$1:$R$3858,17,0),"") -> 99800 | K52: =IFERROR(VLOOKUP(E52,'DATA MASTER'!$B$1:$R$3858,16,0),"") -> 92100 | L52: =IFERROR(IF(F52="MTAB",12.5%*J52,7.5%*J52),"") -> 7485 | M52: =IFERROR(IF(F52="MTAB",19.011%*K52,14.488%*K52),"") -> 13343.448 | O52: 0 | R52: =IFERROR((((J52-L52)/1.11*(100-O52)%*G52)-(ROUNDDOWN(G52/Y52,0)*N52)),"") -> 665333.33 | S52: =IFERROR((K52-M52)/1.11*(100-O52)%*G52,"") -> 567614.79 | T52: =IFERROR(R52-S52,"") -> 97718.544 | U52: =IFERROR(I52*G52*700,"") -> 6888 | V52: =IFERROR(G52*I52/23000*1500000,"") -> 641.73913 | W52: =IFERROR(2%*R52*1.11,"") -> 14770.4 | X52: =IFERROR(T52-U52-V52-W52-Z52-AC52-AB52-AA52-AD52,"") -> 69536.052 | Y52: 1 | Z52: 0 | AA52: =IFERROR(ROUNDDOWN(G52/Y52,0)*P52,"") -> 0 | AB52: =IFERROR(IF(OR(D52="SALES008",D52="SALES010"),IF(MOD(G52,H52)=0,10000*G52/H52,10000*(ROUNDUP(G52/H52,0))),0),"") -> 0 | AC52: 0 | AD52: 5882.3529 | AF52: AVEM001 | AG52: =SUMIF($E$8:$X$2162,AF52,$R$8:$R$2162)*1.11 -> 9890100 | AH52: =SUMIF($E$8:$X$1048576,AF52,$X$8:$X$1048576) -> 797702.97 | AI52: =AH52/AG52 -> 0.080656715
A53: 46 | B53: 46235 | C53: SO.AV.2026.08.00042 | D53: SALES010 | E53: BOVE001 | F53: =IFERROR(VLOOKUP(E53,'DATA MASTER'!$B$1:$R$3858,3,0),"") -> DIV 1 | G53: 4 | H53: =IFERROR(VLOOKUP(E53,'DATA MASTER'!$B$1:$R$3858,6,0),"") -> 24 | I53: =IFERROR(VLOOKUP(E53,'DATA MASTER'!$B$1:$R$3858,5,0),"") -> 1.079 | J53: =IFERROR(VLOOKUP(E53,'DATA MASTER'!$B$1:$R$3858,17,0),"") -> 102900 | K53: =IFERROR(VLOOKUP(E53,'DATA MASTER'!$B$1:$R$3858,16,0),"") -> 94200 | L53: =IFERROR(IF(F53="MTAB",12.5%*J53,7.5%*J53),"") -> 7717.5 | M53: =IFERROR(IF(F53="MTAB",19.011%*K53,14.488%*K53),"") -> 13647.696 | O53: 0 | R53: =IFERROR((((J53-L53)/1.11*(100-O53)%*G53)-(ROUNDDOWN(G53/Y53,0)*N53)),"") -> 343000 | S53: =IFERROR((K53-M53)/1.11*(100-O53)%*G53,"") -> 290278.57 | T53: =IFERROR(R53-S53,"") -> 52721.427 | U53: =IFERROR(I53*G53*700,"") -> 3021.2 | V53: =IFERROR(G53*I53/23000*1500000,"") -> 281.47826 | W53: =IFERROR(2%*R53*1.11,"") -> 7614.6 | X53: =IFERROR(T53-U53-V53-W53-Z53-AC53-AB53-AA53-AD53,"") -> 31804.149 | Y53: 1 | Z53: 0 | AA53: =IFERROR(ROUNDDOWN(G53/Y53,0)*P53,"") -> 0 | AB53: =IFERROR(IF(OR(D53="SALES008",D53="SALES010"),IF(MOD(G53,H53)=0,10000*G53/H53,10000*(ROUNDUP(G53/H53,0))),0),"") -> 10000 | AC53: 0 | AD53: 0 | AF53: AVEM001KBA | AG53: =SUMIF($E$8:$X$2162,AF53,$R$8:$R$2162)*1.11 -> 82600 | AH53: =SUMIF($E$8:$X$1048576,AF53,$X$8:$X$1048576) -> 2671.9274 | AI53: =AH53/AG53 -> 0.032347789
A54: 47 | B54: 46235 | C54: SO.AV.2026.08.00043 | D54: SALES006 | E54: AGEM005 | F54: =IFERROR(VLOOKUP(E54,'DATA MASTER'!$B$1:$R$3858,3,0),"") -> DIV 2 | G54: 14 | H54: =IFERROR(VLOOKUP(E54,'DATA MASTER'!$B$1:$R$3858,6,0),"") -> 4 | I54: =IFERROR(VLOOKUP(E54,'DATA MASTER'!$B$1:$R$3858,5,0),"") -> 4.68 | J54: =IFERROR(VLOOKUP(E54,'DATA MASTER'!$B$1:$R$3858,17,0),"") -> 112100 | K54: =IFERROR(VLOOKUP(E54,'DATA MASTER'!$B$1:$R$3858,16,0),"") -> 96500 | L54: =IFERROR(IF(F54="MTAB",12.5%*J54,7.5%*J54),"") -> 8407.5 | M54: =IFERROR(IF(F54="MTAB",19.011%*K54,14.488%*K54),"") -> 13980.92 | O54: 0 | R54: =IFERROR((((J54-L54)/1.11*(100-O54)%*G54)-(ROUNDDOWN(G54/Y54,0)*N54)),"") -> 1307833.3 | S54: =IFERROR((K54-M54)/1.11*(100-O54)%*G54,"") -> 1040781.2 | T54: =IFERROR(R54-S54,"") -> 267052.14 | U54: =IFERROR(I54*G54*700,"") -> 45864 | V54: =IFERROR(G54*I54/23000*1500000,"") -> 4273.0435 | W54: =IFERROR(2%*R54*1.11,"") -> 29033.9 | X54: =IFERROR(T54-U54-V54-W54-Z54-AC54-AB54-AA54-AD54,"") -> 187881.2 | Y54: 1 | Z54: 0 | AA54: =IFERROR(ROUNDDOWN(G54/Y54,0)*P54,"") -> 0 | AB54: =IFERROR(IF(OR(D54="SALES008",D54="SALES010"),IF(MOD(G54,H54)=0,10000*G54/H54,10000*(ROUNDUP(G54/H54,0))),0),"") -> 0 | AC54: 0 | AD54: 0 | AF54: AVEM001KBC | AG54: =SUMIF($E$8:$X$2162,AF54,$R$8:$R$2162)*1.11 -> 76300 | AH54: =SUMIF($E$8:$X$1048576,AF54,$X$8:$X$1048576) -> 5500.5922 | AI54: =AH54/AG54 -> 0.072091641
A55: 48 | B55: 46235 | C55: SO.AV.2026.08.00044 | D55: SALES019 | E55: AVSY001 | F55: =IFERROR(VLOOKUP(E55,'DATA MASTER'!$B$1:$R$3858,3,0),"") -> DIV 1 | G55: 24 | H55: =IFERROR(VLOOKUP(E55,'DATA MASTER'!$B$1:$R$3858,6,0),"") -> 24 | I55: =IFERROR(VLOOKUP(E55,'DATA MASTER'!$B$1:$R$3858,5,0),"") -> 1.23 | J55: =IFERROR(VLOOKUP(E55,'DATA MASTER'!$B$1:$R$3858,17,0),"") -> 99800 | K55: =IFERROR(VLOOKUP(E55,'DATA MASTER'!$B$1:$R$3858,16,0),"") -> 92100 | L55: =IFERROR(IF(F55="MTAB",12.5%*J55,7.5%*J55),"") -> 7485 | M55: =IFERROR(IF(F55="MTAB",19.011%*K55,14.488%*K55),"") -> 13343.448 | O55: 0 | P55: 60000 | Q55: 148 | R55: =IFERROR((((J55-L55)/1.11*(100-O55)%*G55)-(ROUNDDOWN(G55/Y55,0)*N55)),"") -> 1996000 | S55: =IFERROR((K55-M55)/1.11*(100-O55)%*G55,"") -> 1702844.4 | T55: =IFERROR(R55-S55,"") -> 293155.63 | U55: =IFERROR(I55*G55*700,"") -> 20664 | V55: =IFERROR(G55*I55/23000*1500000,"") -> 1925.2174 | W55: =IFERROR(2%*R55*1.11,"") -> 44311.2 | X55: =IFERROR(T55-U55-V55-W55-Z55-AC55-AB55-AA55-AD55,"") -> 156255.22 | Y55: 24 | Z55: 0 | AA55: =IFERROR(ROUNDDOWN(G55/Y55,0)*P55,"") -> 60000 | AB55: =IFERROR(IF(OR(D55="SALES008",D55="SALES010"),IF(MOD(G55,H55)=0,10000*G55/H55,10000*(ROUNDUP(G55/H55,0))),0),"") -> 0 | AC55: 0 | AD55: 10000 | AF55: AVEM005 | AG55: =SUMIF($E$8:$X$2162,AF55,$R$8:$R$2162)*1.11 -> 2.6023534e+08 | AH55: =SUMIF($E$8:$X$1048576,AF55,$X$8:$X$1048576) -> 19934914 | AI55: =AH55/AG55 -> 0.076603407
A56: 49 | B56: 46235 | C56: SO.AV.2026.08.00045 | D56: SALES012 | E56: AVEM025 | F56: =IFERROR(VLOOKUP(E56,'DATA MASTER'!$B$1:$R$3858,3,0),"") -> DIV 1 | G56: 2 | H56: =IFERROR(VLOOKUP(E56,'DATA MASTER'!$B$1:$R$3858,6,0),"") -> 1 | I56: =IFERROR(VLOOKUP(E56,'DATA MASTER'!$B$1:$R$3858,5,0),"") -> 26.02 | J56: =IFERROR(VLOOKUP(E56,'DATA MASTER'!$B$1:$R$3858,17,0),"") -> 876000 | K56: =IFERROR(VLOOKUP(E56,'DATA MASTER'!$B$1:$R$3858,16,0),"") -> 777200 | L56: =IFERROR(IF(F56="MTAB",12.5%*J56,7.5%*J56),"") -> 65700 | M56: =IFERROR(IF(F56="MTAB",19.011%*K56,14.488%*K56),"") -> 112600.74 | O56: 0 | R56: =IFERROR((((J56-L56)/1.11*(100-O56)%*G56)-(ROUNDDOWN(G56/Y56,0)*N56)),"") -> 1460000 | S56: =IFERROR((K56-M56)/1.11*(100-O56)%*G56,"") -> 1197476.2 | T56: =IFERROR(R56-S56,"") -> 262523.85 | U56: =IFERROR(I56*G56*700,"") -> 36428 | V56: =IFERROR(G56*I56/23000*1500000,"") -> 3393.913 | W56: =IFERROR(2%*R56*1.11,"") -> 32412 | X56: =IFERROR(T56-U56-V56-W56-Z56-AC56-AB56-AA56-AD56,"") -> 190289.94 | Y56: 1 | Z56: 0 | AA56: =IFERROR(ROUNDDOWN(G56/Y56,0)*P56,"") -> 0 | AB56: =IFERROR(IF(OR(D56="SALES008",D56="SALES010"),IF(MOD(G56,H56)=0,10000*G56/H56,10000*(ROUNDUP(G56/H56,0))),0),"") -> 0 | AC56: 0 | AD56: 0 | AF56: AVEM005KBA | AG56: =SUMIF($E$8:$X$2162,AF56,$R$8:$R$2162)*1.11 -> 4343850 | AH56: =SUMIF($E$8:$X$1048576,AF56,$X$8:$X$1048576) -> 247355.35 | AI56: =AH56/AG56 -> 0.056943805
A57: 50 | B57: 46235 | C57: SO.AV.2026.08.00046 | D57: SALES012 | E57: AVSY001 | F57: =IFERROR(VLOOKUP(E57,'DATA MASTER'!$B$1:$R$3858,3,0),"") -> DIV 1 | G57: 24 | H57: =IFERROR(VLOOKUP(E57,'DATA MASTER'!$B$1:$R$3858,6,0),"") -> 24 | I57: =IFERROR(VLOOKUP(E57,'DATA MASTER'!$B$1:$R$3858,5,0),"") -> 1.23 | J57: =IFERROR(VLOOKUP(E57,'DATA MASTER'!$B$1:$R$3858,17,0),"") -> 99800 | K57: =IFERROR(VLOOKUP(E57,'DATA MASTER'!$B$1:$R$3858,16,0),"") -> 92100 | L57: =IFERROR(IF(F57="MTAB",12.5%*J57,7.5%*J57),"") -> 7485 | M57: =IFERROR(IF(F57="MTAB",19.011%*K57,14.488%*K57),"") -> 13343.448 | O57: 0 | P57: 60000 | Q57: 148 | R57: =IFERROR((((J57-L57)/1.11*(100-O57)%*G57)-(ROUNDDOWN(G57/Y57,0)*N57)),"") -> 1996000 | S57: =IFERROR((K57-M57)/1.11*(100-O57)%*G57,"") -> 1702844.4 | T57: =IFERROR(R57-S57,"") -> 293155.63 | U57: =IFERROR(I57*G57*700,"") -> 20664 | V57: =IFERROR(G57*I57/23000*1500000,"") -> 1925.2174 | W57: =IFERROR(2%*R57*1.11,"") -> 44311.2 | X57: =IFERROR(T57-U57-V57-W57-Z57-AC57-AB57-AA57-AD57,"") -> 163477.44 | Y57: 24 | AA57: =IFERROR(ROUNDDOWN(G57/Y57,0)*P57,"") -> 60000 | AB57: =IFERROR(IF(OR(D57="SALES008",D57="SALES010"),IF(MOD(G57,H57)=0,10000*G57/H57,10000*(ROUNDUP(G57/H57,0))),0),"") -> 0 | AC57: =Z57*R57*1.11 -> 0 | AD57: 2777.7778 | AF57: AVEM025 | AG57: =SUMIF($E$8:$X$2162,AF57,$R$8:$R$2162)*1.11 -> 2.058162e+08 | AH57: =SUMIF($E$8:$X$1048576,AF57,$X$8:$X$1048576) -> 18015872 | AI57: =AH57/AG57 -> 0.087533791
A58: 51 | B58: 46235 | C58: SO.AV.2026.08.00048 | D58: SALES006 | E58: AVSY200 | F58: =IFERROR(VLOOKUP(E58,'DATA MASTER'!$B$1:$R$3858,3,0),"") -> DIV 1 | G58: 60 | H58: =IFERROR(VLOOKUP(E58,'DATA MASTER'!$B$1:$R$3858,6,0),"") -> 72 | I58: =IFERROR(VLOOKUP(E58,'DATA MASTER'!$B$1:$R$3858,5,0),"") -> 0.245333 | J58: =IFERROR(VLOOKUP(E58,'DATA MASTER'!$B$1:$R$3858,17,0),"") -> 27908.333 | K58: =IFERROR(VLOOKUP(E58,'DATA MASTER'!$B$1:$R$3858,16,0),"") -> 25850 | L58: =IFERROR(IF(F58="MTAB",12.5%*J58,7.5%*J58),"") -> 2093.125 | M58: =IFERROR(IF(F58="MTAB",19.011%*K58,14.488%*K58),"") -> 3745.148 | O58: 0 | R58: =IFERROR((((J58-L58)/1.11*(100-O58)%*G58)-(ROUNDDOWN(G58/Y58,0)*N58)),"") -> 1395416.7 | S58: =IFERROR((K58-M58)/1.11*(100-O58)%*G58,"") -> 1194856.9 | T58: =IFERROR(R58-S58,"") -> 200559.8 | U58: =IFERROR(I58*G58*700,"") -> 10303.986 | V58: =IFERROR(G58*I58/23000*1500000,"") -> 959.9987 | W58: =IFERROR(2%*R58*1.11,"") -> 30978.25 | X58: =IFERROR(T58-U58-V58-W58-Z58-AC58-AB58-AA58-AD58,"") -> 158317.57 | Y58: 1 | AA58: =IFERROR(ROUNDDOWN(G58/Y58,0)*P58,"") -> 0 | AB58: =IFERROR(IF(OR(D58="SALES008",D58="SALES010"),IF(MOD(G58,H58)=0,10000*G58/H58,10000*(ROUNDUP(G58/H58,0))),0),"") -> 0 | AC58: =Z58*R58*1.11 -> 0 | AD58: 0 | AF58: AVEM025KPBA | AG58: =SUMIF($E$8:$X$2162,AF58,$R$8:$R$2162)*1.11 -> 4392675 | AH58: =SUMIF($E$8:$X$1048576,AF58,$X$8:$X$1048576) -> 251356.29 | AI58: =AH58/AG58 -> 0.057221691
A59: 52 | B59: 46235 | C59: SO.AV.2026.08.00049 | D59: SALES019 | E59: AVEM005 | F59: =IFERROR(VLOOKUP(E59,'DATA MASTER'!$B$1:$R$3858,3,0),"") -> DIV 1 | G59: 1 | H59: =IFERROR(VLOOKUP(E59,'DATA MASTER'!$B$1:$R$3858,6,0),"") -> 4 | I59: =IFERROR(VLOOKUP(E59,'DATA MASTER'!$B$1:$R$3858,5,0),"") -> 5.388 | J59: =IFERROR(VLOOKUP(E59,'DATA MASTER'!$B$1:$R$3858,17,0),"") -> 185700 | K59: =IFERROR(VLOOKUP(E59,'DATA MASTER'!$B$1:$R$3858,16,0),"") -> 165300 | L59: =IFERROR(IF(F59="MTAB",12.5%*J59,7.5%*J59),"") -> 13927.5 | M59: =IFERROR(IF(F59="MTAB",19.011%*K59,14.488%*K59),"") -> 23948.664 | O59: 0 | R59: =IFERROR((((J59-L59)/1.11*(100-O59)%*G59)-(ROUNDDOWN(G59/Y59,0)*N59)),"") -> 154750 | S59: =IFERROR((K59-M59)/1.11*(100-O59)%*G59,"") -> 127343.55 | T59: =IFERROR(R59-S59,"") -> 27406.454 | U59: =IFERROR(I59*G59*700,"") -> 3771.6 | V59: =IFERROR(G59*I59/23000*1500000,"") -> 351.3913 | W59: =IFERROR(2%*R59*1.11,"") -> 3435.45 | X59: =IFERROR(T59-U59-V59-W59-Z59-AC59-AB59-AA59-AD59,"") -> 19848.013 | Y59: 1 | AA59: =IFERROR(ROUNDDOWN(G59/Y59,0)*P59,"") -> 0 | AB59: =IFERROR(IF(OR(D59="SALES008",D59="SALES010"),IF(MOD(G59,H59)=0,10000*G59/H59,10000*(ROUNDUP(G59/H59,0))),0),"") -> 0 | AC59: =Z59*R59*1.11 -> 0 | AD59: 0 | AF59: AVEM025KPBB | AG59: =SUMIF($E$8:$X$2162,AF59,$R$8:$R$2162)*1.11 -> 704550 | AH59: =SUMIF($E$8:$X$1048576,AF59,$X$8:$X$1048576) -> 37115.577 | AI59: =AH59/AG59 -> 0.052679834
A60: 53 | B60: 46235 | C60: SO.GM.2026.08.00001 | D60: SALES002 | E60: AREM020 | F60: =IFERROR(VLOOKUP(E60,'DATA MASTER'!$B$1:$R$3858,3,0),"") -> DIV 1-AREM | G60: 1 | H60: =IFERROR(VLOOKUP(E60,'DATA MASTER'!$B$1:$R$3858,6,0),"") -> 1 | I60: =IFERROR(VLOOKUP(E60,'DATA MASTER'!$B$1:$R$3858,5,0),"") -> 21.03 | J60: =IFERROR(VLOOKUP(E60,'DATA MASTER'!$B$1:$R$3858,17,0),"") -> 285500 | K60: =IFERROR(VLOOKUP(E60,'DATA MASTER'!$B$1:$R$3858,16,0),"") -> 224700 | L60: =IFERROR(IF(F60="MTAB",12.5%*J60,7.5%*J60),"") -> 21412.5 | M60: =IFERROR(IF(F60="MTAB",19.011%*K60,14.488%*K60),"") -> 32554.536 | O60: 0 | R60: =IFERROR((((J60-L60)/1.11*(100-O60)%*G60)-(ROUNDDOWN(G60/Y60,0)*N60)),"") -> 237916.67 | S60: =IFERROR((K60-M60)/1.11*(100-O60)%*G60,"") -> 173104.02 | T60: =IFERROR(R60-S60,"") -> 64812.645 | U60: =IFERROR(I60*G60*700,"") -> 14721 | V60: =IFERROR(G60*I60/23000*1500000,"") -> 1371.5217 | W60: =IFERROR(2%*R60*1.11,"") -> 5281.75 | X60: =IFERROR(T60-U60-V60-W60-Z60-AC60-AB60-AA60-AD60,"") -> 43438.373 | Y60: 1 | Z60: 0 | AA60: =IFERROR(ROUNDDOWN(G60/Y60,0)*P60,"") -> 0 | AB60: =IFERROR(IF(OR(D60="SALES008",D60="SALES010"),IF(MOD(G60,H60)=0,10000*G60/H60,10000*(ROUNDUP(G60/H60,0))),0),"") -> 0 | AC60: 0 | AD60: 0 | AF60: AVEP001 | AG60: =SUMIF($E$8:$X$2162,AF60,$R$8:$R$2162)*1.11 -> 1440040 | AH60: =SUMIF($E$8:$X$1048576,AF60,$X$8:$X$1048576) -> 146408.28 | AI60: =AH60/AG60 -> 0.1016696
A61: 54 | B61: 46235 | C61: SO.GM.2026.08.00003 | D61: SALES014 | E61: AREM020 | F61: =IFERROR(VLOOKUP(E61,'DATA MASTER'!$B$1:$R$3858,3,0),"") -> DIV 1-AREM | G61: 1 | H61: =IFERROR(VLOOKUP(E61,'DATA MASTER'!$B$1:$R$3858,6,0),"") -> 1 | I61: =IFERROR(VLOOKUP(E61,'DATA MASTER'!$B$1:$R$3858,5,0),"") -> 21.03 | J61: =IFERROR(VLOOKUP(E61,'DATA MASTER'!$B$1:$R$3858,17,0),"") -> 285500 | K61: =IFERROR(VLOOKUP(E61,'DATA MASTER'!$B$1:$R$3858,16,0),"") -> 224700 | L61: =IFERROR(IF(F61="MTAB",12.5%*J61,7.5%*J61),"") -> 21412.5 | M61: =IFERROR(IF(F61="MTAB",19.011%*K61,14.488%*K61),"") -> 32554.536 | O61: 0 | R61: =IFERROR((((J61-L61)/1.11*(100-O61)%*G61)-(ROUNDDOWN(G61/Y61,0)*N61)),"") -> 237916.67 | S61: =IFERROR((K61-M61)/1.11*(100-O61)%*G61,"") -> 173104.02 | T61: =IFERROR(R61-S61,"") -> 64812.645 | U61: =IFERROR(I61*G61*700,"") -> 14721 | V61: =IFERROR(G61*I61/23000*1500000,"") -> 1371.5217 | W61: =IFERROR(2%*R61*1.11,"") -> 5281.75 | X61: =IFERROR(T61-U61-V61-W61-Z61-AC61-AB61-AA61-AD61,"") -> 39592.219 | Y61: 1 | Z61: 0 | AA61: =IFERROR(ROUNDDOWN(G61/Y61,0)*P61,"") -> 0 | AB61: =IFERROR(IF(OR(D61="SALES008",D61="SALES010"),IF(MOD(G61,H61)=0,10000*G61/H61,10000*(ROUNDUP(G61/H61,0))),0),"") -> 0 | AC61: 0 | AD61: 3846.1538 | AF61: AVFI001 | AG61: =SUMIF($E$8:$X$2162,AF61,$R$8:$R$2162)*1.11 -> 1234320 | AH61: =SUMIF($E$8:$X$1048576,AF61,$X$8:$X$1048576) -> 121778.24 | AI61: =AH61/AG61 -> 0.098660186
A62: 55 | B62: 46235 | C62: SO.GM.2026.08.00004 | D62: SALES001 | E62: AREM005 | F62: =IFERROR(VLOOKUP(E62,'DATA MASTER'!$B$1:$R$3858,3,0),"") -> DIV 1-AREM | G62: 4 | H62: =IFERROR(VLOOKUP(E62,'DATA MASTER'!$B$1:$R$3858,6,0),"") -> 4 | I62: =IFERROR(VLOOKUP(E62,'DATA MASTER'!$B$1:$R$3858,5,0),"") -> 5.19 | J62: =IFERROR(VLOOKUP(E62,'DATA MASTER'!$B$1:$R$3858,17,0),"") -> 76700 | K62: =IFERROR(VLOOKUP(E62,'DATA MASTER'!$B$1:$R$3858,16,0),"") -> 61100 | L62: =IFERROR(IF(F62="MTAB",12.5%*J62,7.5%*J62),"") -> 5752.5 | M62: =IFERROR(IF(F62="MTAB",19.011%*K62,14.488%*K62),"") -> 8852.168 | O62: 0 | R62: =IFERROR((((J62-L62)/1.11*(100-O62)%*G62)-(ROUNDDOWN(G62/Y62,0)*N62)),"") -> 255666.67 | S62: =IFERROR((K62-M62)/1.11*(100-O62)%*G62,"") -> 188280.48 | T62: =IFERROR(R62-S62,"") -> 67386.191 | U62: =IFERROR(I62*G62*700,"") -> 14532 | V62: =IFERROR(G62*I62/23000*1500000,"") -> 1353.913 | W62: =IFERROR(2%*R62*1.11,"") -> 5675.8 | X62: =IFERROR(T62-U62-V62-W62-Z62-AC62-AB62-AA62-AD62,"") -> 45824.478 | Y62: 1 | Z62: 0 | AA62: =IFERROR(ROUNDDOWN(G62/Y62,0)*P62,"") -> 0 | AB62: =IFERROR(IF(OR(D62="SALES008",D62="SALES010"),IF(MOD(G62,H62)=0,10000*G62/H62,10000*(ROUNDUP(G62/H62,0))),0),"") -> 0 | AC62: 0 | AD62: 0 | AF62: AVFI200 | AG62: =SUMIF($E$8:$X$2162,AF62,$R$8:$R$2162)*1.11 -> 317460 | AH62: =SUMIF($E$8:$X$1048576,AF62,$X$8:$X$1048576) -> 19506.982 | AI62: =AH62/AG62 -> 0.061447054
A63: 57 | B63: 46235 | C63: SO.GM.2026.08.00004 | D63: SALES001 | E63: AREM005KSW | F63: =IFERROR(VLOOKUP(E63,'DATA MASTER'!$B$1:$R$3858,3,0),"") -> DIV 1-AREM | G63: 4 | H63: =IFERROR(VLOOKUP(E63,'DATA MASTER'!$B$1:$R$3858,6,0),"") -> 4 | I63: =IFERROR(VLOOKUP(E63,'DATA MASTER'!$B$1:$R$3858,5,0),"") -> 5.35 | J63: =IFERROR(VLOOKUP(E63,'DATA MASTER'!$B$1:$R$3858,17,0),"") -> 76700 | K63: =IFERROR(VLOOKUP(E63,'DATA MASTER'!$B$1:$R$3858,16,0),"") -> 61100 | L63: =IFERROR(IF(F63="MTAB",12.5%*J63,7.5%*J63),"") -> 5752.5 | M63: =IFERROR(IF(F63="MTAB",19.011%*K63,14.488%*K63),"") -> 8852.168 | O63: 10 | R63: =IFERROR((((J63-L63)/1.11*(100-O63)%*G63)-(ROUNDDOWN(G63/Y63,0)*N63)),"") -> 230100 | S63: =IFERROR((K63-M63)/1.11*(100-O63)%*G63,"") -> 169452.43 | T63: =IFERROR(R63-S63,"") -> 60647.572 | U63: =IFERROR(I63*G63*700,"") -> 14980 | V63: =IFERROR(G63*I63/23000*1500000,"") -> 1395.6522 | W63: =IFERROR(2%*R63*1.11,"") -> 5108.22 | X63: =IFERROR(T63-U63-V63-W63-Z63-AC63-AB63-AA63-AD63,"") -> 39163.7 | Y63: 1 | Z63: 0 | AA63: =IFERROR(ROUNDDOWN(G63/Y63,0)*P63,"") -> 0 | AB63: =IFERROR(IF(OR(D63="SALES008",D63="SALES010"),IF(MOD(G63,H63)=0,10000*G63/H63,10000*(ROUNDUP(G63/H63,0))),0),"") -> 0 | AC63: 0 | AD63: 0 | AF63: AVFO001 | AG63: =SUMIF($E$8:$X$2162,AF63,$R$8:$R$2162)*1.11 -> 214415 | AH63: =SUMIF($E$8:$X$1048576,AF63,$X$8:$X$1048576) -> 22904.305 | AI63: =AH63/AG63 -> 0.10682231
A64: 58 | B64: 46235 | C64: SO.GM.2026.08.00005 | D64: SALES001 | E64: AREM020 | F64: =IFERROR(VLOOKUP(E64,'DATA MASTER'!$B$1:$R$3858,3,0),"") -> DIV 1-AREM | G64: 20 | H64: =IFERROR(VLOOKUP(E64,'DATA MASTER'!$B$1:$R$3858,6,0),"") -> 1 | I64: =IFERROR(VLOOKUP(E64,'DATA MASTER'!$B$1:$R$3858,5,0),"") -> 21.03 | J64: =IFERROR(VLOOKUP(E64,'DATA MASTER'!$B$1:$R$3858,17,0),"") -> 285500 | K64: =IFERROR(VLOOKUP(E64,'DATA MASTER'!$B$1:$R$3858,16,0),"") -> 224700 | L64: =IFERROR(IF(F64="MTAB",12.5%*J64,7.5%*J64),"") -> 21412.5 | M64: =IFERROR(IF(F64="MTAB",19.011%*K64,14.488%*K64),"") -> 32554.536 | O64: 0 | Q64: =VLOOKUP(#REF!,#REF!,1,0) -> #REF! | R64: =IFERROR((((J64-L64)/1.11*(100-O64)%*G64)-(ROUNDDOWN(G64/Y64,0)*N64)),"") -> 4758333.3 | S64: =IFERROR((K64-M64)/1.11*(100-O64)%*G64,"") -> 3462080.4 | T64: =IFERROR(R64-S64,"") -> 1296252.9 | U64: =IFERROR(I64*G64*700,"") -> 294420 | V64: =IFERROR(G64*I64/23000*1500000,"") -> 27430.435 | W64: 0 | X64: =IFERROR(T64-U64-V64-W64-Z64-AC64-AB64-AA64-AD64,"") | Y64: 1 | Z64: =VLOOKUP(Q64,#REF!,4,0) -> #REF! | AA64: =IFERROR(ROUNDDOWN(G64/Y64,0)*P64,"") -> 0 | AB64: =IFERROR(IF(OR(D64="SALES008",D64="SALES010"),IF(MOD(G64,H64)=0,10000*G64/H64,10000*(ROUNDUP(G64/H64,0))),0),"") -> 0 | AC64: =Z64*R64*1.11 -> #REF! | AD64: 0 | AF64: AVFO005 | AG64: =SUMIF($E$8:$X$2162,AF64,$R$8:$R$2162)*1.11 -> 2049430 | AH64: =SUMIF($E$8:$X$1048576,AF64,$X$8:$X$1048576) -> 214809.54 | AI64: =AH64/AG64 -> 0.10481429
A65: 59 | B65: 46235 | C65: SO.GM.2026.08.00006 | D65: SALES001 | E65: AREM020 | F65: =IFERROR(VLOOKUP(E65,'DATA MASTER'!$B$1:$R$3858,3,0),"") -> DIV 1-AREM | G65: 2 | H65: =IFERROR(VLOOKUP(E65,'DATA MASTER'!$B$1:$R$3858,6,0),"") -> 1 | I65: =IFERROR(VLOOKUP(E65,'DATA MASTER'!$B$1:$R$3858,5,0),"") -> 21.03 | J65: =IFERROR(VLOOKUP(E65,'DATA MASTER'!$B$1:$R$3858,17,0),"") -> 285500 | K65: =IFERROR(VLOOKUP(E65,'DATA MASTER'!$B$1:$R$3858,16,0),"") -> 224700 | L65: =IFERROR(IF(F65="MTAB",12.5%*J65,7.5%*J65),"") -> 21412.5 | M65: =IFERROR(IF(F65="MTAB",19.011%*K65,14.488%*K65),"") -> 32554.536 | O65: 0 | Q65: =VLOOKUP(#REF!,#REF!,1,0) -> #REF! | R65: =IFERROR((((J65-L65)/1.11*(100-O65)%*G65)-(ROUNDDOWN(G65/Y65,0)*N65)),"") -> 475833.33 | S65: =IFERROR((K65-M65)/1.11*(100-O65)%*G65,"") -> 346208.04 | T65: =IFERROR(R65-S65,"") -> 129625.29 | U65: =IFERROR(I65*G65*700,"") -> 29442 | V65: =IFERROR(G65*I65/23000*1500000,"") -> 2743.0435 | W65: 0 | X65: =IFERROR(T65-U65-V65-W65-Z65-AC65-AB65-AA65-AD65,"") | Y65: 1 | Z65: =VLOOKUP(Q65,#REF!,4,0) -> #REF! | AA65: =IFERROR(ROUNDDOWN(G65/Y65,0)*P65,"") -> 0 | AB65: =IFERROR(IF(OR(D65="SALES008",D65="SALES010"),IF(MOD(G65,H65)=0,10000*G65/H65,10000*(ROUNDUP(G65/H65,0))),0),"") -> 0 | AC65: =Z65*R65*1.11 -> #REF! | AD65: 0 | AF65: AVGO001 | AG65: =SUMIF($E$8:$X$2162,AF65,$R$8:$R$2162)*1.11 -> 63177.5 | AH65: =SUMIF($E$8:$X$1048576,AF65,$X$8:$X$1048576) -> 6747.4189 | AI65: =AH65/AG65 -> 0.10680098
A66: 60 | B66: 46237 | C66: SO.AV.2026.08.00047 | D66: SALES003 | E66: AVWA005 | F66: =IFERROR(VLOOKUP(E66,'DATA MASTER'!$B$1:$R$3858,3,0),"") -> DIV 2 | G66: 4 | H66: =IFERROR(VLOOKUP(E66,'DATA MASTER'!$B$1:$R$3858,6,0),"") -> 1 | I66: =IFERROR(VLOOKUP(E66,'DATA MASTER'!$B$1:$R$3858,5,0),"") -> 5.14 | J66: =IFERROR(VLOOKUP(E66,'DATA MASTER'!$B$1:$R$3858,17,0),"") -> 120300 | K66: =IFERROR(VLOOKUP(E66,'DATA MASTER'!$B$1:$R$3858,16,0),"") -> 104600 | L66: =IFERROR(IF(F66="MTAB",12.5%*J66,7.5%*J66),"") -> 9022.5 | M66: =IFERROR(IF(F66="MTAB",19.011%*K66,14.488%*K66),"") -> 15154.448 | O66: 0 | R66: =IFERROR((((J66-L66)/1.11*(100-O66)%*G66)-(ROUNDDOWN(G66/Y66,0)*N66)),"") -> 401000 | S66: =IFERROR((K66-M66)/1.11*(100-O66)%*G66,"") -> 322326.31 | T66: =IFERROR(R66-S66,"") -> 78673.686 | U66: =IFERROR(I66*G66*700,"") -> 14392 | V66: =IFERROR(G66*I66/23000*1500000,"") -> 1340.8696 | W66: =IFERROR(2%*R66*1.11,"") -> 8902.2 | X66: =IFERROR(T66-U66-V66-W66-Z66-AC66-AB66-AA66-AD66,"") -> 54038.617 | Y66: 1 | Z66: 0 | AA66: =IFERROR(ROUNDDOWN(G66/Y66,0)*P66,"") -> 0 | AB66: =IFERROR(IF(OR(D66="SALES008",D66="SALES010"),IF(MOD(G66,H66)=0,10000*G66/H66,10000*(ROUNDUP(G66/H66,0))),0),"") -> 0 | AC66: 0 | AD66: 0 | AF66: AVGO005 | AG66: =SUMIF($E$8:$X$2162,AF66,$R$8:$R$2162)*1.11 -> 10296360 | AH66: =SUMIF($E$8:$X$1048576,AF66,$X$8:$X$1048576) -> 1010726 | AI66: =AH66/AG66 -> 0.098163431
A67: 61 | B67: 46237 | C67: SO.AV.2026.08.00050 | D67: SALES007 | E67: AVLA005 | F67: =IFERROR(VLOOKUP(E67,'DATA MASTER'!$B$1:$R$3858,3,0),"") -> DIV 1 | G67: 2 | H67: =IFERROR(VLOOKUP(E67,'DATA MASTER'!$B$1:$R$3858,6,0),"") -> 4 | I67: =IFERROR(VLOOKUP(E67,'DATA MASTER'!$B$1:$R$3858,5,0),"") -> 5.218 | J67: =IFERROR(VLOOKUP(E67,'DATA MASTER'!$B$1:$R$3858,17,0),"") -> 328200 | K67: =IFERROR(VLOOKUP(E67,'DATA MASTER'!$B$1:$R$3858,16,0),"") -> 293300 | L67: =IFERROR(IF(F67="MTAB",12.5%*J67,7.5%*J67),"") -> 24615 | M67: =IFERROR(IF(F67="MTAB",19.011%*K67,14.488%*K67),"") -> 42493.304 | O67: 10 | R67: =IFERROR((((J67-L67)/1.11*(100-O67)%*G67)-(ROUNDDOWN(G67/Y67,0)*N67)),"") -> 492300 | S67: =IFERROR((K67-M67)/1.11*(100-O67)%*G67,"") -> 406713.56 | T67: =IFERROR(R67-S67,"") -> 85586.439 | U67: =IFERROR(I67*G67*700,"") -> 7305.2 | V67: =IFERROR(G67*I67/23000*1500000,"") -> 680.6087 | W67: =IFERROR(2%*R67*1.11,"") -> 10929.06 | X67: =IFERROR(T67-U67-V67-W67-Z67-AC67-AB67-AA67-AD67,"") -> 66671.57 | Y67: 1 | Z67: 0 | AA67: =IFERROR(ROUNDDOWN(G67/Y67,0)*P67,"") -> 0 | AB67: =IFERROR(IF(OR(D67="SALES008",D67="SALES010"),IF(MOD(G67,H67)=0,10000*G67/H67,10000*(ROUNDUP(G67/H67,0))),0),"") -> 0 | AC67: 0 | AD67: 0 | AF67: AVGO005KBB | AG67: =SUMIF($E$8:$X$2162,AF67,$R$8:$R$2162)*1.11 -> 738500 | AH67: =SUMIF($E$8:$X$1048576,AF67,$X$8:$X$1048576) -> 36640.864 | AI67: =AH67/AG67 -> 0.049615253
A68: 62 | B68: 46237 | C68: SO.AV.2026.08.00051 | D68: SALES007 | E68: AVEM005 | F68: =IFERROR(VLOOKUP(E68,'DATA MASTER'!$B$1:$R$3858,3,0),"") -> DIV 1 | G68: 8 | H68: =IFERROR(VLOOKUP(E68,'DATA MASTER'!$B$1:$R$3858,6,0),"") -> 4 | I68: =IFERROR(VLOOKUP(E68,'DATA MASTER'!$B$1:$R$3858,5,0),"") -> 5.388 | J68: =IFERROR(VLOOKUP(E68,'DATA MASTER'!$B$1:$R$3858,17,0),"") -> 185700 | K68: =IFERROR(VLOOKUP(E68,'DATA MASTER'!$B$1:$R$3858,16,0),"") -> 165300 | L68: =IFERROR(IF(F68="MTAB",12.5%*J68,7.5%*J68),"") -> 13927.5 | M68: =IFERROR(IF(F68="MTAB",19.011%*K68,14.488%*K68),"") -> 23948.664 | O68: 0 | R68: =IFERROR((((J68-L68)/1.11*(100-O68)%*G68)-(ROUNDDOWN(G68/Y68,0)*N68)),"") -> 1238000 | S68: =IFERROR((K68-M68)/1.11*(100-O68)%*G68,"") -> 1018748.4 | T68: =IFERROR(R68-S68,"") -> 219251.63 | U68: =IFERROR(I68*G68*700,"") -> 30172.8 | V68: =IFERROR(G68*I68/23000*1500000,"") -> 2811.1304 | W68: =IFERROR(2%*R68*1.11,"") -> 27483.6 | X68: =IFERROR(T68-U68-V68-W68-Z68-AC68-AB68-AA68-AD68,"") -> 148257.79 | Y68: 1 | AA68: =IFERROR(ROUNDDOWN(G68/Y68,0)*P68,"") -> 0 | AB68: =IFERROR(IF(OR(D68="SALES008",D68="SALES010"),IF(MOD(G68,H68)=0,10000*G68/H68,10000*(ROUNDUP(G68/H68,0))),0),"") -> 0 | AC68: =Z68*R68*1.11 -> 0 | AD68: 10526.316 | AF68: AVGO005KBC | AG68: =SUMIF($E$8:$X$2162,AF68,$R$8:$R$2162)*1.11 -> 709100 | AH68: =SUMIF($E$8:$X$1048576,AF68,$X$8:$X$1048576) -> 36176.228 | AI68: =AH68/AG68 -> 0.051017103
A69: 63 | B69: 46237 | C69: SO.AV.2026.08.00051 | D69: SALES007 | E69: AVEM025 | F69: =IFERROR(VLOOKUP(E69,'DATA MASTER'!$B$1:$R$3858,3,0),"") -> DIV 1 | G69: 3 | H69: =IFERROR(VLOOKUP(E69,'DATA MASTER'!$B$1:$R$3858,6,0),"") -> 1 | I69: =IFERROR(VLOOKUP(E69,'DATA MASTER'!$B$1:$R$3858,5,0),"") -> 26.02 | J69: =IFERROR(VLOOKUP(E69,'DATA MASTER'!$B$1:$R$3858,17,0),"") -> 876000 | K69: =IFERROR(VLOOKUP(E69,'DATA MASTER'!$B$1:$R$3858,16,0),"") -> 777200 | L69: =IFERROR(IF(F69="MTAB",12.5%*J69,7.5%*J69),"") -> 65700 | M69: =IFERROR(IF(F69="MTAB",19.011%*K69,14.488%*K69),"") -> 112600.74 | O69: 0 | R69: =IFERROR((((J69-L69)/1.11*(100-O69)%*G69)-(ROUNDDOWN(G69/Y69,0)*N69)),"") -> 2190000 | S69: =IFERROR((K69-M69)/1.11*(100-O69)%*G69,"") -> 1796214.2 | T69: =IFERROR(R69-S69,"") -> 393785.77 | U69: =IFERROR(I69*G69*700,"") -> 54642 | V69: =IFERROR(G69*I69/23000*1500000,"") -> 5090.8696 | W69: =IFERROR(2%*R69*1.11,"") -> 48618 | X69: =IFERROR(T69-U69-V69-W69-Z69-AC69-AB69-AA69-AD69,"") -> 274908.59 | Y69: 1 | AA69: =IFERROR(ROUNDDOWN(G69/Y69,0)*P69,"") -> 0 | AB69: =IFERROR(IF(OR(D69="SALES008",D69="SALES010"),IF(MOD(G69,H69)=0,10000*G69/H69,10000*(ROUNDUP(G69/H69,0))),0),"") -> 0 | AC69: =Z69*R69*1.11 -> 0 | AD69: 10526.316 | AF69: AVGO025 | AG69: =SUMIF($E$8:$X$2162,AF69,$R$8:$R$2162)*1.11 -> 70430888 | AH69: =SUMIF($E$8:$X$1048576,AF69,$X$8:$X$1048576) -> 1141767.8 | AI69: =AH69/AG69 -> 0.016211181
A70: 64 | B70: 46237 | C70: SO.AV.2026.08.00052 | D70: SALES006 | E70: AGEM005 | F70: =IFERROR(VLOOKUP(E70,'DATA MASTER'!$B$1:$R$3858,3,0),"") -> DIV 2 | G70: 16 | H70: =IFERROR(VLOOKUP(E70,'DATA MASTER'!$B$1:$R$3858,6,0),"") -> 4 | I70: =IFERROR(VLOOKUP(E70,'DATA MASTER'!$B$1:$R$3858,5,0),"") -> 4.68 | J70: =IFERROR(VLOOKUP(E70,'DATA MASTER'!$B$1:$R$3858,17,0),"") -> 112100 | K70: =IFERROR(VLOOKUP(E70,'DATA MASTER'!$B$1:$R$3858,16,0),"") -> 96500 | L70: =IFERROR(IF(F70="MTAB",12.5%*J70,7.5%*J70),"") -> 8407.5 | M70: =IFERROR(IF(F70="MTAB",19.011%*K70,14.488%*K70),"") -> 13980.92 | O70: 0 | R70: =IFERROR((((J70-L70)/1.11*(100-O70)%*G70)-(ROUNDDOWN(G70/Y70,0)*N70)),"") -> 1494666.7 | S70: =IFERROR((K70-M70)/1.11*(100-O70)%*G70,"") -> 1189464.2 | T70: =IFERROR(R70-S70,"") -> 305202.45 | U70: =IFERROR(I70*G70*700,"") -> 52416 | V70: =IFERROR(G70*I70/23000*1500000,"") -> 4883.4783 | W70: =IFERROR(2%*R70*1.11,"") -> 33181.6 | X70: =IFERROR(T70-U70-V70-W70-Z70-AC70-AB70-AA70-AD70,"") -> 202221.37 | Y70: =IF(E70="avem005",4,1) -> 1 | Z70: 0 | AA70: =IFERROR(ROUNDDOWN(G70/Y70,0)*P70,"") -> 0 | AB70: =IFERROR(IF(OR(D70="SALES008",D70="SALES010"),IF(MOD(G70,H70)=0,10000*G70/H70,10000*(ROUNDUP(G70/H70,0))),0),"") -> 0 | AC70: 0 | AD70: 12500 | AF70: AVGO025KPBA | AG70: =SUMIF($E$8:$X$2162,AF70,$R$8:$R$2162)*1.11 -> 1826475 | AH70: =SUMIF($E$8:$X$1048576,AF70,$X$8:$X$1048576) -> 92606.763 | AI70: =AH70/AG70 -> 0.050702453
A71: 65 | B71: 46237 | C71: SO.AV.2026.08.00053 | D71: SALES002 | E71: NOBU050 | F71: =IFERROR(VLOOKUP(E71,'DATA MASTER'!$B$1:$R$3858,3,0),"") -> DIV 2 | G71: 3 | H71: =IFERROR(VLOOKUP(E71,'DATA MASTER'!$B$1:$R$3858,6,0),"") -> 54 | I71: =IFERROR(VLOOKUP(E71,'DATA MASTER'!$B$1:$R$3858,5,0),"") -> 0.92 | J71: =IFERROR(VLOOKUP(E71,'DATA MASTER'!$B$1:$R$3858,17,0),"") -> 34300 | K71: =IFERROR(VLOOKUP(E71,'DATA MASTER'!$B$1:$R$3858,16,0),"") -> 30700 | L71: =IFERROR(IF(F71="MTAB",12.5%*J71,7.5%*J71),"") -> 2572.5 | M71: =IFERROR(IF(F71="MTAB",19.011%*K71,14.488%*K71),"") -> 4447.816 | O71: 0 | R71: =IFERROR((((J71-L71)/1.11*(100-O71)%*G71)-(ROUNDDOWN(G71/Y71,0)*N71)),"") -> 85750 | S71: =IFERROR((K71-M71)/1.11*(100-O71)%*G71,"") -> 70951.849 | T71: =IFERROR(R71-S71,"") -> 14798.151 | U71: =IFERROR(I71*G71*700,"") -> 1932 | V71: =IFERROR(G71*I71/23000*1500000,"") -> 180 | W71: =IFERROR(2%*R71*1.11,"") -> 1903.65 | X71: =IFERROR(T71-U71-V71-W71-Z71-AC71-AB71-AA71-AD71,"") -> 7657.5014 | Y71: 1 | Z71: 0 | AA71: =IFERROR(ROUNDDOWN(G71/Y71,0)*P71,"") -> 0 | AB71: =IFERROR(IF(OR(D71="SALES008",D71="SALES010"),IF(MOD(G71,H71)=0,10000*G71/H71,10000*(ROUNDUP(G71/H71,0))),0),"") -> 0 | AC71: 0 | AD71: 3125 | AF71: AVGO025KPBB | AG71: =SUMIF($E$8:$X$2162,AF71,$R$8:$R$2162)*1.11 -> 1757175 | AH71: =SUMIF($E$8:$X$1048576,AF71,$X$8:$X$1048576) -> 91924.886 | AI71: =AH71/AG71 -> 0.052314019
A72: 66 | B72: 46237 | C72: SO.AV.2026.08.00054 | D72: SALES001 | E72: NODR004 | F72: =IFERROR(VLOOKUP(E72,'DATA MASTER'!$B$1:$R$3858,3,0),"") -> DIV 2 | G72: 4 | H72: =IFERROR(VLOOKUP(E72,'DATA MASTER'!$B$1:$R$3858,6,0),"") -> 4 | I72: =IFERROR(VLOOKUP(E72,'DATA MASTER'!$B$1:$R$3858,5,0),"") -> 4.24 | J72: =IFERROR(VLOOKUP(E72,'DATA MASTER'!$B$1:$R$3858,17,0),"") -> 310600 | K72: =IFERROR(VLOOKUP(E72,'DATA MASTER'!$B$1:$R$3858,16,0),"") -> 283000 | L72: =IFERROR(IF(F72="MTAB",12.5%*J72,7.5%*J72),"") -> 23295 | M72: =IFERROR(IF(F72="MTAB",19.011%*K72,14.488%*K72),"") -> 41001.04 | O72: 0 | R72: =IFERROR((((J72-L72)/1.11*(100-O72)%*G72)-(ROUNDDOWN(G72/Y72,0)*N72)),"") -> 1035333.3 | S72: =IFERROR((K72-M72)/1.11*(100-O72)%*G72,"") -> 872068.32 | T72: =IFERROR(R72-S72,"") -> 163265.01 | U72: =IFERROR(I72*G72*700,"") -> 11872 | V72: =IFERROR(G72*I72/23000*1500000,"") -> 1106.087 | W72: =IFERROR(2%*R72*1.11,"") -> 22984.4 | X72: =IFERROR(T72-U72-V72-W72-Z72-AC72-AB72-AA72-AD72,"") -> 117302.52 | Y72: =IF(E72="avem005",4,1) -> 1 | Z72: 0 | AA72: =IFERROR(ROUNDDOWN(G72/Y72,0)*P72,"") -> 0 | AB72: =IFERROR(IF(OR(D72="SALES008",D72="SALES010"),IF(MOD(G72,H72)=0,10000*G72/H72,10000*(ROUNDUP(G72/H72,0))),0),"") -> 0 | AC72: 0 | AD72: 10000 | AF72: AVHA001 | AG72: =SUMIF($E$8:$X$2162,AF72,$R$8:$R$2162)*1.11 -> 400340 | AH72: =SUMIF($E$8:$X$1048576,AF72,$X$8:$X$1048576) -> 0 | AI72: =AH72/AG72 -> 0
A73: 67 | B73: 46237 | C73: SO.AV.2026.08.00055 | D73: SALES005 | E73: AVWI005 | F73: =IFERROR(VLOOKUP(E73,'DATA MASTER'!$B$1:$R$3858,3,0),"") -> DIV 2 | G73: 3 | H73: =IFERROR(VLOOKUP(E73,'DATA MASTER'!$B$1:$R$3858,6,0),"") -> 4 | I73: =IFERROR(VLOOKUP(E73,'DATA MASTER'!$B$1:$R$3858,5,0),"") -> 5.23 | J73: =IFERROR(VLOOKUP(E73,'DATA MASTER'!$B$1:$R$3858,17,0),"") -> 163600 | K73: =IFERROR(VLOOKUP(E73,'DATA MASTER'!$B$1:$R$3858,16,0),"") -> 144200 | L73: =IFERROR(IF(F73="MTAB",12.5%*J73,7.5%*J73),"") -> 12270 | M73: =IFERROR(IF(F73="MTAB",19.011%*K73,14.488%*K73),"") -> 20891.696 | O73: 0 | R73: =IFERROR((((J73-L73)/1.11*(100-O73)%*G73)-(ROUNDDOWN(G73/Y73,0)*N73)),"") -> 409000 | S73: =IFERROR((K73-M73)/1.11*(100-O73)%*G73,"") -> 333265.69 | T73: =IFERROR(R73-S73,"") -> 75734.314 | U73: =IFERROR(I73*G73*700,"") -> 10983 | V73: =IFERROR(G73*I73/23000*1500000,"") -> 1023.2609 | W73: =IFERROR(2%*R73*1.11,"") -> 9079.8 | X73: =IFERROR(T73-U73-V73-W73-Z73-AC73-AB73-AA73-AD73,"") -> 51707.076 | Y73: 1 | Z73: 0 | AA73: =IFERROR(ROUNDDOWN(G73/Y73,0)*P73,"") -> 0 | AB73: =IFERROR(IF(OR(D73="SALES008",D73="SALES010"),IF(MOD(G73,H73)=0,10000*G73/H73,10000*(ROUNDUP(G73/H73,0))),0),"") -> 0 | AC73: 0 | AD73: 2941.1765 | AF73: AVKA001 | AG73: =SUMIF($E$8:$X$2162,AF73,$R$8:$R$2162)*1.11 -> 398120 | AH73: =SUMIF($E$8:$X$1048576,AF73,$X$8:$X$1048576) -> 42850.796 | AI73: =AH73/AG73 -> 0.10763286
A74: 68 | B74: 46237 | C74: SO.AV.2026.08.00057 | D74: Office | E74: NODR020 | F74: =IFERROR(VLOOKUP(E74,'DATA MASTER'!$B$1:$R$3858,3,0),"") -> DIV 2 | G74: 2 | H74: =IFERROR(VLOOKUP(E74,'DATA MASTER'!$B$1:$R$3858,6,0),"") -> 1 | I74: =IFERROR(VLOOKUP(E74,'DATA MASTER'!$B$1:$R$3858,5,0),"") -> 21.11 | J74: =IFERROR(VLOOKUP(E74,'DATA MASTER'!$B$1:$R$3858,17,0),"") -> 1428200 | K74: =IFERROR(VLOOKUP(E74,'DATA MASTER'!$B$1:$R$3858,16,0),"") -> 1291700 | L74: =IFERROR(IF(F74="MTAB",12.5%*J74,7.5%*J74),"") -> 107115 | M74: =IFERROR(IF(F74="MTAB",19.011%*K74,14.488%*K74),"") -> 187141.5 | O74: 0 | R74: =IFERROR((((J74-L74)/1.11*(100-O74)%*G74)-(ROUNDDOWN(G74/Y74,0)*N74)),"") -> 2380333.3 | S74: =IFERROR((K74-M74)/1.11*(100-O74)%*G74,"") -> 1990195.5 | T74: =IFERROR(R74-S74,"") -> 390137.83 | U74: =IFERROR(I74*G74*700,"") -> 29554 | V74: =IFERROR(G74*I74/23000*1500000,"") -> 2753.4783 | W74: =IFERROR(2%*R74*1.11,"") -> 52843.4 | X74: =IFERROR(T74-U74-V74-W74-Z74-AC74-AB74-AA74-AD74,"") -> 304986.95 | Y74: 1 | Z74: 0 | AA74: =IFERROR(ROUNDDOWN(G74/Y74,0)*P74,"") -> 0 | AB74: =IFERROR(IF(OR(D74="SALES008",D74="SALES010"),IF(MOD(G74,H74)=0,10000*G74/H74,10000*(ROUNDUP(G74/H74,0))),0),"") -> 0 | AC74: 0 | AD74: 0 | AF74: AVLA005 | AG74: =SUMIF($E$8:$X$2162,AF74,$R$8:$R$2162)*1.11 -> 3825171 | AH74: =SUMIF($E$8:$X$1048576,AF74,$X$8:$X$1048576) -> 447058.13 | AI74: =AH74/AG74 -> 0.11687272
A75: 69 | B75: 46237 | C75: SO.AV.2026.08.00058 | D75: SALES001 | E75: NODR001 | F75: =IFERROR(VLOOKUP(E75,'DATA MASTER'!$B$1:$R$3858,3,0),"") -> DIV 2 | G75: 4 | H75: =IFERROR(VLOOKUP(E75,'DATA MASTER'!$B$1:$R$3858,6,0),"") -> 24 | I75: =IFERROR(VLOOKUP(E75,'DATA MASTER'!$B$1:$R$3858,5,0),"") -> 1.09 | J75: =IFERROR(VLOOKUP(E75,'DATA MASTER'!$B$1:$R$3858,17,0),"") -> 82200 | K75: =IFERROR(VLOOKUP(E75,'DATA MASTER'!$B$1:$R$3858,16,0),"") -> 74900 | L75: =IFERROR(IF(F75="MTAB",12.5%*J75,7.5%*J75),"") -> 6165 | M75: =IFERROR(IF(F75="MTAB",19.011%*K75,14.488%*K75),"") -> 10851.512 | O75: 0 | R75: =IFERROR((((J75-L75)/1.11*(100-O75)%*G75)-(ROUNDDOWN(G75/Y75,0)*N75)),"") -> 274000 | S75: =IFERROR((K75-M75)/1.11*(100-O75)%*G75,"") -> 230805.36 | T75: =IFERROR(R75-S75,"") -> 43194.638 | U75: =IFERROR(I75*G75*700,"") -> 3052 | V75: =IFERROR(G75*I75/23000*1500000,"") -> 284.34783 | W75: =IFERROR(2%*R75*1.11,"") -> 6082.8 | X75: =IFERROR(T75-U75-V75-W75-Z75-AC75-AB75-AA75-AD75,"") -> 30442.157 | Y75: 1 | Z75: 0 | AA75: =IFERROR(ROUNDDOWN(G75/Y75,0)*P75,"") -> 0 | AB75: =IFERROR(IF(OR(D75="SALES008",D75="SALES010"),IF(MOD(G75,H75)=0,10000*G75/H75,10000*(ROUNDUP(G75/H75,0))),0),"") -> 0 | AC75: 0 | AD75: 3333.3333 | AF75: AVLA025 | AG75: =SUMIF($E$8:$X$2162,AF75,$R$8:$R$2162)*1.11 -> 3610885.5 | AH75: =SUMIF($E$8:$X$1048576,AF75,$X$8:$X$1048576) -> 440645.83 | AI75: =AH75/AG75 -> 0.12203262
A76: 70 | B76: 46237 | C76: SO.AV.2026.08.00059 | D76: SALES002 | E76: NODR001 | F76: =IFERROR(VLOOKUP(E76,'DATA MASTER'!$B$1:$R$3858,3,0),"") -> DIV 2 | G76: 6 | H76: =IFERROR(VLOOKUP(E76,'DATA MASTER'!$B$1:$R$3858,6,0),"") -> 24 | I76: =IFERROR(VLOOKUP(E76,'DATA MASTER'!$B$1:$R$3858,5,0),"") -> 1.09 | J76: =IFERROR(VLOOKUP(E76,'DATA MASTER'!$B$1:$R$3858,17,0),"") -> 82200 | K76: =IFERROR(VLOOKUP(E76,'DATA MASTER'!$B$1:$R$3858,16,0),"") -> 74900 | L76: =IFERROR(IF(F76="MTAB",12.5%*J76,7.5%*J76),"") -> 6165 | M76: =IFERROR(IF(F76="MTAB",19.011%*K76,14.488%*K76),"") -> 10851.512 | O76: 0 | R76: =IFERROR((((J76-L76)/1.11*(100-O76)%*G76)-(ROUNDDOWN(G76/Y76,0)*N76)),"") -> 411000 | S76: =IFERROR((K76-M76)/1.11*(100-O76)%*G76,"") -> 346208.04 | T76: =IFERROR(R76-S76,"") -> 64791.957 | U76: =IFERROR(I76*G76*700,"") -> 4578 | V76: =IFERROR(G76*I76/23000*1500000,"") -> 426.52174 | W76: =IFERROR(2%*R76*1.11,"") -> 9124.2 | X76: =IFERROR(T76-U76-V76-W76-Z76-AC76-AB76-AA76-AD76,"") -> 44413.235 | Y76: =IF(E76="avem005",4,1) -> 1 | Z76: 0 | AA76: =IFERROR(ROUNDDOWN(G76/Y76,0)*P76,"") -> 0 | AB76: =IFERROR(IF(OR(D76="SALES008",D76="SALES010"),IF(MOD(G76,H76)=0,10000*G76/H76,10000*(ROUNDUP(G76/H76,0))),0),"") -> 0 | AC76: 0 | AD76: 6250 | AF76: AVLA500 | AG76: =SUMIF($E$8:$X$2162,AF76,$R$8:$R$2162)*1.11 -> 0 | AH76: =SUMIF($E$8:$X$1048576,AF76,$X$8:$X$1048576) -> -16041.422 | AI76: =AH76/AG76 -> #DIV/0!
A77: 71 | B77: 46237 | C77: SO.AV.2026.08.00060 | D77: SALES012 | E77: NODR001 | F77: =IFERROR(VLOOKUP(E77,'DATA MASTER'!$B$1:$R$3858,3,0),"") -> DIV 2 | G77: 9 | H77: =IFERROR(VLOOKUP(E77,'DATA MASTER'!$B$1:$R$3858,6,0),"") -> 24 | I77: =IFERROR(VLOOKUP(E77,'DATA MASTER'!$B$1:$R$3858,5,0),"") -> 1.09 | J77: =IFERROR(VLOOKUP(E77,'DATA MASTER'!$B$1:$R$3858,17,0),"") -> 82200 | K77: =IFERROR(VLOOKUP(E77,'DATA MASTER'!$B$1:$R$3858,16,0),"") -> 74900 | L77: =IFERROR(IF(F77="MTAB",12.5%*J77,7.5%*J77),"") -> 6165 | M77: =IFERROR(IF(F77="MTAB",19.011%*K77,14.488%*K77),"") -> 10851.512 | O77: 0 | R77: =IFERROR((((J77-L77)/1.11*(100-O77)%*G77)-(ROUNDDOWN(G77/Y77,0)*N77)),"") -> 616500 | S77: =IFERROR((K77-M77)/1.11*(100-O77)%*G77,"") -> 519312.06 | T77: =IFERROR(R77-S77,"") -> 97187.935 | U77: =IFERROR(I77*G77*700,"") -> 6867 | V77: =IFERROR(G77*I77/23000*1500000,"") -> 639.78261 | W77: =IFERROR(2%*R77*1.11,"") -> 13686.3 | X77: =IFERROR(T77-U77-V77-W77-Z77-AC77-AB77-AA77-AD77,"") -> 70439.297 | Y77: =IF(E77="avem005",4,1) -> 1 | Z77: 0 | AA77: =IFERROR(ROUNDDOWN(G77/Y77,0)*P77,"") -> 0 | AB77: =IFERROR(IF(OR(D77="SALES008",D77="SALES010"),IF(MOD(G77,H77)=0,10000*G77/H77,10000*(ROUNDUP(G77/H77,0))),0),"") -> 0 | AC77: 0 | AD77: 5555.5556 | AF77: AVLE001KHAR | AG77: =SUMIF($E$8:$X$2162,AF77,$R$8:$R$2162)*1.11 -> 0 | AH77: =SUMIF($E$8:$X$1048576,AF77,$X$8:$X$1048576) -> -28745.195 | AI77: =AH77/AG77 -> #DIV/0!
A78: 72 | B78: 46237 | C78: SO.AV.2026.08.00061 | D78: Office | E78: AVEP001 | F78: =IFERROR(VLOOKUP(E78,'DATA MASTER'!$B$1:$R$3858,3,0),"") -> DIV 2 | G78: 1 | H78: =IFERROR(VLOOKUP(E78,'DATA MASTER'!$B$1:$R$3858,6,0),"") -> 24 | I78: =IFERROR(VLOOKUP(E78,'DATA MASTER'!$B$1:$R$3858,5,0),"") -> 1 | J78: =IFERROR(VLOOKUP(E78,'DATA MASTER'!$B$1:$R$3858,17,0),"") -> 111200 | K78: =IFERROR(VLOOKUP(E78,'DATA MASTER'!$B$1:$R$3858,16,0),"") -> 101600 | L78: =IFERROR(IF(F78="MTAB",12.5%*J78,7.5%*J78),"") -> 8340 | M78: =IFERROR(IF(F78="MTAB",19.011%*K78,14.488%*K78),"") -> 14719.808 | O78: 0 | R78: =IFERROR((((J78-L78)/1.11*(100-O78)%*G78)-(ROUNDDOWN(G78/Y78,0)*N78)),"") -> 92666.667 | S78: =IFERROR((K78-M78)/1.11*(100-O78)%*G78,"") -> 78270.443 | T78: =IFERROR(R78-S78,"") -> 14396.223 | U78: =IFERROR(I78*G78*700,"") -> 700 | V78: =IFERROR(G78*I78/23000*1500000,"") -> 65.217391 | W78: =IFERROR(2%*R78*1.11,"") -> 2057.2 | X78: =IFERROR(T78-U78-V78-W78-Z78-AC78-AB78-AA78-AD78,"") -> 11573.806 | Y78: 1 | Z78: 0 | AA78: =IFERROR(ROUNDDOWN(G78/Y78,0)*P78,"") -> 0 | AB78: =IFERROR(IF(OR(D78="SALES008",D78="SALES010"),IF(MOD(G78,H78)=0,10000*G78/H78,10000*(ROUNDUP(G78/H78,0))),0),"") -> 0 | AC78: 0 | AD78: 0 | AF78: AVLE001KHEHAR | AG78: =SUMIF($E$8:$X$2162,AF78,$R$8:$R$2162)*1.11 -> 0 | AH78: =SUMIF($E$8:$X$1048576,AF78,$X$8:$X$1048576) -> 0 | AI78: =AH78/AG78 -> #DIV/0!
A79: 73 | B79: 46237 | C79: SO.AV.2026.08.00061 | D79: Office | E79: AVSY500 | F79: =IFERROR(VLOOKUP(E79,'DATA MASTER'!$B$1:$R$3858,3,0),"") -> DIV 1 | G79: 2 | H79: =IFERROR(VLOOKUP(E79,'DATA MASTER'!$B$1:$R$3858,6,0),"") -> 36 | I79: =IFERROR(VLOOKUP(E79,'DATA MASTER'!$B$1:$R$3858,5,0),"") -> 0.621 | J79: =IFERROR(VLOOKUP(E79,'DATA MASTER'!$B$1:$R$3858,17,0),"") -> 56900 | K79: =IFERROR(VLOOKUP(E79,'DATA MASTER'!$B$1:$R$3858,16,0),"") -> 52000 | L79: =IFERROR(IF(F79="MTAB",12.5%*J79,7.5%*J79),"") -> 4267.5 | M79: =IFERROR(IF(F79="MTAB",19.011%*K79,14.488%*K79),"") -> 7533.76 | O79: 0 | R79: =IFERROR((((J79-L79)/1.11*(100-O79)%*G79)-(ROUNDDOWN(G79/Y79,0)*N79)),"") -> 94833.333 | S79: =IFERROR((K79-M79)/1.11*(100-O79)%*G79,"") -> 80119.351 | T79: =IFERROR(R79-S79,"") -> 14713.982 | U79: =IFERROR(I79*G79*700,"") -> 869.4 | V79: =IFERROR(G79*I79/23000*1500000,"") -> 81 | W79: =IFERROR(2%*R79*1.11,"") -> 2105.3 | X79: =IFERROR(T79-U79-V79-W79-Z79-AC79-AB79-AA79-AD79,"") -> 11658.282 | Y79: 1 | AA79: =IFERROR(ROUNDDOWN(G79/Y79,0)*P79,"") -> 0 | AB79: =IFERROR(IF(OR(D79="SALES008",D79="SALES010"),IF(MOD(G79,H79)=0,10000*G79/H79,10000*(ROUNDUP(G79/H79,0))),0),"") -> 0 | AC79: =Z79*R79*1.11 -> 0 | AD79: 0 | AF79: AVLE001KHEPOX | AG79: =SUMIF($E$8:$X$2162,AF79,$R$8:$R$2162)*1.11 -> 548710 | AH79: =SUMIF($E$8:$X$1048576,AF79,$X$8:$X$1048576) -> 0 | AI79: =AH79/AG79 -> 0
A80: 74 | B80: 46237 | C80: SO.AV.2026.08.00062 | D80: SALES002 | E80: AGEM005KBA | F80: =IFERROR(VLOOKUP(E80,'DATA MASTER'!$B$1:$R$3858,3,0),"") -> MTAB | G80: 2 | H80: =IFERROR(VLOOKUP(E80,'DATA MASTER'!$B$1:$R$3858,6,0),"") -> 4 | I80: =IFERROR(VLOOKUP(E80,'DATA MASTER'!$B$1:$R$3858,5,0),"") -> 4.68 | J80: =IFERROR(VLOOKUP(E80,'DATA MASTER'!$B$1:$R$3858,17,0),"") -> 106800 | K80: =IFERROR(VLOOKUP(E80,'DATA MASTER'!$B$1:$R$3858,16,0),"") -> 96500 | L80: =IFERROR(IF(F80="MTAB",12.5%*J80,7.5%*J80),"") -> 13350 | M80: =IFERROR(IF(F80="MTAB",19.011%*K80,14.488%*K80),"") -> 18345.615 | O80: 0 | R80: =IFERROR((((J80-L80)/1.11*(100-O80)%*G80)-(ROUNDDOWN(G80/Y80,0)*N80)),"") -> 168378.38 | S80: =IFERROR((K80-M80)/1.11*(100-O80)%*G80,"") -> 140818.71 | T80: =IFERROR(R80-S80,"") -> 27559.667 | U80: =IFERROR(I80*G80*700,"") -> 6552 | V80: =IFERROR(G80*I80/23000*1500000,"") -> 610.43478 | W80: =IFERROR(2%*R80*1.11,"") -> 3738 | X80: =IFERROR(T80-U80-V80-W80-Z80-AC80-AB80-AA80-AD80,"") -> 13534.232 | Y80: 1 | Z80: 0 | AA80: =IFERROR(ROUNDDOWN(G80/Y80,0)*P80,"") -> 0 | AB80: =IFERROR(IF(OR(D80="SALES008",D80="SALES010"),IF(MOD(G80,H80)=0,10000*G80/H80,10000*(ROUNDUP(G80/H80,0))),0),"") -> 0 | AC80: 0 | AD80: 3125 | AF80: AVLE001KPOX | AG80: =SUMIF($E$8:$X$2162,AF80,$R$8:$R$2162)*1.11 -> 1609962.5 | AH80: =SUMIF($E$8:$X$1048576,AF80,$X$8:$X$1048576) -> 153785.3 | AI80: =AH80/AG80 -> 0.095521046
A81: 75 | B81: 46237 | C81: SO.AV.2026.08.00063 | D81: SALES007 | E81: NODR004 | F81: =IFERROR(VLOOKUP(E81,'DATA MASTER'!$B$1:$R$3858,3,0),"") -> DIV 2 | G81: 2 | H81: =IFERROR(VLOOKUP(E81,'DATA MASTER'!$B$1:$R$3858,6,0),"") -> 4 | I81: =IFERROR(VLOOKUP(E81,'DATA MASTER'!$B$1:$R$3858,5,0),"") -> 4.24 | J81: =IFERROR(VLOOKUP(E81,'DATA MASTER'!$B$1:$R$3858,17,0),"") -> 310600 | K81: =IFERROR(VLOOKUP(E81,'DATA MASTER'!$B$1:$R$3858,16,0),"") -> 283000 | L81: =IFERROR(IF(F81="MTAB",12.5%*J81,7.5%*J81),"") -> 23295 | M81: =IFERROR(IF(F81="MTAB",19.011%*K81,14.488%*K81),"") -> 41001.04 | O81: 0 | R81: =IFERROR((((J81-L81)/1.11*(100-O81)%*G81)-(ROUNDDOWN(G81/Y81,0)*N81)),"") -> 517666.67 | S81: =IFERROR((K81-M81)/1.11*(100-O81)%*G81,"") -> 436034.16 | T81: =IFERROR(R81-S81,"") -> 81632.505 | U81: =IFERROR(I81*G81*700,"") -> 5936 | V81: =IFERROR(G81*I81/23000*1500000,"") -> 553.04348 | W81: =IFERROR(2%*R81*1.11,"") -> 11492.2 | X81: =IFERROR(T81-U81-V81-W81-Z81-AC81-AB81-AA81-AD81,"") -> 63651.261 | Y81: 1 | AA81: =IFERROR(ROUNDDOWN(G81/Y81,0)*P81,"") -> 0 | AB81: =IFERROR(IF(OR(D81="SALES008",D81="SALES010"),IF(MOD(G81,H81)=0,10000*G81/H81,10000*(ROUNDUP(G81/H81,0))),0),"") -> 0 | AC81: =Z81*R81*1.11 -> 0 | AD81: 0 | AF81: AVLE200CHAR | AG81: =SUMIF($E$8:$X$2162,AF81,$R$8:$R$2162)*1.11 -> 0 | AH81: =SUMIF($E$8:$X$1048576,AF81,$X$8:$X$1048576) -> -107280.26 | AI81: =AH81/AG81 -> #DIV/0!
A82: 76 | B82: 46237 | C82: SO.AV.2026.08.00064 | D82: SALES002 | E82: AVSY001 | F82: =IFERROR(VLOOKUP(E82,'DATA MASTER'!$B$1:$R$3858,3,0),"") -> DIV 1 | G82: 72 | H82: =IFERROR(VLOOKUP(E82,'DATA MASTER'!$B$1:$R$3858,6,0),"") -> 24 | I82: =IFERROR(VLOOKUP(E82,'DATA MASTER'!$B$1:$R$3858,5,0),"") -> 1.23 | J82: =IFERROR(VLOOKUP(E82,'DATA MASTER'!$B$1:$R$3858,17,0),"") -> 99800 | K82: =IFERROR(VLOOKUP(E82,'DATA MASTER'!$B$1:$R$3858,16,0),"") -> 92100 | L82: =IFERROR(IF(F82="MTAB",12.5%*J82,7.5%*J82),"") -> 7485 | M82: =IFERROR(IF(F82="MTAB",19.011%*K82,14.488%*K82),"") -> 13343.448 | O82: 0 | P82: 60000 | Q82: 148 | R82: =IFERROR((((J82-L82)/1.11*(100-O82)%*G82)-(ROUNDDOWN(G82/Y82,0)*N82)),"") -> 5988000 | S82: =IFERROR((K82-M82)/1.11*(100-O82)%*G82,"") -> 5108533.1 | T82: =IFERROR(R82-S82,"") -> 879466.9 | U82: =IFERROR(I82*G82*700,"") -> 61992 | V82: =IFERROR(G82*I82/23000*1500000,"") -> 5775.6522 | W82: =IFERROR(2%*R82*1.11,"") -> 132933.6 | X82: =IFERROR(T82-U82-V82-W82-Z82-AC82-AB82-AA82-AD82,"") -> 486265.65 | Y82: 24 | Z82: 0 | AA82: =IFERROR(ROUNDDOWN(G82/Y82,0)*P82,"") -> 180000 | AB82: =IFERROR(IF(OR(D82="SALES008",D82="SALES010"),IF(MOD(G82,H82)=0,10000*G82/H82,10000*(ROUNDUP(G82/H82,0))),0),"") -> 0 | AC82: 0 | AD82: 12500 | AF82: AVLE200CHEHAR | AG82: =SUMIF($E$8:$X$2162,AF82,$R$8:$R$2162)*1.11 -> 0 | AH82: =SUMIF($E$8:$X$1048576,AF82,$X$8:$X$1048576) -> -5697.9799 | AI82: =AH82/AG82 -> #DIV/0!
A83: 77 | B83: 46237 | C83: SO.AV.2026.08.00065 | D83: SALES012 | E83: AVSY100 | F83: =IFERROR(VLOOKUP(E83,'DATA MASTER'!$B$1:$R$3858,3,0),"") -> DIV 1 | G83: 60 | H83: =IFERROR(VLOOKUP(E83,'DATA MASTER'!$B$1:$R$3858,6,0),"") -> 120 | I83: =IFERROR(VLOOKUP(E83,'DATA MASTER'!$B$1:$R$3858,5,0),"") -> 0.145 | J83: =IFERROR(VLOOKUP(E83,'DATA MASTER'!$B$1:$R$3858,17,0),"") -> 15108.333 | K83: =IFERROR(VLOOKUP(E83,'DATA MASTER'!$B$1:$R$3858,16,0),"") -> 14025 | L83: =IFERROR(IF(F83="MTAB",12.5%*J83,7.5%*J83),"") -> 1133.125 | M83: =IFERROR(IF(F83="MTAB",19.011%*K83,14.488%*K83),"") -> 2031.942 | O83: 0 | R83: =IFERROR((((J83-L83)/1.11*(100-O83)%*G83)-(ROUNDDOWN(G83/Y83,0)*N83)),"") -> 755416.67 | S83: =IFERROR((K83-M83)/1.11*(100-O83)%*G83,"") -> 648273.41 | T83: =IFERROR(R83-S83,"") -> 107143.26 | U83: =IFERROR(I83*G83*700,"") -> 6090 | V83: =IFERROR(G83*I83/23000*1500000,"") -> 567.3913 | W83: =IFERROR(2%*R83*1.11,"") -> 16770.25 | X83: =IFERROR(T83-U83-V83-W83-Z83-AC83-AB83-AA83-AD83,"") -> 74624.711 | Y83: 1 | Z83: 0 | AA83: =IFERROR(ROUNDDOWN(G83/Y83,0)*P83,"") -> 0 | AB83: =IFERROR(IF(OR(D83="SALES008",D83="SALES010"),IF(MOD(G83,H83)=0,10000*G83/H83,10000*(ROUNDUP(G83/H83,0))),0),"") -> 0 | AC83: 0 | AD83: 9090.9091 | AF83: AVLE200CHEPOX | AG83: =SUMIF($E$8:$X$2162,AF83,$R$8:$R$2162)*1.11 -> 1011487.5 | AH83: =SUMIF($E$8:$X$1048576,AF83,$X$8:$X$1048576) -> 79948.005 | AI83: =AH83/AG83 -> 0.079040033
A84: 78 | B84: 46237 | C84: SO.AV.2026.08.00066 | D84: SALES014 | E84: ACSY001 | F84: =IFERROR(VLOOKUP(E84,'DATA MASTER'!$B$1:$R$3858,3,0),"") -> DIV 2 | G84: 4 | H84: =IFERROR(VLOOKUP(E84,'DATA MASTER'!$B$1:$R$3858,6,0),"") -> 24 | I84: =IFERROR(VLOOKUP(E84,'DATA MASTER'!$B$1:$R$3858,5,0),"") -> 0.902 | J84: =IFERROR(VLOOKUP(E84,'DATA MASTER'!$B$1:$R$3858,17,0),"") -> 81000 | K84: =IFERROR(VLOOKUP(E84,'DATA MASTER'!$B$1:$R$3858,16,0),"") -> 74300 | L84: =IFERROR(IF(F84="MTAB",12.5%*J84,7.5%*J84),"") -> 6075 | M84: =IFERROR(IF(F84="MTAB",19.011%*K84,14.488%*K84),"") -> 10764.584 | O84: 10 | R84: =IFERROR((((J84-L84)/1.11*(100-O84)%*G84)-(ROUNDDOWN(G84/Y84,0)*N84)),"") -> 243000 | S84: =IFERROR((K84-M84)/1.11*(100-O84)%*G84,"") -> 206060.81 | T84: =IFERROR(R84-S84,"") -> 36939.191 | U84: =IFERROR(I84*G84*700,"") -> 2525.6 | V84: =IFERROR(G84*I84/23000*1500000,"") -> 235.30435 | W84: =IFERROR(2%*R84*1.11,"") -> 5394.6 | X84: =IFERROR(T84-U84-V84-W84-Z84-AC84-AB84-AA84-AD84,"") -> 28783.687 | Y84: 1 | Z84: 0 | AA84: =IFERROR(ROUNDDOWN(G84/Y84,0)*P84,"") -> 0 | AB84: =IFERROR(IF(OR(D84="SALES008",D84="SALES010"),IF(MOD(G84,H84)=0,10000*G84/H84,10000*(ROUNDUP(G84/H84,0))),0),"") -> 0 | AC84: 0 | AD84: 0 | AF84: AVLE200CPOX | AG84: =SUMIF($E$8:$X$2162,AF84,$R$8:$R$2162)*1.11 -> 50694810 | AH84: =SUMIF($E$8:$X$1048576,AF84,$X$8:$X$1048576) -> 1838942.2 | AI84: =AH84/AG84 -> 0.036274762
A85: 79 | B85: 46237 | C85: SO.AV.2026.08.00067 | D85: SALES005 | E85: ACSY001 | F85: =IFERROR(VLOOKUP(E85,'DATA MASTER'!$B$1:$R$3858,3,0),"") -> DIV 2 | G85: 28 | H85: =IFERROR(VLOOKUP(E85,'DATA MASTER'!$B$1:$R$3858,6,0),"") -> 24 | I85: =IFERROR(VLOOKUP(E85,'DATA MASTER'!$B$1:$R$3858,5,0),"") -> 0.902 | J85: =IFERROR(VLOOKUP(E85,'DATA MASTER'!$B$1:$R$3858,17,0),"") -> 81000 | K85: =IFERROR(VLOOKUP(E85,'DATA MASTER'!$B$1:$R$3858,16,0),"") -> 74300 | L85: =IFERROR(IF(F85="MTAB",12.5%*J85,7.5%*J85),"") -> 6075 | M85: =IFERROR(IF(F85="MTAB",19.011%*K85,14.488%*K85),"") -> 10764.584 | O85: 10 | R85: =IFERROR((((J85-L85)/1.11*(100-O85)%*G85)-(ROUNDDOWN(G85/Y85,0)*N85)),"") -> 1701000 | S85: =IFERROR((K85-M85)/1.11*(100-O85)%*G85,"") -> 1442425.7 | T85: =IFERROR(R85-S85,"") -> 258574.34 | U85: =IFERROR(I85*G85*700,"") -> 17679.2 | V85: =IFERROR(G85*I85/23000*1500000,"") -> 1647.1304 | W85: =IFERROR(2%*R85*1.11,"") -> 37762.2 | X85: =IFERROR(T85-U85-V85-W85-Z85-AC85-AB85-AA85-AD85,"") -> 184819.14 | Y85: =IF(E85="avem005",4,1) -> 1 | Z85: 0 | AA85: =IFERROR(ROUNDDOWN(G85/Y85,0)*P85,"") -> 0 | AB85: =IFERROR(IF(OR(D85="SALES008",D85="SALES010"),IF(MOD(G85,H85)=0,10000*G85/H85,10000*(ROUNDUP(G85/H85,0))),0),"") -> 0 | AC85: 0 | AD85: 16666.667 | AF85: AVNO003KHAR | AG85: =SUMIF($E$8:$X$2162,AF85,$R$8:$R$2162)*1.11 -> 0 | AH85: =SUMIF($E$8:$X$1048576,AF85,$X$8:$X$1048576) -> -100977.93 | AI85: =AH85/AG85 -> #DIV/0!
A86: 80 | B86: 46237 | C86: SO.AV.2026.08.00068 | D86: SALES005 | E86: AVSY001 | F86: =IFERROR(VLOOKUP(E86,'DATA MASTER'!$B$1:$R$3858,3,0),"") -> DIV 1 | G86: 3 | H86: =IFERROR(VLOOKUP(E86,'DATA MASTER'!$B$1:$R$3858,6,0),"") -> 24 | I86: =IFERROR(VLOOKUP(E86,'DATA MASTER'!$B$1:$R$3858,5,0),"") -> 1.23 | J86: =IFERROR(VLOOKUP(E86,'DATA MASTER'!$B$1:$R$3858,17,0),"") -> 99800 | K86: =IFERROR(VLOOKUP(E86,'DATA MASTER'!$B$1:$R$3858,16,0),"") -> 92100 | L86: =IFERROR(IF(F86="MTAB",12.5%*J86,7.5%*J86),"") -> 7485 | M86: =IFERROR(IF(F86="MTAB",19.011%*K86,14.488%*K86),"") -> 13343.448 | O86: 0 | R86: =IFERROR((((J86-L86)/1.11*(100-O86)%*G86)-(ROUNDDOWN(G86/Y86,0)*N86)),"") -> 249500 | S86: =IFERROR((K86-M86)/1.11*(100-O86)%*G86,"") -> 212855.55 | T86: =IFERROR(R86-S86,"") -> 36644.454 | U86: =IFERROR(I86*G86*700,"") -> 2583 | V86: =IFERROR(G86*I86/23000*1500000,"") -> 240.65217 | W86: =IFERROR(2%*R86*1.11,"") -> 5538.9 | X86: =IFERROR(T86-U86-V86-W86-Z86-AC86-AB86-AA86-AD86,"") -> 28281.902 | Y86: =IF(E86="avem005",4,1) -> 1 | Z86: 0 | AA86: =IFERROR(ROUNDDOWN(G86/Y86,0)*P86,"") -> 0 | AB86: =IFERROR(IF(OR(D86="SALES008",D86="SALES010"),IF(MOD(G86,H86)=0,10000*G86/H86,10000*(ROUNDUP(G86/H86,0))),0),"") -> 0 | AC86: 0 | AD86: 0 | AF86: AVNO003KPOX | AG86: =SUMIF($E$8:$X$2162,AF86,$R$8:$R$2162)*1.11 -> 12938808 | AH86: =SUMIF($E$8:$X$1048576,AF86,$X$8:$X$1048576) -> 1355635.5 | AI86: =AH86/AG86 -> 0.10477283
A87: 81 | B87: 46237 | C87: SO.AV.2026.08.00068 | D87: SALES005 | E87: AVSY500 | F87: =IFERROR(VLOOKUP(E87,'DATA MASTER'!$B$1:$R$3858,3,0),"") -> DIV 1 | G87: 6 | H87: =IFERROR(VLOOKUP(E87,'DATA MASTER'!$B$1:$R$3858,6,0),"") -> 36 | I87: =IFERROR(VLOOKUP(E87,'DATA MASTER'!$B$1:$R$3858,5,0),"") -> 0.621 | J87: =IFERROR(VLOOKUP(E87,'DATA MASTER'!$B$1:$R$3858,17,0),"") -> 56900 | K87: =IFERROR(VLOOKUP(E87,'DATA MASTER'!$B$1:$R$3858,16,0),"") -> 52000 | L87: =IFERROR(IF(F87="MTAB",12.5%*J87,7.5%*J87),"") -> 4267.5 | M87: =IFERROR(IF(F87="MTAB",19.011%*K87,14.488%*K87),"") -> 7533.76 | O87: 0 | R87: =IFERROR((((J87-L87)/1.11*(100-O87)%*G87)-(ROUNDDOWN(G87/Y87,0)*N87)),"") -> 284500 | S87: =IFERROR((K87-M87)/1.11*(100-O87)%*G87,"") -> 240358.05 | T87: =IFERROR(R87-S87,"") -> 44141.946 | U87: =IFERROR(I87*G87*700,"") -> 2608.2 | V87: =IFERROR(G87*I87/23000*1500000,"") -> 243 | W87: =IFERROR(2%*R87*1.11,"") -> 6315.9 | X87: =IFERROR(T87-U87-V87-W87-Z87-AC87-AB87-AA87-AD87,"") -> 34974.846 | Y87: 1 | Z87: 0 | AA87: =IFERROR(ROUNDDOWN(G87/Y87,0)*P87,"") -> 0 | AB87: =IFERROR(IF(OR(D87="SALES008",D87="SALES010"),IF(MOD(G87,H87)=0,10000*G87/H87,10000*(ROUNDUP(G87/H87,0))),0),"") -> 0 | AC87: 0 | AD87: 0 | AF87: AVNO400CHAR | AG87: =SUMIF($E$8:$X$2162,AF87,$R$8:$R$2162)*1.11 -> 0 | AH87: =SUMIF($E$8:$X$1048576,AF87,$X$8:$X$1048576) -> -44573.599 | AI87: =AH87/AG87 -> #DIV/0!
A88: 82 | B88: 46237 | C88: SO.AV.2026.08.00070 | D88: SALES001 | E88: YOSY001 | F88: =IFERROR(VLOOKUP(E88,'DATA MASTER'!$B$1:$R$3858,3,0),"") -> DIV 2 | G88: 16 | H88: =IFERROR(VLOOKUP(E88,'DATA MASTER'!$B$1:$R$3858,6,0),"") -> 24 | I88: =IFERROR(VLOOKUP(E88,'DATA MASTER'!$B$1:$R$3858,5,0),"") -> 0.85 | J88: =IFERROR(VLOOKUP(E88,'DATA MASTER'!$B$1:$R$3858,17,0),"") -> 74700 | K88: =IFERROR(VLOOKUP(E88,'DATA MASTER'!$B$1:$R$3858,16,0),"") -> 67900 | L88: =IFERROR(IF(F88="MTAB",12.5%*J88,7.5%*J88),"") -> 5602.5 | M88: =IFERROR(IF(F88="MTAB",19.011%*K88,14.488%*K88),"") -> 9837.352 | O88: 0 | Q88: =VLOOKUP(#REF!,#REF!,1,0) -> #REF! | R88: =IFERROR((((J88-L88)/1.11*(100-O88)%*G88)-(ROUNDDOWN(G88/Y88,0)*N88)),"") -> 996000 | S88: =IFERROR((K88-M88)/1.11*(100-O88)%*G88,"") -> 836939.07 | T88: =IFERROR(R88-S88,"") -> 159060.93 | U88: =IFERROR(I88*G88*700,"") -> 9520 | V88: =IFERROR(G88*I88/23000*1500000,"") -> 886.95652 | W88: =IFERROR(2%*R88*1.11,"") -> 22111.2 | X88: =IFERROR(T88-U88-V88-W88-Z88-AC88-AB88-AA88-AD88,"") | Y88: =IF(E88="avem005",4,1) -> 1 | Z88: =VLOOKUP(Q88,#REF!,4,0) -> #REF! | AA88: =IFERROR(ROUNDDOWN(G88/Y88,0)*P88,"") -> 0 | AB88: =IFERROR(IF(OR(D88="SALES008",D88="SALES010"),IF(MOD(G88,H88)=0,10000*G88/H88,10000*(ROUNDUP(G88/H88,0))),0),"") -> 0 | AC88: =Z88*R88*1.11 -> #REF! | AD88: 0 | AF88: AVNO400CHEHAR | AG88: =SUMIF($E$8:$X$2162,AF88,$R$8:$R$2162)*1.11 -> 0 | AH88: =SUMIF($E$8:$X$1048576,AF88,$X$8:$X$1048576) -> -26905.275 | AI88: =AH88/AG88 -> #DIV/0!
A89: 83 | B89: 46237 | C89: SO.AV.2026.08.00071 | D89: SALES010 | E89: AVEM005 | F89: =IFERROR(VLOOKUP(E89,'DATA MASTER'!$B$1:$R$3858,3,0),"") -> DIV 1 | G89: 8 | H89: =IFERROR(VLOOKUP(E89,'DATA MASTER'!$B$1:$R$3858,6,0),"") -> 4 | I89: =IFERROR(VLOOKUP(E89,'DATA MASTER'!$B$1:$R$3858,5,0),"") -> 5.388 | J89: =IFERROR(VLOOKUP(E89,'DATA MASTER'!$B$1:$R$3858,17,0),"") -> 185700 | K89: =IFERROR(VLOOKUP(E89,'DATA MASTER'!$B$1:$R$3858,16,0),"") -> 165300 | L89: =IFERROR(IF(F89="MTAB",12.5%*J89,7.5%*J89),"") -> 13927.5 | M89: =IFERROR(IF(F89="MTAB",19.011%*K89,14.488%*K89),"") -> 23948.664 | O89: 0 | R89: =IFERROR((((J89-L89)/1.11*(100-O89)%*G89)-(ROUNDDOWN(G89/Y89,0)*N89)),"") -> 1238000 | S89: =IFERROR((K89-M89)/1.11*(100-O89)%*G89,"") -> 1018748.4 | T89: =IFERROR(R89-S89,"") -> 219251.63 | U89: =IFERROR(I89*G89*700,"") -> 30172.8 | V89: =IFERROR(G89*I89/23000*1500000,"") -> 2811.1304 | W89: =IFERROR(2%*R89*1.11,"") -> 27483.6 | X89: =IFERROR(T89-U89-V89-W89-Z89-AC89-AB89-AA89-AD89,"") -> 138784.1 | Y89: 1 | Z89: 0 | AA89: =IFERROR(ROUNDDOWN(G89/Y89,0)*P89,"") -> 0 | AB89: =IFERROR(IF(OR(D89="SALES008",D89="SALES010"),IF(MOD(G89,H89)=0,10000*G89/H89,10000*(ROUNDUP(G89/H89,0))),0),"") -> 20000 | AC89: 0 | AD89: 0 | AF89: AVNO400CHEPOX | AG89: =SUMIF($E$8:$X$2162,AF89,$R$8:$R$2162)*1.11 -> 2192250 | AH89: =SUMIF($E$8:$X$1048576,AF89,$X$8:$X$1048576) -> 226365.62 | AI89: =AH89/AG89 -> 0.10325721
A90: 84 | B90: 46237 | C90: SO.AV.2026.08.00072 | D90: SALES001 | E90: AVEM025 | F90: =IFERROR(VLOOKUP(E90,'DATA MASTER'!$B$1:$R$3858,3,0),"") -> DIV 1 | G90: 2 | H90: =IFERROR(VLOOKUP(E90,'DATA MASTER'!$B$1:$R$3858,6,0),"") -> 1 | I90: =IFERROR(VLOOKUP(E90,'DATA MASTER'!$B$1:$R$3858,5,0),"") -> 26.02 | J90: =IFERROR(VLOOKUP(E90,'DATA MASTER'!$B$1:$R$3858,17,0),"") -> 876000 | K90: =IFERROR(VLOOKUP(E90,'DATA MASTER'!$B$1:$R$3858,16,0),"") -> 777200 | L90: =IFERROR(IF(F90="MTAB",12.5%*J90,7.5%*J90),"") -> 65700 | M90: =IFERROR(IF(F90="MTAB",19.011%*K90,14.488%*K90),"") -> 112600.74 | O90: 0 | R90: =IFERROR((((J90-L90)/1.11*(100-O90)%*G90)-(ROUNDDOWN(G90/Y90,0)*N90)),"") -> 1460000 | S90: =IFERROR((K90-M90)/1.11*(100-O90)%*G90,"") -> 1197476.2 | T90: =IFERROR(R90-S90,"") -> 262523.85 | U90: =IFERROR(I90*G90*700,"") -> 36428 | V90: =IFERROR(G90*I90/23000*1500000,"") -> 3393.913 | W90: =IFERROR(2%*R90*1.11,"") -> 32412 | X90: =IFERROR(T90-U90-V90-W90-Z90-AC90-AB90-AA90-AD90,"") -> 181956.6 | Y90: =IF(E90="avem005",4,1) -> 1 | Z90: 0 | AA90: =IFERROR(ROUNDDOWN(G90/Y90,0)*P90,"") -> 0 | AB90: =IFERROR(IF(OR(D90="SALES008",D90="SALES010"),IF(MOD(G90,H90)=0,10000*G90/H90,10000*(ROUNDUP(G90/H90,0))),0),"") -> 0 | AC90: 0 | AD90: 8333.3333 | AF90: AVNO400CPOX | AG90: =SUMIF($E$8:$X$2162,AF90,$R$8:$R$2162)*1.11 -> 50486963 | AH90: =SUMIF($E$8:$X$1048576,AF90,$X$8:$X$1048576) -> 388206.42 | AI90: =AH90/AG90 -> 0.007689241
A91: 85 | B91: 46237 | C91: SO.AV.2026.08.00073 | D91: SALES001 | E91: NODR001 | F91: =IFERROR(VLOOKUP(E91,'DATA MASTER'!$B$1:$R$3858,3,0),"") -> DIV 2 | G91: 6 | H91: =IFERROR(VLOOKUP(E91,'DATA MASTER'!$B$1:$R$3858,6,0),"") -> 24 | I91: =IFERROR(VLOOKUP(E91,'DATA MASTER'!$B$1:$R$3858,5,0),"") -> 1.09 | J91: =IFERROR(VLOOKUP(E91,'DATA MASTER'!$B$1:$R$3858,17,0),"") -> 82200 | K91: =IFERROR(VLOOKUP(E91,'DATA MASTER'!$B$1:$R$3858,16,0),"") -> 74900 | L91: =IFERROR(IF(F91="MTAB",12.5%*J91,7.5%*J91),"") -> 6165 | M91: =IFERROR(IF(F91="MTAB",19.011%*K91,14.488%*K91),"") -> 10851.512 | O91: 0 | R91: =IFERROR((((J91-L91)/1.11*(100-O91)%*G91)-(ROUNDDOWN(G91/Y91,0)*N91)),"") -> 411000 | S91: =IFERROR((K91-M91)/1.11*(100-O91)%*G91,"") -> 346208.04 | T91: =IFERROR(R91-S91,"") -> 64791.957 | U91: =IFERROR(I91*G91*700,"") -> 4578 | V91: =IFERROR(G91*I91/23000*1500000,"") -> 426.52174 | W91: =IFERROR(2%*R91*1.11,"") -> 9124.2 | X91: =IFERROR(T91-U91-V91-W91-Z91-AC91-AB91-AA91-AD91,"") -> 42329.902 | Y91: =IF(E91="avgo005",4,1) -> 1 | Z91: 0 | AA91: =IFERROR(ROUNDDOWN(G91/Y91,0)*P91,"") -> 0 | AB91: =IFERROR(IF(OR(D91="SALES008",D91="SALES010"),IF(MOD(G91,H91)=0,10000*G91/H91,10000*(ROUNDUP(G91/H91,0))),0),"") -> 0 | AC91: 0 | AD91: 8333.3333 | AF91: AVPI020 | AG91: =SUMIF($E$8:$X$2162,AF91,$R$8:$R$2162)*1.11 -> 6347812.5 | AH91: =SUMIF($E$8:$X$1048576,AF91,$X$8:$X$1048576) -> 678695.86 | AI91: =AH91/AG91 -> 0.10691807
A92: 86 | B92: 46237 | C92: SO.AV.2026.08.00074 | D92: SALES002 | E92: AVGO025 | F92: =IFERROR(VLOOKUP(E92,'DATA MASTER'!$B$1:$R$3858,3,0),"") -> DIV 1 | G92: 1 | H92: =IFERROR(VLOOKUP(E92,'DATA MASTER'!$B$1:$R$3858,6,0),"") -> 1 | I92: =IFERROR(VLOOKUP(E92,'DATA MASTER'!$B$1:$R$3858,5,0),"") -> 26.01 | J92: =IFERROR(VLOOKUP(E92,'DATA MASTER'!$B$1:$R$3858,17,0),"") -> 1103500 | K92: =IFERROR(VLOOKUP(E92,'DATA MASTER'!$B$1:$R$3858,16,0),"") -> 991800 | L92: =IFERROR(IF(F92="MTAB",12.5%*J92,7.5%*J92),"") -> 82762.5 | M92: =IFERROR(IF(F92="MTAB",19.011%*K92,14.488%*K92),"") -> 143691.98 | O92: 0 | R92: =IFERROR((((J92-L92)/1.11*(100-O92)%*G92)-(ROUNDDOWN(G92/Y92,0)*N92)),"") -> 919583.33 | S92: =IFERROR((K92-M92)/1.11*(100-O92)%*G92,"") -> 764061.28 | T92: =IFERROR(R92-S92,"") -> 155522.06 | U92: =IFERROR(I92*G92*700,"") -> 18207 | V92: =IFERROR(G92*I92/23000*1500000,"") -> 1696.3043 | W92: =IFERROR(2%*R92*1.11,"") -> 20414.75 | X92: =IFERROR(T92-U92-V92-W92-Z92-AC92-AB92-AA92-AD92,"") -> 115204 | Y92: 1 | Z92: 0 | AA92: =IFERROR(ROUNDDOWN(G92/Y92,0)*P92,"") -> 0 | AB92: =IFERROR(IF(OR(D92="SALES008",D92="SALES010"),IF(MOD(G92,H92)=0,10000*G92/H92,10000*(ROUNDUP(G92/H92,0))),0),"") -> 0 | AC92: =Z92*R92*1.11 -> 0 | AD92: 0 | AF92: AVRO004 | AG92: =SUMIF($E$8:$X$2162,AF92,$R$8:$R$2162)*1.11 -> 715117.5 | AH92: =SUMIF($E$8:$X$1048576,AF92,$X$8:$X$1048576) -> 57450.341 | AI92: =AH92/AG92 -> 0.080336926
A93: 87 | B93: 46237 | C93: SO.AV.2026.08.00075 | D93: SALES006 | E93: AVSY500 | F93: =IFERROR(VLOOKUP(E93,'DATA MASTER'!$B$1:$R$3858,3,0),"") -> DIV 1 | G93: 3 | H93: =IFERROR(VLOOKUP(E93,'DATA MASTER'!$B$1:$R$3858,6,0),"") -> 36 | I93: =IFERROR(VLOOKUP(E93,'DATA MASTER'!$B$1:$R$3858,5,0),"") -> 0.621 | J93: =IFERROR(VLOOKUP(E93,'DATA MASTER'!$B$1:$R$3858,17,0),"") -> 56900 | K93: =IFERROR(VLOOKUP(E93,'DATA MASTER'!$B$1:$R$3858,16,0),"") -> 52000 | L93: =IFERROR(IF(F93="MTAB",12.5%*J93,7.5%*J93),"") -> 4267.5 | M93: =IFERROR(IF(F93="MTAB",19.011%*K93,14.488%*K93),"") -> 7533.76 | O93: 0 | Q93: =VLOOKUP(#REF!,#REF!,1,0) -> #REF! | R93: =IFERROR((((J93-L93)/1.11*(100-O93)%*G93)-(ROUNDDOWN(G93/Y93,0)*N93)),"") -> 142250 | S93: =IFERROR((K93-M93)/1.11*(100-O93)%*G93,"") -> 120179.03 | T93: =IFERROR(R93-S93,"") -> 22070.973 | U93: =IFERROR(I93*G93*700,"") -> 1304.1 | V93: =IFERROR(G93*I93/23000*1500000,"") -> 121.5 | W93: =IFERROR(2%*R93*1.11,"") -> 3157.95 | X93: =IFERROR(T93-U93-V93-W93-Z93-AC93-AB93-AA93-AD93,"") | Y93: 1 | Z93: =VLOOKUP(Q93,#REF!,4,0) -> #REF! | AA93: =IFERROR(ROUNDDOWN(G93/Y93,0)*P93,"") -> 0 | AB93: =IFERROR(IF(OR(D93="SALES008",D93="SALES010"),IF(MOD(G93,H93)=0,10000*G93/H93,10000*(ROUNDUP(G93/H93,0))),0),"") -> 0 | AC93: =Z93*R93*1.11 -> #REF! | AD93: 0 | AF93: AVSY001 | AG93: =SUMIF($E$8:$X$2162,AF93,$R$8:$R$2162)*1.11 -> 7.8412361e+08 | AH93: =SUMIF($E$8:$X$1048576,AF93,$X$8:$X$1048576) -> 53537011 | AI93: =AH93/AG93 -> 0.068276238
A94: 88 | B94: 46237 | C94: SO.AV.2026.08.00075 | D94: SALES006 | E94: BOVE001 | F94: =IFERROR(VLOOKUP(E94,'DATA MASTER'!$B$1:$R$3858,3,0),"") -> DIV 1 | G94: 3 | H94: =IFERROR(VLOOKUP(E94,'DATA MASTER'!$B$1:$R$3858,6,0),"") -> 24 | I94: =IFERROR(VLOOKUP(E94,'DATA MASTER'!$B$1:$R$3858,5,0),"") -> 1.079 | J94: =IFERROR(VLOOKUP(E94,'DATA MASTER'!$B$1:$R$3858,17,0),"") -> 102900 | K94: =IFERROR(VLOOKUP(E94,'DATA MASTER'!$B$1:$R$3858,16,0),"") -> 94200 | L94: =IFERROR(IF(F94="MTAB",12.5%*J94,7.5%*J94),"") -> 7717.5 | M94: =IFERROR(IF(F94="MTAB",19.011%*K94,14.488%*K94),"") -> 13647.696 | O94: 0 | Q94: =VLOOKUP(#REF!,#REF!,1,0) -> #REF! | R94: =IFERROR((((J94-L94)/1.11*(100-O94)%*G94)-(ROUNDDOWN(G94/Y94,0)*N94)),"") -> 257250 | S94: =IFERROR((K94-M94)/1.11*(100-O94)%*G94,"") -> 217708.93 | T94: =IFERROR(R94-S94,"") -> 39541.07 | U94: =IFERROR(I94*G94*700,"") -> 2265.9 | V94: =IFERROR(G94*I94/23000*1500000,"") -> 211.1087 | W94: =IFERROR(2%*R94*1.11,"") -> 5710.95 | X94: =IFERROR(T94-U94-V94-W94-Z94-AC94-AB94-AA94-AD94,"") | Y94: =IF(E94="avem005",4,1) -> 1 | Z94: =VLOOKUP(Q94,#REF!,4,0) -> #REF! | AA94: =IFERROR(ROUNDDOWN(G94/Y94,0)*P94,"") -> 0 | AB94: =IFERROR(IF(OR(D94="SALES008",D94="SALES010"),IF(MOD(G94,H94)=0,10000*G94/H94,10000*(ROUNDUP(G94/H94,0))),0),"") -> 0 | AC94: =Z94*R94*1.11 -> #REF! | AD94: 0 | AF94: AVSY001KBA | AG94: =SUMIF($E$8:$X$2162,AF94,$R$8:$R$2162)*1.11 -> 331450 | AH94: =SUMIF($E$8:$X$1048576,AF94,$X$8:$X$1048576) -> 19934.158 | AI94: =AH94/AG94 -> 0.060142276
A95: 89 | B95: 46237 | C95: SO.AV.2026.08.00075 | D95: SALES006 | E95: BOVE500 | F95: =IFERROR(VLOOKUP(E95,'DATA MASTER'!$B$1:$R$3858,3,0),"") -> DIV 1 | G95: 5 | H95: =IFERROR(VLOOKUP(E95,'DATA MASTER'!$B$1:$R$3858,6,0),"") -> 24 | I95: =IFERROR(VLOOKUP(E95,'DATA MASTER'!$B$1:$R$3858,5,0),"") -> 0.575 | J95: =IFERROR(VLOOKUP(E95,'DATA MASTER'!$B$1:$R$3858,17,0),"") -> 57800 | K95: =IFERROR(VLOOKUP(E95,'DATA MASTER'!$B$1:$R$3858,16,0),"") -> 53100 | L95: =IFERROR(IF(F95="MTAB",12.5%*J95,7.5%*J95),"") -> 4335 | M95: =IFERROR(IF(F95="MTAB",19.011%*K95,14.488%*K95),"") -> 7693.128 | O95: 0 | Q95: =VLOOKUP(#REF!,#REF!,1,0) -> #REF! | R95: =IFERROR((((J95-L95)/1.11*(100-O95)%*G95)-(ROUNDDOWN(G95/Y95,0)*N95)),"") -> 240833.33 | S95: =IFERROR((K95-M95)/1.11*(100-O95)%*G95,"") -> 204535.46 | T95: =IFERROR(R95-S95,"") -> 36297.874 | U95: =IFERROR(I95*G95*700,"") -> 2012.5 | V95: =IFERROR(G95*I95/23000*1500000,"") -> 187.5 | W95: =IFERROR(2%*R95*1.11,"") -> 5346.5 | X95: =IFERROR(T95-U95-V95-W95-Z95-AC95-AB95-AA95-AD95,"") | Y95: 1 | Z95: =VLOOKUP(Q95,#REF!,4,0) -> #REF! | AA95: =IFERROR(ROUNDDOWN(G95/Y95,0)*P95,"") -> 0 | AB95: =IFERROR(IF(OR(D95="SALES008",D95="SALES010"),IF(MOD(G95,H95)=0,10000*G95/H95,10000*(ROUNDUP(G95/H95,0))),0),"") -> 0 | AC95: =Z95*R95*1.11 -> #REF! | AD95: 0 | AF95: AVSY001KBB | AG95: =SUMIF($E$8:$X$2162,AF95,$R$8:$R$2162)*1.11 -> 318850 | AH95: =SUMIF($E$8:$X$1048576,AF95,$X$8:$X$1048576) -> 19847.6 | AI95: =AH95/AG95 -> 0.062247453
A96: 90 | B96: 46237 | C96: SO.AV.2026.08.00076 | D96: SALES019 | E96: AGEM005 | F96: =IFERROR(VLOOKUP(E96,'DATA MASTER'!$B$1:$R$3858,3,0),"") -> DIV 2 | G96: 4 | H96: =IFERROR(VLOOKUP(E96,'DATA MASTER'!$B$1:$R$3858,6,0),"") -> 4 | I96: =IFERROR(VLOOKUP(E96,'DATA MASTER'!$B$1:$R$3858,5,0),"") -> 4.68 | J96: =IFERROR(VLOOKUP(E96,'DATA MASTER'!$B$1:$R$3858,17,0),"") -> 112100 | K96: =IFERROR(VLOOKUP(E96,'DATA MASTER'!$B$1:$R$3858,16,0),"") -> 96500 | L96: =IFERROR(IF(F96="MTAB",12.5%*J96,7.5%*J96),"") -> 8407.5 | M96: =IFERROR(IF(F96="MTAB",19.011%*K96,14.488%*K96),"") -> 13980.92 | O96: 0 | R96: =IFERROR((((J96-L96)/1.11*(100-O96)%*G96)-(ROUNDDOWN(G96/Y96,0)*N96)),"") -> 373666.67 | S96: =IFERROR((K96-M96)/1.11*(100-O96)%*G96,"") -> 297366.05 | T96: =IFERROR(R96-S96,"") -> 76300.613 | U96: =IFERROR(I96*G96*700,"") -> 13104 | V96: =IFERROR(G96*I96/23000*1500000,"") -> 1220.8696 | W96: =IFERROR(2%*R96*1.11,"") -> 8295.4 | X96: =IFERROR(T96-U96-V96-W96-Z96-AC96-AB96-AA96-AD96,"") -> 41180.343 | Y96: 1 | Z96: 0 | AA96: =IFERROR(ROUNDDOWN(G96/Y96,0)*P96,"") -> 0 | AB96: =IFERROR(IF(OR(D96="SALES008",D96="SALES010"),IF(MOD(G96,H96)=0,10000*G96/H96,10000*(ROUNDUP(G96/H96,0))),0),"") -> 0 | AC96: 0 | AD96: 12500 | AF96: AVSY004 | AG96: =SUMIF($E$8:$X$2162,AF96,$R$8:$R$2162)*1.11 -> 13066920 | AH96: =SUMIF($E$8:$X$1048576,AF96,$X$8:$X$1048576) -> 1261715.1 | AI96: =AH96/AG96 -> 0.096557954
A97: 91 | B97: 46237 | C97: SO.AV.2026.08.00077 | D97: SALES019 | E97: AVSY001 | F97: =IFERROR(VLOOKUP(E97,'DATA MASTER'!$B$1:$R$3858,3,0),"") -> DIV 1 | G97: 6 | H97: =IFERROR(VLOOKUP(E97,'DATA MASTER'!$B$1:$R$3858,6,0),"") -> 24 | I97: =IFERROR(VLOOKUP(E97,'DATA MASTER'!$B$1:$R$3858,5,0),"") -> 1.23 | J97: =IFERROR(VLOOKUP(E97,'DATA MASTER'!$B$1:$R$3858,17,0),"") -> 99800 | K97: =IFERROR(VLOOKUP(E97,'DATA MASTER'!$B$1:$R$3858,16,0),"") -> 92100 | L97: =IFERROR(IF(F97="MTAB",12.5%*J97,7.5%*J97),"") -> 7485 | M97: =IFERROR(IF(F97="MTAB",19.011%*K97,14.488%*K97),"") -> 13343.448 | O97: 0 | R97: =IFERROR((((J97-L97)/1.11*(100-O97)%*G97)-(ROUNDDOWN(G97/Y97,0)*N97)),"") -> 499000 | S97: =IFERROR((K97-M97)/1.11*(100-O97)%*G97,"") -> 425711.09 | T97: =IFERROR(R97-S97,"") -> 73288.908 | U97: =IFERROR(I97*G97*700,"") -> 5166 | V97: =IFERROR(G97*I97/23000*1500000,"") -> 481.30435 | W97: =IFERROR(2%*R97*1.11,"") -> 11077.8 | X97: =IFERROR(T97-U97-V97-W97-Z97-AC97-AB97-AA97-AD97,"") -> 56563.804 | Y97: 1 | Z97: 0 | AA97: =IFERROR(ROUNDDOWN(G97/Y97,0)*P97,"") -> 0 | AB97: =IFERROR(IF(OR(D97="SALES008",D97="SALES010"),IF(MOD(G97,H97)=0,10000*G97/H97,10000*(ROUNDUP(G97/H97,0))),0),"") -> 0 | AC97: =Z97*R97*1.11 -> 0 | AD97: 0 | AF97: AVSY100 | AG97: =SUMIF($E$8:$X$2162,AF97,$R$8:$R$2162)*1.11 -> 30689557 | AH97: =SUMIF($E$8:$X$1048576,AF97,$X$8:$X$1048576) -> 2159630.6 | AI97: =AH97/AG97 -> 0.070370209
A98: 92 | B98: 46237 | C98: SO.AV.2026.08.00078 | D98: SALES002 | E98: AVEM025 | F98: =IFERROR(VLOOKUP(E98,'DATA MASTER'!$B$1:$R$3858,3,0),"") -> DIV 1 | G98: 3 | H98: =IFERROR(VLOOKUP(E98,'DATA MASTER'!$B$1:$R$3858,6,0),"") -> 1 | I98: =IFERROR(VLOOKUP(E98,'DATA MASTER'!$B$1:$R$3858,5,0),"") -> 26.02 | J98: =IFERROR(VLOOKUP(E98,'DATA MASTER'!$B$1:$R$3858,17,0),"") -> 876000 | K98: =IFERROR(VLOOKUP(E98,'DATA MASTER'!$B$1:$R$3858,16,0),"") -> 777200 | L98: =IFERROR(IF(F98="MTAB",12.5%*J98,7.5%*J98),"") -> 65700 | M98: =IFERROR(IF(F98="MTAB",19.011%*K98,14.488%*K98),"") -> 112600.74 | O98: 0 | R98: =IFERROR((((J98-L98)/1.11*(100-O98)%*G98)-(ROUNDDOWN(G98/Y98,0)*N98)),"") -> 2190000 | S98: =IFERROR((K98-M98)/1.11*(100-O98)%*G98,"") -> 1796214.2 | T98: =IFERROR(R98-S98,"") -> 393785.77 | U98: =IFERROR(I98*G98*700,"") -> 54642 | V98: =IFERROR(G98*I98/23000*1500000,"") -> 5090.8696 | W98: =IFERROR(2%*R98*1.11,"") -> 48618 | X98: =IFERROR(T98-U98-V98-W98-Z98-AC98-AB98-AA98-AD98,"") -> 271798.54 | Y98: 1 | Z98: 0 | AA98: =IFERROR(ROUNDDOWN(G98/Y98,0)*P98,"") -> 0 | AB98: =IFERROR(IF(OR(D98="SALES008",D98="SALES010"),IF(MOD(G98,H98)=0,10000*G98/H98,10000*(ROUNDUP(G98/H98,0))),0),"") -> 0 | AC98: =Z98*R98*1.11 -> 0 | AD98: 13636.364 | AF98: AVSY200 | AG98: =SUMIF($E$8:$X$2162,AF98,$R$8:$R$2162)*1.11 -> 39032595 | AH98: =SUMIF($E$8:$X$1048576,AF98,$X$8:$X$1048576) -> 3190046.6 | AI98: =AH98/AG98 -> 0.081727762
A99: 93 | B99: 46237 | C99: SO.AV.2026.08.00080 | D99: SALES007 | E99: AVLE200CHAR | F99: =IFERROR(VLOOKUP(E99,'DATA MASTER'!$B$1:$R$3858,3,0),"") -> DIV 1 | G99: 30 | H99: =IFERROR(VLOOKUP(E99,'DATA MASTER'!$B$1:$R$3858,6,0),"") -> 30 | I99: =IFERROR(VLOOKUP(E99,'DATA MASTER'!$B$1:$R$3858,5,0),"") -> 0.215 | J99: =IFERROR(VLOOKUP(E99,'DATA MASTER'!$B$1:$R$3858,17,0),"") -> 0 | K99: =IFERROR(VLOOKUP(E99,'DATA MASTER'!$B$1:$R$3858,16,0),"") -> 0 | L99: =IFERROR(IF(F99="MTAB",12.5%*J99,7.5%*J99),"") -> 0 | M99: =IFERROR(IF(F99="MTAB",19.011%*K99,14.488%*K99),"") -> 0 | O99: 0 | R99: =IFERROR((((J99-L99)/1.11*(100-O99)%*G99)-(ROUNDDOWN(G99/Y99,0)*N99)),"") -> 0 | S99: =IFERROR((K99-M99)/1.11*(100-O99)%*G99,"") -> 0 | T99: =IFERROR(R99-S99,"") -> 0 | U99: =IFERROR(I99*G99*700,"") -> 4515 | V99: =IFERROR(G99*I99/23000*1500000,"") -> 420.65217 | W99: =IFERROR(2%*R99*1.11,"") -> 0 | X99: =IFERROR(T99-U99-V99-W99-Z99-AC99-AB99-AA99-AD99,"") -> -11185.652 | Y99: 1 | Z99: 0 | AA99: =IFERROR(ROUNDDOWN(G99/Y99,0)*P99,"") -> 0 | AB99: =IFERROR(IF(OR(D99="SALES008",D99="SALES010"),IF(MOD(G99,H99)=0,10000*G99/H99,10000*(ROUNDUP(G99/H99,0))),0),"") -> 0 | AC99: 0 | AD99: 6250 | AF99: AVSY500 | AG99: =SUMIF($E$8:$X$2162,AF99,$R$8:$R$2162)*1.11 -> 7368550 | AH99: =SUMIF($E$8:$X$1048576,AF99,$X$8:$X$1048576) -> 671267.87 | AI99: =AH99/AG99 -> 0.091099045
A100: 94 | B100: 46237 | C100: SO.AV.2026.08.00080 | D100: SALES007 | E100: AVLE200CPOX | F100: =IFERROR(VLOOKUP(E100,'DATA MASTER'!$B$1:$R$3858,3,0),"") -> DIV 1 | G100: 30 | H100: =IFERROR(VLOOKUP(E100,'DATA MASTER'!$B$1:$R$3858,6,0),"") -> 30 | I100: =IFERROR(VLOOKUP(E100,'DATA MASTER'!$B$1:$R$3858,5,0),"") -> 0.215 | J100: =IFERROR(VLOOKUP(E100,'DATA MASTER'!$B$1:$R$3858,17,0),"") -> 83800 | K100: =IFERROR(VLOOKUP(E100,'DATA MASTER'!$B$1:$R$3858,16,0),"") -> 77100 | L100: =IFERROR(IF(F100="MTAB",12.5%*J100,7.5%*J100),"") -> 6285 | M100: =IFERROR(IF(F100="MTAB",19.011%*K100,14.488%*K100),"") -> 11170.248 | O100: 0 | R100: =IFERROR((((J100-L100)/1.11*(100-O100)%*G100)-(ROUNDDOWN(G100/Y100,0)*N100)),"") -> 2095000 | S100: =IFERROR((K100-M100)/1.11*(100-O100)%*G100,"") -> 1781885.2 | T100: =IFERROR(R100-S100,"") -> 313114.81 | U100: =IFERROR(I100*G100*700,"") -> 4515 | V100: =IFERROR(G100*I100/23000*1500000,"") -> 420.65217 | W100: =IFERROR(2%*R100*1.11,"") -> 46509 | X100: =IFERROR(T100-U100-V100-W100-Z100-AC100-AB100-AA100-AD100,"") -> 255420.16 | Y100: 1 | Z100: 0 | AA100: =IFERROR(ROUNDDOWN(G100/Y100,0)*P100,"") -> 0 | AB100: =IFERROR(IF(OR(D100="SALES008",D100="SALES010"),IF(MOD(G100,H100)=0,10000*G100/H100,10000*(ROUNDUP(G100/H100,0))),0),"") -> 0 | AC100: 0 | AD100: 6250 | AF100: AVTH001 | AG100: =SUMIF($E$8:$X$2162,AF100,$R$8:$R$2162)*1.11 -> 381100 | AH100: =SUMIF($E$8:$X$1048576,AF100,$X$8:$X$1048576) -> 42910.426 | AI100: =AH100/AG100 -> 0.11259624
A101: 95 | B101: 46237 | C101: SO.AV.2026.08.00081 | D101: SALES014 | E101: ACSY001 | F101: =IFERROR(VLOOKUP(E101,'DATA MASTER'!$B$1:$R$3858,3,0),"") -> DIV 2 | G101: 4 | H101: =IFERROR(VLOOKUP(E101,'DATA MASTER'!$B$1:$R$3858,6,0),"") -> 24 | I101: =IFERROR(VLOOKUP(E101,'DATA MASTER'!$B$1:$R$3858,5,0),"") -> 0.902 | J101: =IFERROR(VLOOKUP(E101,'DATA MASTER'!$B$1:$R$3858,17,0),"") -> 81000 | K101: =IFERROR(VLOOKUP(E101,'DATA MASTER'!$B$1:$R$3858,16,0),"") -> 74300 | L101: =IFERROR(IF(F101="MTAB",12.5%*J101,7.5%*J101),"") -> 6075 | M101: =IFERROR(IF(F101="MTAB",19.011%*K101,14.488%*K101),"") -> 10764.584 | O101: 10 | R101: =IFERROR((((J101-L101)/1.11*(100-O101)%*G101)-(ROUNDDOWN(G101/Y101,0)*N101)),"") -> 243000 | S101: =IFERROR((K101-M101)/1.11*(100-O101)%*G101,"") -> 206060.81 | T101: =IFERROR(R101-S101,"") -> 36939.191 | U101: =IFERROR(I101*G101*700,"") -> 2525.6 | V101: =IFERROR(G101*I101/23000*1500000,"") -> 235.30435 | W101: =IFERROR(2%*R101*1.11,"") -> 5394.6 | X101: =IFERROR(T101-U101-V101-W101-Z101-AC101-AB101-AA101-AD101,"") -> 28783.687 | Y101: 1 | Z101: 0 | AA101: =IFERROR(ROUNDDOWN(G101/Y101,0)*P101,"") -> 0 | AB101: =IFERROR(IF(OR(D101="SALES008",D101="SALES010"),IF(MOD(G101,H101)=0,10000*G101/H101,10000*(ROUNDUP(G101/H101,0))),0),"") -> 0 | AC101: 0 | AD101: 0 | AF101: AVTO005 | AG101: =SUMIF($E$8:$X$2162,AF101,$R$8:$R$2162)*1.11 -> 1634364 | AH101: =SUMIF($E$8:$X$1048576,AF101,$X$8:$X$1048576) -> 171574.91 | AI101: =AH101/AG101 -> 0.10497962
...

Sheet Detail1
A1: Details for Sum of HJ Total
A3: Tanggal | B3: Nomor Faktur | C3: SALES | D3: Brand | E3: Divisi | F3: Kuantitas | G3: HJ Total | H3: HB Total | I3: Margin awal | J3: biaya pengiriman | K3: Status | L3: Promo ID | M3: CB Promo | N3: Gathering | O3: Kontrak | P3: 2% | Q3: Margin Akhir
A4: 46235 | B4: SO.AV.2026.08.00001 | C4: SALES002 | D4: ABEM005 | E4: DIV 2 | F4: 2 | G4: 183150 | H4: 129423.57 | I4: 35576.432 | J4: 7254.2609 | K4: NoN Local Promo | L4: Gathering Only | M4: 0 | N4: 3125 | O4: 0 | P4: 3663 | Q4: 21534.172
A5: 46235 | B5: SO.AV.2026.08.00002 | C5: SALES005 | D5: AVSY100 | E5: DIV 1 | F5: 24 | G5: 335405 | H5: 259309.36 | I5: 42857.305 | J5: 2662.9565 | K5: NoN Local Promo | L5: Non Campaign | M5: 0 | N5: 0 | O5: 0 | P5: 6708.1 | Q5: 33486.248
A6: 46235 | B6: SO.AV.2026.08.00002 | C6: SALES005 | D6: AVSY200 | E6: DIV 1 | F6: 36 | G6: 929347.5 | H6: 716914.12 | I6: 120335.88 | J6: 6758.3908 | K6: NoN Local Promo | L6: Non Campaign | M6: 0 | N6: 0 | O6: 0 | P6: 18586.95 | Q6: 94990.54
A7: 46235 | B7: SO.AV.2026.08.00003 | C7: SALES001 | D7: AVSY001 | E7: DIV 1 | F7: 6 | G7: 553890 | H7: 425711.09 | I7: 73288.908 | J7: 5647.3043 | K7: NoN Local Promo | L7: Gathering Only | M7: 0 | N7: 8333.3333 | O7: 0 | P7: 11077.8 | Q7: 48230.47
A8: 46235 | B8: SO.AV.2026.08.00004 | C8: SALES012 | D8: AVSY001 | E8: DIV 1 | F8: 5 | G8: 461575 | H8: 354759.24 | I8: 61074.09 | J8: 4706.087 | K8: NoN Local Promo | L8: Gathering Only | M8: 0 | N8: 7142.8571 | O8: 0 | P8: 9231.5 | Q8: 39993.646
A9: 46235 | B9: SO.AV.2026.08.00006 | C9: SALES001 | D9: AVSY100 | E9: DIV 1 | F9: 12 | G9: 167702.5 | H9: 129654.68 | I9: 21428.652 | J9: 1331.4783 | K9: NoN Local Promo | L9: Gathering Only | M9: 0 | N9: 3333.3333 | O9: 0 | P9: 3354.05 | Q9: 13409.791
A10: 46235 | B10: SO.AV.2026.08.00006 | C10: SALES001 | D10: AVSY500 | E10: DIV 1 | F10: 6 | G10: 315795 | H10: 240358.05 | I10: 44141.946 | J10: 2851.2 | K10: NoN Local Promo | L10: Gathering Only | M10: 0 | N10: 3333.3333 | O10: 0 | P10: 6315.9 | Q10: 31641.513
A11: 46235 | B11: SO.AV.2026.08.00007 | C11: SALES004 | D11: AVSY001 | E11: DIV 1 | F11: 6 | G11: 553890 | H11: 425711.09 | I11: 73288.908 | J11: 5647.3043 | K11: NoN Local Promo | L11: Non Campaign | M11: 0 | N11: 0 | O11: 0 | P11: 11077.8 | Q11: 56563.804
A12: 46235 | B12: SO.AV.2026.08.00008 | C12: SALES004 | D12: NODR001 | E12: DIV 2 | F12: 2 | G12: 152070 | H12: 115402.68 | I12: 21597.319 | J12: 1668.1739 | K12: Kontrak | L12: Contract | M12: 0 | N12: 0 | O12: 6082.8 | P12: 3041.4 | Q12: 10804.945
A13: 46235 | B13: SO.AV.2026.08.00009 | C13: SALES005 | D13: YOSY001 | E13: DIV 2 | F13: 18 | G13: 1243755 | H13: 941556.45 | I13: 178943.55 | J13: 11707.826 | K13: NoN Local Promo | L13: Gathering Only | M13: 0 | N13: 2941.1765 | O13: 0 | P13: 24875.1 | Q13: 139419.44
A14: 46235 | B14: SO.AV.2026.08.00010 | C14: SALES001 | D14: AVGO005 | E14: DIV 1 | F14: 2 | G14: 429015 | H14: 321555.94 | I14: 64944.065 | J14: 8004.1739 | K14: NoN Local Promo | L14: Gathering Only | M14: 0 | N14: 10000 | O14: 0 | P14: 8580.3 | Q14: 38359.591
A15: 46235 | B15: SO.AV.2026.08.00011 | C15: SALES001 | D15: ABEM001 | E15: DIV 1 | F15: 2 | G15: 61790 | H15: 45298.249 | I15: 10368.418 | J15: 1606.9565 | K15: NoN Local Promo | L15: Gathering Only | M15: 0 | N15: 3571.4286 | O15: 0 | P15: 1235.8 | Q15: 3954.2329
... A2158: 46265 | B2158: SO.GM.2026.08.00191 | C2158: SALES005 | D2158: AREM020KPSW | E2158: DIV 1-AREM | F2158: 1 | G2158: 237678.75 | H2158: 155793.62 | I2158: 58331.381 | J2158: 16107.826 | K2158: NoN Local Promo | L2158: Gathering Only | M2158: 0 | N2158: 2941.1765 | O2158: 0 | P2158: 4753.575 | Q2158: 34528.803

Sheet Data pre proccesed
A3: Sum of HJ Total | B3: Sum of Margin Akhir | C3: Sum of Biaya Promo | E3: Promo ID | F3: Sum of Margin Akhir | K3: Tanggal | L3: Sum of HJ Total
A4: 2.610796e+09 | B4: 2.3242902e+08 | C4: 59613325 | E4: Contract | F4: 34934494 | K4: 46235 | L4: 64664364
E5: Gathering Only | F5: 98017724 | K5: 46237 | L5: 1.1069718e+08
E6: Non Campaign | F6: 41697838 | K6: 46238 | L6: 96995616
E7: Local + Gathering | F7: 50218482 | K7: 46239 | L7: 164724154
A8: Tanggal | B8: Sum of HJ Total | C8: Sum of Margin Akhir | E8: Local Only | F8: 7560484.7 | K8: 46240 | L8: 69752929
A9: 46235 | B9: 64664364 | C9: 5952371.9 | E9: Grand Total | F9: 2.3242902e+08 | K9: 46241 | L9: 1.0094309e+08
A10: 46237 | B10: 1.1069718e+08 | C10: 10439303 | K10: 46242 | L10: 90209506
A11: 46238 | B11: 96995616 | C11: 7828619.5 | K11: 46244 | L11: 1.1645252e+08
A12: 46239 | B12: 164724154 | C12: 12585958 | K12: 46245 | L12: 90040534
A13: 46240 | B13: 69752929 | C13: 6605139.4 | E13: SALES | F13: Sum of HJ Total | G13: Sum of Margin Akhir | K13: 46246 | L13: 98197401
A14: 46241 | B14: 1.0094309e+08 | C14: 8173271.3 | E14: SALES001 | F14: 3.3139284e+08 | G14: 28130747 | K14: 46247 | L14: 65925736
A15: 46242 | B15: 90209506 | C15: 7189475.3 | E15: SALES006 | F15: 3.1429795e+08 | G15: 26183382 | K15: 46248 | L15: 88838592
A16: 46244 | B16: 1.1645252e+08 | C16: 9969032.9 | E16: SALES019 | F16: 2.6922981e+08 | G16: 23193013 | K16: 46249 | L16: 95085060
A17: 46245 | B17: 90040534 | C17: 7350247.1 | E17: SALES007 | F17: 2.1227754e+08 | G17: 20007541 | K17: 46252 | L17: 1.2929103e+08
A18: 46246 | B18: 98197401 | C18: 8825135.4 | E18: SALES008 | F18: 2.3048566e+08 | G18: 18897528 | K18: 46253 | L18: 1.0419795e+08
A19: 46247 | B19: 65925736 | C19: 5901472.4 | E19: SALES004 | F19: 1.9069135e+08 | G19: 16536005 | K19: 46254 | L19: 64784635
A20: 46248 | B20: 88838592 | C20: 7306947.1 | E20: SALES003 | F20: 1.5272131e+08 | G20: 15391293 | K20: 46255 | L20: 74782319
A21: 46249 | B21: 95085060 | C21: 9314132.8 | E21: SALES002 | F21: 1.4878307e+08 | G21: 13544994 | K21: 46256 | L21: 48658495
A22: 46252 | B22: 1.2929103e+08 | C22: 10686578 | E22: SALES018 | F22: 1.5046529e+08 | G22: 13463605 | K22: 46258 | L22: 1.1082383e+08
A23: 46253 | B23: 1.0419795e+08 | C23: 10161161 | E23: SALES005 | F23: 1.3389046e+08 | G23: 12920486 | K23: 46259 | L23: 87909409
A24: 46254 | B24: 64784635 | C24: 6187307.8 | E24: SALES012 | F24: 1.2484706e+08 | G24: 11836735 | K24: 46260 | L24: 94102289
A25: 46255 | B25: 74782319 | C25: 7381789.5 | E25: SALES010 | F25: 1.2150404e+08 | G25: 11164592 | K25: 46261 | L25: 74789706
... A28: 46259 | B28: 87909409 | C28: 8494003.3 | E28: Office | F28: 18936138 | G28: 2191960.9 | K28: 46265 | L28: 3.9884438e+08
A29: 46260 | B29: 94102289 | C29: 8613250.2 | E29: Grand Total | F29: 2.610796e+09 | G29: 2.3242902e+08 | K29: Grand Total | L29: 2.610796e+09
A30: 46261 | B30: 74789706 | C30: 7781223.4
A31: 46262 | B31: 87307672 | C31: 7639705.7
A32: 46263 | B32: 82777566 | C32: 7977610.1
A33: 46265 | B33: 3.9884438e+08 | C33: 35037145
A34: Grand Total | B34: 2.610796e+09 | C34: 2.3242902e+08
A40: Brand | B40: Sum of HJ Total | C40: Sum of Margin Akhir | G40: Status | H40: Sum of HJ Total | I40: Sum of Kontrak | J40: Sum of CB Promo | K40: Sum of Margin Akhir | M40: Values
A41: AVSY001 | B41: 784123610 | C41: 61398976 | G41: 148 | H41: 85299060 | I41: 0 | J41: 2280000 | K41: 5852815.3 | M41: Sum of Margin awal | N41: 3.9276956e+08
A42: AVEM005 | B42: 2.6023534e+08 | C42: 21738710 | G42: 151 | H42: 133040160 | I42: 0 | J42: 6300000 | K42: 8272048.8 | M42: Sum of CB Promo | N42: 19115000
A43: AVEM025 | B43: 205816200 | C43: 19039727 | G43: 153 | H43: 48546775 | I43: 0 | J43: 1600000 | K43: 3567618.9 | M43: Sum of Gathering | N43: 14000000
A44: ACSY001 | B44: 123401475 | C44: 11592507 | G44: 155 | H44: 191461310 | I44: 0 | J44: 4300000 | K44: 14249354 | M44: Sum of Kontrak | N44: 26498325
A45: NODR020 | B45: 105686800 | C45: 9996960.7 | G45: 159 | H45: 98450895 | I45: 0 | J45: 2010000 | K45: 8600912.4 | M45: Sum of 2% | N45: 47299145
A46: NODR004 | B46: 111474340 | C46: 9975630.3 | G46: 160 | H46: 4778272.5 | I46: 0 | J46: 125000 | K46: 367383.71 | M46: Sum of biaya pengiriman | N46: 53428065
A47: BOVE001 | B47: 1.0907914e+08 | C47: 9857180.4 | G47: 161 | H47: 22843800 | I47: 0 | J47: 500000 | K47: 1805778.5 | M47: Sum of Margin Akhir | N47: 2.3242902e+08
A48: AREM020KPSW | B48: 75106485 | C48: 9666794.7 | G48: 164 | H48: 178537210 | I48: 0 | J48: 2000000 | K48: 15094418
A49: NODR001 | B49: 64553715 | C49: 6118987.4 | G49: Kontrak | H49: 5.0720182e+08 | I49: 26498325 | J49: 0 | K49: 34676551
A50: AVGO025 | B50: 70430888 | C50: 5802539.8 | G50: NoN Local Promo | H50: 1.3406367e+09 | I50: 0 | J50: 0 | K50: 1.3994214e+08
A51: Grand Total | B51: 1909907995 | C51: 1.6518801e+08 | G51: Grand Total | H51: 2.610796e+09 | I51: 26498325 | J51: 19115000 | K51: 2.3242902e+08

Sheet DASHBOARD
B3: SALES OVERVIEW
B4: AUGUST PROMO PERFORMANCE DASHBOARD
C7: Total Sales | E7: Margin akhir | I7: Biaya Promo | L7: Persen Margin Akhir
C8: =GETPIVOTDATA("HJ Total",'Data pre proccesed'!$A$3) -> 2.610796e+09 | E8: =GETPIVOTDATA("Margin Akhir",'Data pre proccesed'!$B$3) -> 2.3242902e+08 | I8: =GETPIVOTDATA("Biaya Promo",'Data pre proccesed'!$C$3) -> 59613325 | L8: =GETPIVOTDATA("Margin Akhir",'Data pre proccesed'!$B$3)/GETPIVOTDATA("HJ Total",'Data pre proccesed'!$A$3) -> 0.089026116
C10: =2785110312-C8 -> 1.7431436e+08 | E10: =245956486-E8 -> 13527463 | I10: =66857477-I8 -> 7244151.6 | L10: =ABS(8.83%-L8) -> 0.00072611579
C11: Previous : 2.785.110.312 | E11: Previous : 245.956.486 | I11: Previous : 66.857.477 | L11: ="Previous: "&(245956486/2785110312)*100&" %" -> Previous: 8.8311218747877 %
L47: Component | M47: Amount | N47: Persentage leaked
L48: Margin awal | M48: =GETPIVOTDATA("Sum of Margin awal",'Data pre proccesed'!$M$40) -> 3.9276956e+08 | N48: =M48/$M$48 -> 1
L49: CB Promo | M49: =-GETPIVOTDATA("Sum of CB Promo",'Data pre proccesed'!$M$40) -> -19115000 | N49: =M49/$M$48 -> -0.048667214
L50: Gathering | M50: =-GETPIVOTDATA("Sum of Gathering",'Data pre proccesed'!$M$40) -> -14000000 | N50: =M50/$M$48 -> -0.03564431
L51: Kontrak | M51: =-GETPIVOTDATA("Sum of Kontrak",'Data pre proccesed'!$M$40) -> -26498325 | N51: =M51/$M$48 -> -0.067465324
L52: Potongan 2% | M52: =-GETPIVOTDATA("Sum of 2%",'Data pre proccesed'!$M$40) -> -47299145 | N52: =M52/$M$48 -> -0.12042467
L53: biaya pengiriman | M53: =-GETPIVOTDATA("Sum of biaya pengiriman",'Data pre proccesed'!$M$40) -> -53428065 | N53: =M53/$M$48 -> -0.13602904
L54: Margin Akhir | M54: =GETPIVOTDATA("Sum of Margin Akhir",'Data pre proccesed'!$M$40) -> 2.3242902e+08 | N54: =M54/$M$48 -> 0.59176944
J62: List Promo | K62: Pencapaian | L62: Reward | M62: Margin Akhir | N62: Persen Margin | O62: Persen biaya
J63: NoN Local Promo | K63: =GETPIVOTDATA("Sum of HJ Total",'Data pre proccesed'!$G$40,"Status","NoN Local Promo") -> 1.3406367e+09 | L63: =GETPIVOTDATA("Sum of Kontrak",'Data pre proccesed'!$G$40,"Status","NoN Local Promo") -> 0 | M63: =GETPIVOTDATA("Sum of Margin Akhir",'Data pre proccesed'!$G$40,"Status","NoN Local Promo") -> 1.3994214e+08 | N63: =M63/K63 -> 0.10438484 | O63: =L63/K63 -> 0
J64: 159 | K64: =GETPIVOTDATA("Sum of HJ Total",'Data pre proccesed'!$G$40,"Status","159") -> 98450895 | L64: =GETPIVOTDATA("Sum of CB Promo",'Data pre proccesed'!$G$40,"Status","159") -> 2010000 | M64: =GETPIVOTDATA("Sum of Margin Akhir",'Data pre proccesed'!$G$40,"Status","159") -> 8600912.4 | N64: =M64/K64 -> 0.08736246 | O64: =L64/K64 -> 0.020416269
J65: 164 | K65: =GETPIVOTDATA("Sum of HJ Total",'Data pre proccesed'!$G$40,"Status","164") -> 178537210 | L65: =GETPIVOTDATA("Sum of CB Promo",'Data pre proccesed'!$G$40,"Status","164") -> 2000000 | M65: =GETPIVOTDATA("Sum of Margin Akhir",'Data pre proccesed'!$G$40,"Status","164") -> 15094418 | N65: =M65/K65 -> 0.084544941 | O65: =L65/K65 -> 0.011202147
J66: 161 | K66: =GETPIVOTDATA("Sum of HJ Total",'Data pre proccesed'!$G$40,"Status","161") -> 22843800 | L66: =GETPIVOTDATA("Sum of CB Promo",'Data pre proccesed'!$G$40,"Status","161") -> 500000 | M66: =GETPIVOTDATA("Sum of Margin Akhir",'Data pre proccesed'!$G$40,"Status","161") -> 1805778.5 | N66: =M66/K66 -> 0.079048956 | O66: =L66/K66 -> 0.021887777
J67: 160 | K67: =GETPIVOTDATA("Sum of HJ Total",'Data pre proccesed'!$G$40,"Status","160") -> 4778272.5 | L67: =GETPIVOTDATA("Sum of CB Promo",'Data pre proccesed'!$G$40,"Status","160") -> 125000 | M67: =GETPIVOTDATA("Sum of Margin Akhir",'Data pre proccesed'!$G$40,"Status","160") -> 367383.71 | N67: =M67/K67 -> 0.076886303 | O67: =L67/K67 -> 0.026160082
J68: 155 | K68: =GETPIVOTDATA("Sum of HJ Total",'Data pre proccesed'!$G$40,"Status","155") -> 191461310 | L68: =GETPIVOTDATA("Sum of CB Promo",'Data pre proccesed'!$G$40,"Status","155") -> 4300000 | M68: =GETPIVOTDATA("Sum of Margin Akhir",'Data pre proccesed'!$G$40,"Status","155") -> 14249354 | N68: =M68/K68 -> 0.074424193 | O68: =L68/K68 -> 0.022458846
J69: 153 | K69: =GETPIVOTDATA("Sum of HJ Total",'Data pre proccesed'!$G$40,"Status","153") -> 48546775 | L69: =GETPIVOTDATA("Sum of CB Promo",'Data pre proccesed'!$G$40,"Status","153") -> 1600000 | M69: =GETPIVOTDATA("Sum of Margin Akhir",'Data pre proccesed'!$G$40,"Status","153") -> 3567618.9 | N69: =M69/K69 -> 0.073488278 | O69: =L69/K69 -> 0.032957905
J70: 148 | K70: =GETPIVOTDATA("Sum of HJ Total",'Data pre proccesed'!$G$40,"Status","148") -> 85299060 | L70: =GETPIVOTDATA("Sum of CB Promo",'Data pre proccesed'!$G$40,"Status","148") -> 2280000 | M70: =GETPIVOTDATA("Sum of Margin Akhir",'Data pre proccesed'!$G$40,"Status","148") -> 5852815.3 | N70: =M70/K70 -> 0.068615238 | O70: =L70/K70 -> 0.026729486
J71: Kontrak | K71: =GETPIVOTDATA("Sum of HJ Total",'Data pre proccesed'!$G$40,"Status","Kontrak") -> 5.0720182e+08 | L71: =GETPIVOTDATA("Sum of Kontrak",'Data pre proccesed'!$G$40,"Status","Kontrak") -> 26498325 | M71: =GETPIVOTDATA("Sum of Margin Akhir",'Data pre proccesed'!$G$40,"Status","Kontrak") -> 34676551 | N71: =M71/K71 -> 0.068368349 | O71: =L71/K71 -> 0.052244145
J72: 151 | K72: =GETPIVOTDATA("Sum of HJ Total",'Data pre proccesed'!$G$40,"Status","151") -> 133040160 | L72: =GETPIVOTDATA("Sum of CB Promo",'Data pre proccesed'!$G$40,"Status","151") -> 6300000 | M72: =GETPIVOTDATA("Sum of Margin Akhir",'Data pre proccesed'!$G$40,"Status","151") -> 8272048.8 | N72: =M72/K72 -> 0.062177081 | O72: =L72/K72 -> 0.047354122

Sheet acc gathering
A1: ATLAS MITRA BERLIAN
A2: Rekap Pencapaian Promo Atlas 162/I/PR-AMB/CV/VIII/26 Gathering
A3: Periode : 01 Agustus- 31 Agustus 2025
A5: Pelanggan | B5: Total | C5: SALES | D5: Retur | E5: Total | F5: Uang tunai 50rb | G5: Potongan 50rb
A6: Hendi Jaya | B6: 51036320 | C6: SALES001 | E6: =B6-D6 -> 51036320 | F6: =IF(OR(C6="SALES001",C6="SALES002",C6="SALES003",C6="SALES004", C6="SALES012",C6="SALES014",C6="ROSDIANA PERMATA SARI"),((ROUNDDOWN(E6/5000000,0))*50000),0) -> 500000 | G6: =IF(F6=0,((ROUNDDOWN(E6/5000000,0))*50000),0) -> 0
A7: Tony Jaya (Bagan Pete) | B7: 17589985 | C7: SALES001 | E7: =B7-D7 -> 17589985 | F7: =IF(OR(C7="SALES001",C7="SALES002",C7="SALES003",C7="SALES004", C7="SALES012",C7="SALES014",C7="ROSDIANA PERMATA SARI"),((ROUNDDOWN(E7/5000000,0))*50000),0) -> 150000 | G7: =IF(F7=0,((ROUNDDOWN(E7/5000000,0))*50000),0) -> 0
A8: Mikayla Jaya | B8: 16025255 | C8: SALES001 | E8: =B8-D8 -> 16025255 | F8: =IF(OR(C8="SALES001",C8="SALES002",C8="SALES003",C8="SALES004", C8="SALES012",C8="SALES014",C8="ROSDIANA PERMATA SARI"),((ROUNDDOWN(E8/5000000,0))*50000),0) -> 150000 | G8: =IF(F8=0,((ROUNDDOWN(E8/5000000,0))*50000),0) -> 0
A9: Sekawan Jaya | B9: 12763242 | C9: SALES001 | E9: =B9-D9 -> 12763242 | F9: =IF(OR(C9="SALES001",C9="SALES002",C9="SALES003",C9="SALES004", C9="SALES012",C9="SALES014",C9="ROSDIANA PERMATA SARI"),((ROUNDDOWN(E9/5000000,0))*50000),0) -> 100000 | G9: =IF(F9=0,((ROUNDDOWN(E9/5000000,0))*50000),0) -> 0
A10: Putra Berlian | B10: 10895020 | C10: SALES001 | E10: =B10-D10 -> 10895020 | F10: =IF(OR(C10="SALES001",C10="SALES002",C10="SALES003",C10="SALES004", C10="SALES012",C10="SALES014",C10="ROSDIANA PERMATA SARI"),((ROUNDDOWN(E10/5000000,0))*50000),0) -> 100000 | G10: =IF(F10=0,((ROUNDDOWN(E10/5000000,0))*50000),0) -> 0
A11: Mutiara Hijau | B11: 10512819 | C11: SALES001 | E11: =B11-D11 -> 10512819 | F11: =IF(OR(C11="SALES001",C11="SALES002",C11="SALES003",C11="SALES004", C11="SALES012",C11="SALES014",C11="ROSDIANA PERMATA SARI"),((ROUNDDOWN(E11/5000000,0))*50000),0) -> 100000 | G11: =IF(F11=0,((ROUNDDOWN(E11/5000000,0))*50000),0) -> 0
A12: Naga Terang | B12: 10365938 | C12: SALES001 | E12: =B12-D12 -> 10365938 | F12: =IF(OR(C12="SALES001",C12="SALES002",C12="SALES003",C12="SALES004", C12="SALES012",C12="SALES014",C12="ROSDIANA PERMATA SARI"),((ROUNDDOWN(E12/5000000,0))*50000),0) -> 100000 | G12: =IF(F12=0,((ROUNDDOWN(E12/5000000,0))*50000),0) -> 0
A13: Hendra Jaya | B13: 8560135 | C13: SALES001 | E13: =B13-D13 -> 8560135 | F13: =IF(OR(C13="SALES001",C13="SALES002",C13="SALES003",C13="SALES004", C13="SALES012",C13="SALES014",C13="ROSDIANA PERMATA SARI"),((ROUNDDOWN(E13/5000000,0))*50000),0) -> 50000 | G13: =IF(F13=0,((ROUNDDOWN(E13/5000000,0))*50000),0) -> 0
A14: PT. Tayang Sari | B14: 7818682.8 | C14: SALES001 | E14: =B14-D14 -> 7818682.8 | F14: =IF(OR(C14="SALES001",C14="SALES002",C14="SALES003",C14="SALES004", C14="SALES012",C14="SALES014",C14="ROSDIANA PERMATA SARI"),((ROUNDDOWN(E14/5000000,0))*50000),0) -> 50000 | G14: =IF(F14=0,((ROUNDDOWN(E14/5000000,0))*50000),0) -> 0
A15: JAYA BANGUN UTAMA | B15: 6160870 | C15: SALES001 | E15: =B15-D15 -> 6160870 | F15: =IF(OR(C15="SALES001",C15="SALES002",C15="SALES003",C15="SALES004", C15="SALES012",C15="SALES014",C15="ROSDIANA PERMATA SARI"),((ROUNDDOWN(E15/5000000,0))*50000),0) -> 50000 | G15: =IF(F15=0,((ROUNDDOWN(E15/5000000,0))*50000),0) -> 0
A16: Agung Wijaya | B16: 6080210 | C16: SALES001 | E16: =B16-D16 -> 6080210 | F16: =IF(OR(C16="SALES001",C16="SALES002",C16="SALES003",C16="SALES004", C16="SALES012",C16="SALES014",C16="ROSDIANA PERMATA SARI"),((ROUNDDOWN(E16/5000000,0))*50000),0) -> 50000 | G16: =IF(F16=0,((ROUNDDOWN(E16/5000000,0))*50000),0) -> 0
A17: Mapan Jaya | B17: 5644313 | C17: SALES001 | E17: =B17-D17 -> 5644313 | F17: =IF(OR(C17="SALES001",C17="SALES002",C17="SALES003",C17="SALES004", C17="SALES012",C17="SALES014",C17="ROSDIANA PERMATA SARI"),((ROUNDDOWN(E17/5000000,0))*50000),0) -> 50000 | G17: =IF(F17=0,((ROUNDDOWN(E17/5000000,0))*50000),0) -> 0
... A101: Maju Tb | B101: 8742267.5 | C101: SALES005 | E101: =B101-D101 -> 8742267.5 | F101: =IF(OR(C101="SALES001",C101="SALES002",C101="SALES003",C101="SALES004", C101="SALES012",C101="SALES014",C101="ROSDIANA PERMATA SARI"),((ROUNDDOWN(E101/5000000,0))*50000),0) -> 0 | G101: =IF(F101=0,((ROUNDDOWN(E101/5000000,0))*50000),0) -> 50000
A102: Pemayung Indah | B102: 8768167.5 | C102: SALES005 | D102: 1222937 | E102: =B102-D102 -> 7545230.5 | F102: =IF(OR(C102="SALES001",C102="SALES002",C102="SALES003",C102="SALES004", C102="SALES012",C102="SALES014",C102="ROSDIANA PERMATA SARI"),((ROUNDDOWN(E102/5000000,0))*50000),0) -> 0 | G102: =IF(F102=0,((ROUNDDOWN(E102/5000000,0))*50000),0) -> 50000
A103: Sinar Harapan | B103: 7274200 | C103: SALES005 | E103: =B103-D103 -> 7274200 | F103: =IF(OR(C103="SALES001",C103="SALES002",C103="SALES003",C103="SALES004", C103="SALES012",C103="SALES014",C103="ROSDIANA PERMATA SARI"),((ROUNDDOWN(E103/5000000,0))*50000),0) -> 0 | G103: =IF(F103=0,((ROUNDDOWN(E103/5000000,0))*50000),0) -> 50000
A104: Intan Jaya | B104: 6622910 | C104: SALES005 | E104: =B104-D104 -> 6622910 | F104: =IF(OR(C104="SALES001",C104="SALES002",C104="SALES003",C104="SALES004", C104="SALES012",C104="SALES014",C104="ROSDIANA PERMATA SARI"),((ROUNDDOWN(E104/5000000,0))*50000),0) -> 0 | G104: =IF(F104=0,((ROUNDDOWN(E104/5000000,0))*50000),0) -> 50000
A105: Akbar Mandiri | B105: 6562930.5 | C105: SALES005 | E105: =B105-D105 -> 6562930.5 | F105: =IF(OR(C105="SALES001",C105="SALES002",C105="SALES003",C105="SALES004", C105="SALES012",C105="SALES014",C105="ROSDIANA PERMATA SARI"),((ROUNDDOWN(E105/5000000,0))*50000),0) -> 0 | G105: =IF(F105=0,((ROUNDDOWN(E105/5000000,0))*50000),0) -> 50000
A106: Sinar Rengas | B106: 6371122.5 | C106: SALES005 | E106: =B106-D106 -> 6371122.5 | F106: =IF(OR(C106="SALES001",C106="SALES002",C106="SALES003",C106="SALES004", C106="SALES012",C106="SALES014",C106="ROSDIANA PERMATA SARI"),((ROUNDDOWN(E106/5000000,0))*50000),0) -> 0 | G106: =IF(F106=0,((ROUNDDOWN(E106/5000000,0))*50000),0) -> 50000
A107: Alif Bangunan | B107: 6338655 | C107: SALES005 | E107: =B107-D107 -> 6338655 | F107: =IF(OR(C107="SALES001",C107="SALES002",C107="SALES003",C107="SALES004", C107="SALES012",C107="SALES014",C107="ROSDIANA PERMATA SARI"),((ROUNDDOWN(E107/5000000,0))*50000),0) -> 0 | G107: =IF(F107=0,((ROUNDDOWN(E107/5000000,0))*50000),0) -> 50000
A108: Suryadi / Empat Saudara | B108: 5683052 | C108: SALES005 | E108: =B108-D108 -> 5683052 | F108: =IF(OR(C108="SALES001",C108="SALES002",C108="SALES003",C108="SALES004", C108="SALES012",C108="SALES014",C108="ROSDIANA PERMATA SARI"),((ROUNDDOWN(E108/5000000,0))*50000),0) -> 0 | G108: =IF(F108=0,((ROUNDDOWN(E108/5000000,0))*50000),0) -> 50000
A109: Sinar Surya | B109: 5119320 | C109: SALES005 | E109: =B109-D109 -> 5119320 | F109: =IF(OR(C109="SALES001",C109="SALES002",C109="SALES003",C109="SALES004", C109="SALES012",C109="SALES014",C109="ROSDIANA PERMATA SARI"),((ROUNDDOWN(E109/5000000,0))*50000),0) -> 0 | G109: =IF(F109=0,((ROUNDDOWN(E109/5000000,0))*50000),0) -> 50000
A110: Mowi Jaya | B110: 4641835 | C110: SALES005 | E110: =B110-D110 -> 4641835 | F110: =IF(OR(C110="SALES001",C110="SALES002",C110="SALES003",C110="SALES004", C110="SALES012",C110="SALES014",C110="ROSDIANA PERMATA SARI"),((ROUNDDOWN(E110/5000000,0))*50000),0) -> 0 | G110: =IF(F110=0,((ROUNDDOWN(E110/5000000,0))*50000),0) -> 0
A111: KIM BANGUN JAYA | B111: 3561712.5 | C111: SALES005 | E111: =B111-D111 -> 3561712.5 | F111: =IF(OR(C111="SALES001",C111="SALES002",C111="SALES003",C111="SALES004", C111="SALES012",C111="SALES014",C111="ROSDIANA PERMATA SARI"),((ROUNDDOWN(E111/5000000,0))*50000),0) -> 0 | G111: =IF(F111=0,((ROUNDDOWN(E111/5000000,0))*50000),0) -> 0
A112: Azzahra | B112: 3542990.5 | C112: SALES005 | E112: =B112-D112 -> 3542990.5 | F112: =IF(OR(C112="SALES001",C112="SALES002",C112="SALES003",C112="SALES004", C112="SALES012",C112="SALES014",C112="ROSDIANA PERMATA SARI"),((ROUNDDOWN(E112/5000000,0))*50000),0) -> 0 | G112: =IF(F112=0,((ROUNDDOWN(E112/5000000,0))*50000),0) -> 0
A113: Mawan Jaya (Simpang Karmeo) | B113: 3477907.5 | C113: SALES005 | E113: =B113-D113 -> 3477907.5 | F113: =IF(OR(C113="SALES001",C113="SALES002",C113="SALES003",C113="SALES004", C113="SALES012",C113="SALES014",C113="ROSDIANA PERMATA SARI"),((ROUNDDOWN(E113/5000000,0))*50000),0) -> 0 | G113: =IF(F113=0,((ROUNDDOWN(E113/5000000,0))*50000),0) -> 0
A114: Jaya Kampung Tengah | B114: 2622023.5 | C114: SALES005 | E114: =B114-D114 -> 2622023.5 | F114: =IF(OR(C114="SALES001",C114="SALES002",C114="SALES003",C114="SALES004", C114="SALES012",C114="SALES014",C114="ROSDIANA PERMATA SARI"),((ROUNDDOWN(E114/5000000,0))*50000),0) -> 0 | G114: =IF(F114=0,((ROUNDDOWN(E114/5000000,0))*50000),0) -> 0
A115: TB Sukses Jaya | B115: 2484550 | C115: SALES005 | E115: =B115-D115 -> 2484550 | F115: =IF(OR(C115="SALES001",C115="SALES002",C115="SALES003",C115="SALES004", C115="SALES012",C115="SALES014",C115="ROSDIANA PERMATA SARI"),((ROUNDDOWN(E115/5000000,0))*50000),0) -> 0 | G115: =IF(F115=0,((ROUNDDOWN(E115/5000000,0))*50000),0) -> 0
A116: Tembesi Lamo | B116: 4185773 | C116: SALES005 | D116: 2061270 | E116: =B116-D116 -> 2124503 | F116: =IF(OR(C116="SALES001",C116="SALES002",C116="SALES003",C116="SALES004", C116="SALES012",C116="SALES014",C116="ROSDIANA PERMATA SARI"),((ROUNDDOWN(E116/5000000,0))*50000),0) -> 0 | G116: =IF(F116=0,((ROUNDDOWN(E116/5000000,0))*50000),0) -> 0
A117: Umran Jaya Abadi | B117: 1451880 | C117: SALES005 | E117: =B117-D117 -> 1451880 | F117: =IF(OR(C117="SALES001",C117="SALES002",C117="SALES003",C117="SALES004", C117="SALES012",C117="SALES014",C117="ROSDIANA PERMATA SARI"),((ROUNDDOWN(E117/5000000,0))*50000),0) -> 0 | G117: =IF(F117=0,((ROUNDDOWN(E117/5000000,0))*50000),0) -> 0
A118: Eddy (Bajubang) | B118: 894660 | C118: SALES005 | E118: =B118-D118 -> 894660 | F118: =IF(OR(C118="SALES001",C118="SALES002",C118="SALES003",C118="SALES004", C118="SALES012",C118="SALES014",C118="ROSDIANA PERMATA SARI"),((ROUNDDOWN(E118/5000000,0))*50000),0) -> 0 | G118: =IF(F118=0,((ROUNDDOWN(E118/5000000,0))*50000),0) -> 0
A119: Daffa Jaya Plafon | B119: 528175 | C119: SALES005 | E119: =B119-D119 -> 528175 | F119: =IF(OR(C119="SALES001",C119="SALES002",C119="SALES003",C119="SALES004", C119="SALES012",C119="SALES014",C119="ROSDIANA PERMATA SARI"),((ROUNDDOWN(E119/5000000,0))*50000),0) -> 0 | G119: =IF(F119=0,((ROUNDDOWN(E119/5000000,0))*50000),0) -> 0
A120: Barokah | B120: 283790 | C120: SALES005 | E120: =B120-D120 -> 283790 | F120: =IF(OR(C120="SALES001",C120="SALES002",C120="SALES003",C120="SALES004", C120="SALES012",C120="SALES014",C120="ROSDIANA PERMATA SARI"),((ROUNDDOWN(E120/5000000,0))*50000),0) -> 0 | G120: =IF(F120=0,((ROUNDDOWN(E120/5000000,0))*50000),0) -> 0
A121: Sumber Material | B121: 264087.5 | C121: SALES005 | E121: =B121-D121 -> 264087.5 | F121: =IF(OR(C121="SALES001",C121="SALES002",C121="SALES003",C121="SALES004", C121="SALES012",C121="SALES014",C121="ROSDIANA PERMATA SARI"),((ROUNDDOWN(E121/5000000,0))*50000),0) -> 0 | G121: =IF(F121=0,((ROUNDDOWN(E121/5000000,0))*50000),0) -> 0
A122: Terbit | B122: 16659712 | C122: SALES006 | E122: =B122-D122 -> 16659712 | F122: =IF(OR(C122="SALES001",C122="SALES002",C122="SALES003",C122="SALES004", C122="SALES012",C122="SALES014",C122="ROSDIANA PERMATA SARI"),((ROUNDDOWN(E122/5000000,0))*50000),0) -> 0 | G122: =IF(F122=0,((ROUNDDOWN(E122/5000000,0))*50000),0) -> 150000
A123: Usaha Jaya 2 | B123: 16495044 | C123: SALES006 | E123: =B123-D123 -> 16495044 | F123: =IF(OR(C123="SALES001",C123="SALES002",C123="SALES003",C123="SALES004", C123="SALES012",C123="SALES014",C123="ROSDIANA PERMATA SARI"),((ROUNDDOWN(E123/5000000,0))*50000),0) -> 0 | G123: =IF(F123=0,((ROUNDDOWN(E123/5000000,0))*50000),0) -> 150000
A124: Sejati ( Tungkal ) | B124: 13932669 | C124: SALES006 | E124: =B124-D124 -> 13932669 | F124: =IF(OR(C124="SALES001",C124="SALES002",C124="SALES003",C124="SALES004", C124="SALES012",C124="SALES014",C124="ROSDIANA PERMATA SARI"),((ROUNDDOWN(E124/5000000,0))*50000),0) -> 0 | G124: =IF(F124=0,((ROUNDDOWN(E124/5000000,0))*50000),0) -> 100000
A125: HARAPAN UTAMA INDAH (Guntung) | B125: 10986410 | C125: SALES006 | E125: =B125-D125 -> 10986410 | F125: =IF(OR(C125="SALES001",C125="SALES002",C125="SALES003",C125="SALES004", C125="SALES012",C125="SALES014",C125="ROSDIANA PERMATA SARI"),((ROUNDDOWN(E125/5000000,0))*50000),0) -> 0 | G125: =IF(F125=0,((ROUNDDOWN(E125/5000000,0))*50000),0) -> 100000
A126: Sinar Maju | B126: 10930262 | C126: SALES006 | E126: =B126-D126 -> 10930262 | F126: =IF(OR(C126="SALES001",C126="SALES002",C126="SALES003",C126="SALES004", C126="SALES012",C126="SALES014",C126="ROSDIANA PERMATA SARI"),((ROUNDDOWN(E126/5000000,0))*50000),0) -> 0 | G126: =IF(F126=0,((ROUNDDOWN(E126/5000000,0))*50000),0) -> 100000
A127: Berkat Bintang 2 (P. Lumut) | B127: 8285410 | C127: SALES006 | E127: =B127-D127 -> 8285410 | F127: =IF(OR(C127="SALES001",C127="SALES002",C127="SALES003",C127="SALES004", C127="SALES012",C127="SALES014",C127="ROSDIANA PERMATA SARI"),((ROUNDDOWN(E127/5000000,0))*50000),0) -> 0 | G127: =IF(F127=0,((ROUNDDOWN(E127/5000000,0))*50000),0) -> 50000
A128: Sumber Rejeki Baru | B128: 7204640 | C128: SALES006 | E128: =B128-D128 -> 7204640 | F128: =IF(OR(C128="SALES001",C128="SALES002",C128="SALES003",C128="SALES004", C128="SALES012",C128="SALES014",C128="ROSDIANA PERMATA SARI"),((ROUNDDOWN(E128/5000000,0))*50000),0) -> 0 | G128: =IF(F128=0,((ROUNDDOWN(E128/5000000,0))*50000),0) -> 50000
... A332: Berkat Usaha (Babeko) | B332: 171772.5 | C332: SALES019 | E332: =B332-D332 -> 171772.5 | F332: =IF(OR(C332="SALES001",C332="SALES002",C332="SALES003",C332="SALES004", C332="SALES012",C332="SALES014",C332="ROSDIANA PERMATA SARI"),((ROUNDDOWN(E332/5000000,0))*50000),0) -> 0 | G332: =IF(F332=0,((ROUNDDOWN(E332/5000000,0))*50000),0) -> 0
A333: Grand Total | B333: =SUM(B6:B332) -> 2.0125242e+09 | D333: =SUM(D6:D332) -> 3284207 | E333: =SUM(E6:E332) -> 2.00924e+09 | F333: =SUM(F6:F332) -> 6200000 | G333: =SUM(G6:G332) -> 7800000

Sheet Rincian Pesanan Penjualan
B1: CV. ATLAS MITRA BERLIAN
B2: Rincian Pesanan Penjualan
B3: From 13 Jun 2026 until 20 Jun 2026
B4: Branch : Kantor Pusat, Filtered by : Status Pesanan Penjualan
B5: Kode # | D5: Kategori | F5: Nama Barang | H5: Kuantitas | J5: Kts (Unit#1) | L5: Nama Satuan | N5: Keterangan Pesanan Penjualan | P5: Total Harga | R5: Nomor # | T5: Tanggal | V5: Pelanggan | X5: Sub Total | Z5: Total | AB5: Nama Syarat Pembayaran Pesanan Penjualan | AD5: Nama Departemen | AF5: Nama Tenaga Penjual | AH5: Status Pesanan Penjualan | AJ5: Diskon Pesanan Penjualan
B6: VIPL100C | D6: BAHAN BANGUNAN | F6: Viplas Lem PVC 100 Gr | H6: 12 | J6: 12 | L6: KL | P6: 231157.5 | R6: SO.AV.2026.06.00626 | T6: 46186 | V6: Bintang Baru (Rambahan) | X6: 231157.5 | Z6: 231157.5 | AB6: net 42 | AD6: Avia Avian | AF6: SALES007 | AH6: Processed | AJ6: 0
B7: AVSY001K303 | D7: DIVISI 1 CAT | F7: AVIAN Synthetic 303 0.9 Lt | H7: 6 | J7: 6 | L7: KL | N7: 114 | P7: 553890 | R7: SO.AV.2026.06.01069 | T7: 46192 | V7: Andeslint | X7: 2215560 | Z7: 2215560 | AB7: net 42 | AD7: Avia Avian | AF7: SALES019 | AH7: Processed | AJ7: 0
B8: AVSY001K331 | D8: DIVISI 1 CAT | F8: AVIAN Synthetic 331 0.9 Lt | H8: 6 | J8: 6 | L8: KL | N8: 114 | P8: 553890 | R8: SO.AV.2026.06.01069 | T8: 46192 | V8: Andeslint | X8: 2215560 | Z8: 2215560 | AB8: net 42 | AD8: Avia Avian | AF8: SALES019 | AH8: Processed | AJ8: 0
B9: NODR001K001 | D9: DIVISI 2 CAT | F9: NO DROP 001 1 Kg | H9: 3 | J9: 3 | L9: KL | P9: 228105 | R9: SO.AV.2026.06.00835 | T9: 46189 | V9: Batanghari Jaya | X9: 456210 | Z9: 456210 | AB9: net 42 | AD9: Avia Avian | AF9: SALES001 | AH9: Processed | AJ9: 0
B10: NODR001K009 | D10: DIVISI 2 CAT | F10: NO DROP 009 1 Kg | H10: 3 | J10: 3 | L10: KL | P10: 228105 | R10: SO.AV.2026.06.00835 | T10: 46189 | V10: Batanghari Jaya | X10: 456210 | Z10: 456210 | AB10: net 42 | AD10: Avia Avian | AF10: SALES001 | AH10: Processed | AJ10: 0
B11: AVEM005KSW | D11: DIVISI 1 CAT | F11: AVITEX Emulsion SW 5 Kg | H11: 1 | J11: 4 | L11: DS | N11: 110 | P11: 687090 | R11: SO.AV.2026.06.00837 | T11: 46189 | V11: Putra Berlian | X11: 687090 | Z11: 687090 | AB11: net 42 | AD11: Avia Avian | AF11: SALES001 | AH11: Processed | AJ11: 0
B12: BOVE001KS611 | D12: DIVISI 1 CAT | F12: BOYO Politur Vernis S611 1 Lt | H12: 4 | J12: 4 | L12: KL | P12: 380730 | R12: SO.AV.2026.06.00834 | T12: 46189 | V12: Sumber Maju Jaya | X12: 380730 | Z12: 380730 | AB12: net 42 | AD12: Avia Avian | AF12: SALES004 | AH12: Processed | AJ12: 0
B13: AVLE200CHEHAR | D13: DIVISI 1 CAT | F13: AVIAN Lem Epoxy Hemat Hardener 340 CC | H13: 4 | J13: 4 | L13: KL | P13: 0 | R13: SO.AV.2026.06.01093 | T13: 46193 | V13: Sumber Maju Jaya | X13: 269730 | Z13: 269730 | AB13: net 42 | AD13: Avia Avian | AF13: SALES004 | AH13: Processed | AJ13: 0
B14: AVLE200CHEPOX | D14: DIVISI 1 CAT | F14: AVIAN Lem Epoxy Hemat Resin 340 CC | H14: 3 | J14: 3 | L14: KL | P14: 202297.5 | R14: SO.AV.2026.06.00709 | T14: 46186 | V14: Maju Jaya ( Sipin ) | X14: 202297.5 | Z14: 202297.5 | AB14: net 42 | AD14: Avia Avian | AF14: SALES002 | AH14: Processed | AJ14: 0
B15: NODR004K009 | D15: DIVISI 2 CAT | F15: NO DROP 009 4 Kg | H15: 2 | J15: 2 | L15: KL | N15: 111 han jaya 1 | P15: 574610 | R15: SO.AV.2026.06.00891 | T15: 46190 | V15: Han Jaya | X15: 1149220 | Z15: 1149220 | AB15: net 42 | AD15: Avia Avian | AF15: SALES004 | AH15: Processed | AJ15: 0
B16: AREM005KSW | D16: DIVISI 1 CAT - AREM | F16: ARIES Emulsion SW 5 Kg | H16: 2 | J16: 2 | L16: KL | P16: 141895 | R16: SO.GM.2026.06.00095 | T16: 46190 | V16: BuildXpert Mart | X16: 141895 | Z16: 141895 | AB16: net 42 | AD16: Avia Avian | AF16: Office | AH16: Processed | AJ16: 0
B17: AVEM005K601 | D17: DIVISI 1 CAT | F17: AVITEX Emulsion 601 5 Kg | H17: 1 | J17: 4 | L17: DS | N17: 112 | P17: 687090 | R17: SO.AV.2026.06.01035 | T17: 46192 | V17: Eko Jaya | X17: 2061270 | Z17: 2061270 | AB17: net 42 | AD17: Avia Avian | AF17: SALES007 | AH17: Processed | AJ17: 0
B18: AVLE200CHAR | D18: DIVISI 1 CAT | F18: AVIAN Lem Epoxy Hardener 340 Gr 30 Set | H18: 15 | J18: 15 | L18: KL | P18: 0 | R18: SO.AV.2026.06.00879 | T18: 46190 | V18: Setia Makmur (Rantau Rasau) | X18: 2408515 | Z18: 2408515 | AB18: net 42 | AD18: Avia Avian | AF18: SALES007 | AH18: Processed | AJ18: 0
B19: AVEM005KSW | D19: DIVISI 1 CAT | F19: AVITEX Emulsion SW 5 Kg | H19: 1 | J19: 4 | L19: DS | N19: 112 | P19: 687090 | R19: SO.AV.2026.06.01092 | T19: 46193 | V19: Sejati ( Tungkal ) | X19: 687090 | Z19: 687090 | AB19: net 42 | AD19: Avia Avian | AF19: Jhondry Ferdians | AH19: Processed | AJ19: 0
B20: GIMO040KP385 | D20: BAHAN BANGUNAN | F20: GIANT Mortar 385 40 Kg | H20: 2 | J20: 2 | L20: SAK | P20: 199430 | R20: SO.GM.2026.06.00110 | T20: 46192 | V20: Bangunan Baru (Simp.Acai) | X20: 199430 | Z20: 199430 | AB20: net 42 | AD20: Avia Avian | AF20: SALES014 | AH20: Processed | AJ20: 0
B21: AGEM020KP302 | D21: DIVISI 2 CAT | F21: ARIES GOLD Emulsion 302 18 Kg | H21: 2 | J21: 2 | L21: PL | N21: tolong antar pagi ini | P21: 743944.2 | R21: SO.AV.2026.06.00712 | T21: 46186 | V21: Cahaya Bangunan (Niaso) | X21: 743944.2 | Z21: 743944.2 | AB21: net 42 | AD21: Avia Avian | AF21: SALES007 | AH21: Processed | AJ21: 0
B22: NODR004K009 | D22: DIVISI 2 CAT | F22: NO DROP 009 4 Kg | H22: 2 | J22: 2 | L22: KL | N22: bb bri Serempak TW | P22: 574610 | R22: SO.AV.2026.06.00895 | T22: 46190 | V22: Bintang Baru/Bintang Baru Jaya | X22: 574610 | Z22: 574610 | AB22: net 42 | AD22: Avia Avian | AF22: SALES004 | AH22: Processed | AJ22: 0
B23: BOVE500CS615 | D23: DIVISI 1 CAT | F23: BOYO Politur Vernis S 615 0.5 Lt | H23: 3 | J23: 3 | L23: KL | P23: 160395 | R23: SO.AV.2026.06.00710 | T23: 46186 | V23: CITRA BANGUNAN | X23: 664335 | Z23: 664335 | AB23: net 42 | AD23: Avia Avian | AF23: SALES007 | AH23: Processed | AJ23: 0
B24: NODR001K019 | D24: DIVISI 2 CAT | F24: NO DROP 019 1 Kg | H24: 2 | J24: 2 | L24: KL | P24: 152070 | R24: SO.AV.2026.06.00778 | T24: 46188 | V24: Jambi Jaya | X24: 608280 | Z24: 608280 | AB24: net 42 | AD24: Avia Avian | AF24: SALES003 | AH24: Processed | AJ24: 0
B26: ACCURATE Accounting System Report
B28: Printed on 24 June 2026 - 13:22
B29: Page Break 1 | AK29: of 49
B30: CV. ATLAS MITRA BERLIAN
B31: Rincian Pesanan Penjualan
B32: From 13 Jun 2026 until 20 Jun 2026
B33: Branch : Kantor Pusat, Filtered by : Status Pesanan Penjualan
B34: Kode # | D34: Kategori | F34: Nama Barang | H34: Kuantitas | J34: Kts (Unit#1) | L34: Nama Satuan | N34: Keterangan Pesanan Penjualan | P34: Total Harga | R34: Nomor # | T34: Tanggal | V34: Pelanggan | X34: Sub Total | Z34: Total | AB34: Nama Syarat Pembayaran Pesanan Penjualan | AD34: Nama Departemen | AF34: Nama Tenaga Penjual | AH34: Status Pesanan Penjualan | AJ34: Diskon Pesanan Penjualan
B35: NODR001K032 | D35: DIVISI 2 CAT | F35: NO DROP 032 1 Kg | H35: 2 | J35: 2 | L35: KL | P35: 152070 | R35: SO.AV.2026.06.00778 | T35: 46188 | V35: Jambi Jaya | X35: 608280 | Z35: 608280 | AB35: net 42 | AD35: Avia Avian | AF35: SALES003 | AH35: Processed | AJ35: 0
B36: NODR001K002 | D36: DIVISI 2 CAT | F36: NO DROP 002 1 Kg | H36: 2 | J36: 2 | L36: KL | P36: 152070 | R36: SO.AV.2026.06.00778 | T36: 46188 | V36: Jambi Jaya | X36: 608280 | Z36: 608280 | AB36: net 42 | AD36: Avia Avian | AF36: SALES003 | AH36: Processed | AJ36: 0
B37: NODR001K025 | D37: DIVISI 2 CAT | F37: NO DROP 025 1 Kg | H37: 2 | J37: 2 | L37: KL | P37: 152070 | R37: SO.AV.2026.06.00778 | T37: 46188 | V37: Jambi Jaya | X37: 608280 | Z37: 608280 | AB37: net 42 | AD37: Avia Avian | AF37: SALES003 | AH37: Processed | AJ37: 0
B38: AREM005K690 | D38: DIVISI 1 CAT - AREM | F38: ARIES Emulsion 690 5 Kg | H38: 1 | J38: 4 | L38: DS | N38: 116 | P38: 283790 | R38: SO.GM.2026.06.00120 | T38: 46193 | V38: Jaya ( Tungkal ) | X38: 851370 | Z38: 851370 | AB38: net 42 | AD38: Avia Avian | AF38: Jhondry Ferdians | AH38: Processed | AJ38: 0
B39: AREM005K691 | D39: DIVISI 1 CAT - AREM | F39: ARIES Emulsion 691 5 Kg | H39: 1 | J39: 4 | L39: DS | N39: 116 | P39: 283790 | R39: SO.GM.2026.06.00120 | T39: 46193 | V39: Jaya ( Tungkal ) | X39: 851370 | Z39: 851370 | AB39: net 42 | AD39: Avia Avian | AF39: Jhondry Ferdians | AH39: Processed | AJ39: 0
B40: AREM005K694 | D40: DIVISI 1 CAT - AREM | F40: ARIES Emulsion 694 5 Kg | H40: 1 | J40: 4 | L40: DS | N40: 116 | P40: 283790 | R40: SO.GM.2026.06.00120 | T40: 46193 | V40: Jaya ( Tungkal ) | X40: 851370 | Z40: 851370 | AB40: net 42 | AD40: Avia Avian | AF40: Jhondry Ferdians | AH40: Processed | AJ40: 0
B41: NODR001K009 | D41: DIVISI 2 CAT | F41: NO DROP 009 1 Kg | H41: 12 | J41: 12 | L41: KL | P41: 912420 | R41: SO.AV.2026.06.00867 | T41: 46189 | V41: KBS (Karya Baru Sejati SPA) | X41: 912420 | Z41: 912420 | AB41: net 42 | AD41: Avia Avian | AF41: SALES019 | AH41: Processed | AJ41: 0
B42: AVGO005KSW | D42: DIVISI 1 CAT | F42: AVITEX GOLD Emulsion SW 5 Kg | H42: 4 | J42: 4 | L42: KL | N42: urgent | P42: 858030 | R42: SO.AV.2026.06.00781 | T42: 46188 | V42: Dewi Eka Jaya Abadi | X42: 858030 | Z42: 858030 | AB42: net 42 | AD42: Avia Avian | AF42: SALES003 | AH42: Processed | AJ42: 0
B43: ACSY001K72 | D43: DIVISI 2 CAT | F43: AVIAN Cling Synthetic 72 0,85L | H43: 12 | J43: 12 | L43: KL | P43: 809190 | R43: SO.AV.2026.06.00841 | T43: 46189 | V43: Permata Jaya Bangunan (Singkut) | X43: 2427570 | Z43: 2427570 | AB43: net 42 | AD43: Avia Avian | AF43: SALES008 | AH43: Processed | AJ43: 0
B44: ACSY001K16 | D44: DIVISI 2 CAT | F44: AVIAN Cling Synthetic 16 0,85L | H44: 12 | J44: 12 | L44: KL | P44: 809190 | R44: SO.AV.2026.06.00841 | T44: 46189 | V44: Permata Jaya Bangunan (Singkut) | X44: 2427570 | Z44: 2427570 | AB44: net 42 | AD44: Avia Avian | AF44: SALES008 | AH44: Processed | AJ44: 0
B45: AVSY001K192 | D45: DIVISI 1 CAT | F45: AVIAN Synthetic 192 0.9 Lt | H45: 6 | J45: 6 | L45: KL | N45: 108 | P45: 553890 | R45: SO.AV.2026.06.00817 | T45: 46188 | V45: Nanda Bangunan Jaya | X45: 4431120 | Z45: 4431120 | AB45: net 42 | AD45: Avia Avian | AF45: SALES009 | AH45: Processed | AJ45: 0
B46: AVEM005KSW | D46: DIVISI 1 CAT | F46: AVITEX Emulsion SW 5 Kg | H46: 4 | J46: 4 | L46: KL | N46: 110 | P46: 687090 | R46: SO.AV.2026.06.00843 | T46: 46189 | V46: Rezeki TB | X46: 687090 | Z46: 687090 | AB46: net 42 | AD46: Avia Avian | AF46: SALES003 | AH46: Processed | AJ46: 0
B47: AVGO025KP700 | D47: DIVISI 1 CAT | F47: AVITEX GOLD Emulsion 700 25 Kg | H47: 1 | J47: 1 | L47: PL | P47: 1020737.5 | R47: SO.AV.2026.06.01038 | T47: 46192 | V47: Anto Jaya | X47: 3062212.5 | Z47: 3062212.5 | AB47: net 42 | AD47: Avia Avian | AF47: SALES001 | AH47: Processed | AJ47: 0
B48: AVGO025KP745 | D48: DIVISI 1 CAT | F48: AVITEX GOLD Emulsion 745 25 Kg | H48: 2 | J48: 2 | L48: PL | P48: 2041475 | R48: SO.AV.2026.06.01038 | T48: 46192 | V48: Anto Jaya | X48: 3062212.5 | Z48: 3062212.5 | AB48: net 42 | AD48: Avia Avian | AF48: SALES001 | AH48: Processed | AJ48: 0
B49: NODR004K024 | D49: DIVISI 2 CAT | F49: NO DROP 024 4 Kg | H49: 1 | J49: 4 | L49: DS | N49: bungo kincai | P49: 1149220 | R49: SO.AV.2026.06.00964 | T49: 46191 | V49: Putra jaya | X49: 2769820 | Z49: 2769820 | AB49: net 42 | AD49: Avia Avian | AF49: SALES010 | AH49: Processed | AJ49: 0
B50: BOVE500CS603 | D50: DIVISI 1 CAT | F50: BOYO Politur Vernis S603 0.5 Lt | H50: 3 | J50: 3 | L50: KL | P50: 160395 | R50: SO.AV.2026.06.00888 | T50: 46190 | V50: Tony Jaya (Bagan Pete) | X50: 160395 | Z50: 160395 | AB50: net 42 | AD50: Avia Avian | AF50: SALES001 | AH50: Processed | AJ50: 0
B51: ABEM005K707 | D51: DIVISI 1 CAT | F51: Aries Bling Emulsion 707 4,5 Kg | H51: 2 | J51: 2 | L51: KL | N51: srempak tw | P51: 183150 | R51: SO.AV.2026.06.00771 | T51: 46188 | V51: Anto Jaya | X51: 366300 | Z51: 366300 | AB51: net 42 | AD51: Avia Avian | AF51: SALES001 | AH51: Processed | AJ51: 0
B52: ABEM005K723 | D52: DIVISI 1 CAT | F52: Aries Bling Emulsion 723 4,5 Kg | H52: 2 | J52: 2 | L52: KL | N52: srempak tw | P52: 183150 | R52: SO.AV.2026.06.00771 | T52: 46188 | V52: Anto Jaya | X52: 366300 | Z52: 366300 | AB52: net 42 | AD52: Avia Avian | AF52: SALES001 | AH52: Processed | AJ52: 0
